Workbook

Sheet Top 200 COs
A1: MBN Selected? | B1: Selected? | C1: CLLI | D1: Site_Number | E1: Land_Ownership | F1: Asset_Type | G1: Primary_Use | H1: Secondary_Use | I1: LAT | J1: LONG | K1: Address | L1: City | M1: State | N1: Lease_ID | O1: REIT_ID | P1: Ownership | Q1: Entity_Name | R1: ABS_Category | S1: KOIOS - BSM 2025 | T1: KOIOS - UTILITIES 2025 | U1: KOIOS - BSM 2026 | V1: KOIOS - UTILITIES 2026 | W1: Square Ft-Interior | X1: Rack Count | Y1: KIN COPPER_SUBS | Z1: KIN FIBER_SUBS | AA1: KIN TOTAL_SUBS | AB1: Drop MRR | AC1: Drop MRR (Non OM) | AD1: Pass Through MRR | AE1: Drop MRR Total | AF1: COLO_MRR | AG1: Overall MRR Total | AH1: Min LEASE_ID - ExecutionDate | AI1: Site Photo Link | AJ1: Site Photo Link
C2: ABRDNCXA | D2: WNS1899 | E2: Owned | F2: Building | G2: Central Office | I2: 35.13472 | J2: -79.426783 | K2: 211 North Poplar Street | L2: Aberdeen | M2: NC | N2: ON017-NC-003 | O2: 204 | P2: REIT_ILEC | Q2: Windstream North Carolina| LLC | R2: ABS 2 | S2: 34426.06 | T2: 17596.95 | U2: 9988.85 | V2: 4668.77 | W2: 3604 | X2: 27 | Y2: 244 | Z2: 682 | AA2: 926 | AB2: 1470 | AC2: 14248.52 | AD2: 4304.8 | AE2: 15718.52 | AF2: 0 | AG2: 15718.52 | AI2: https://www.sitefotos.com/vpics/guestmapdev?w7t7y6 | AJ2: =HYPERLINK(AI2,"LINK") -> LINK
C3: ADELGAXA | D3: WNS1464 | E3: Owned | F3: Building | G3: Central Office | I3: 31.137892 | J3: -83.422447 | K3: 106 North Parrish Avenue | L3: Adel | M3: GA | N3: ON042-GA-002 | O3: 2354 | P3: REIT_ILEC | Q3: Windstream Georgia Communications| LLC | R3: ABS 1 | S3: 21133.02 | T3: 36863.82 | U3: 8916.16 | V3: 2275.09 | W3: 3331 | X3: 27 | Y3: 205 | Z3: 1371 | AA3: 1576 | AB3: 7641.5 | AC3: 11048.81 | AD3: 2320 | AE3: 18690.31 | AF3: 0 | AG3: 18690.31 | AH3: 42881 | AI3: https://sitefotos.com/vpics/guestmapdev?t8c7i4 | AJ3: =HYPERLINK(AI3,"LINK") -> LINK
C4: ANWOIAXO | D4: WNS0433 | E4: Owned | F4: Building | G4: Central Office | I4: 41.289147 | J4: -91.555145 | K4: 240 5th Street | L4: Ainsworth | M4: IA | N4: ON132-IA-1004 | O4: 3053 | P4: REIT_ILEC | Q4: Windstream Iowa Communications| Inc. | R4: ABS 2 | S4: 0 | T4: 0 | U4: 0 | V4: 0 | W4: 10084 | X4: 8 | Y4: 64 | Z4: 67 | AA4: 131 | AB4: 565 | AC4: 10064.1 | AD4: 19832.4 | AE4: 10629.1 | AF4: 0 | AG4: 10629.1 | AJ4: =HYPERLINK(AI4,"LINK") -> LINK
C5: ALCHFL01 | D5: WNS1425 | E5: Owned | F5: Building | G5: Central Office | H5: Warehouse | I5: 29.802351 | J5: -82.492208 | K5: 13715 West County Road 235 | L5: Alachua | M5: FL | N5: B047051 | O5: 2334 | P5: REIT_ILEC | Q5: Windstream Florida| Inc. | R5: ABS 2 | S5: 0 | T5: 0 | U5: 0 | V5: 0 | W5: 10685 | X5: 4 | Y5: 0 | Z5: 0 | AA5: 0 | AB5: 0 | AC5: 0 | AD5: 0 | AE5: 0 | AF5: 0 | AG5: 0 | AI5: https://www.google.com/maps/place/29%C2%B048'08.1%22N+82%C2%B029'32.7%22W/@29.8022512,-82.4930604,236m/data=!3m2!1e3!4b1!4m4!3m3!8m2!3d29.80225!4d-82.4924167?entry=ttu&amp;g_ep=EgoyMDI2MDIyNC4wIKXMDSoASAFQAw%3D%3D">Google Maps</a> | AJ5: =HYPERLINK(AI5,"LINK") -> LINK
C6: ALCHFLAJ | E6: Owned | F6: Building | G6: Central Office | I6: 29.789387 | J6: -82.495896 | K6: 14600 Main Street | L6: Alachua | M6: FL | N6: ON047-FL-1002 | O6: 2335 | P6: REIT_ILEC | Q6: Windstream Florida| Inc. | R6: ABS 2 | S6: 0 | T6: 0 | U6: 0 | V6: 0 | W6: 10685 | X6: #N/A | Y6: #N/A | Z6: #N/A | AA6: #N/A | AB6: #N/A | AC6: #N/A | AD6: #N/A | AE6: #N/A | AF6: #N/A | AG6: #N/A | AI6: https://www.google.com/maps/place/29%C2%B048'08.1%22N+82%C2%B029'32.7%22W/@29.8022512,-82.4930604,236m/data=!3m2!1e3!4b1!4m4!3m3!8m2!3d29.80225!4d-82.4924167?entry=ttu&amp;g_ep=EgoyMDI2MDIyNC4wIKXMDSoASAFQAw%3D%3D">Google Maps</a> | AJ6: =HYPERLINK(AI6,"LINK") -> LINK
C7: ALCHFLXA | D7: WNS1426 | E7: Owned | F7: Building | G7: Central Office | I7: 29.7894 | J7: -82.4962 | K7: 14600 Main St | L7: Alachua | M7: FL | N7: ON047-FL-003 | P7: WIN_ILEC | Q7: Windstream Florida| Inc. | R7: ABS 2 | S7: 46914.99 | T7: 21147.61 | U7: 6951.12 | V7: 14497.16 | W7: 3786 | X7: 32 | Y7: 385 | Z7: 769 | AA7: 1154 | AB7: 9195.43 | AC7: 14725.04 | AD7: 31318.52 | AE7: 23920.47 | AF7: 0 | AG7: 23920.47 | AH7: 43282 | AI7: https://www.google.com/maps/place/29%C2%B047'21.9%22N+82%C2%B029'45.1%22W/@29.7894179,-82.4965048,236m/data=!3m2!1e3!4b1!4m4!3m3!8m2!3d29.7894167!4d-82.4958611?entry=ttu&amp;g_ep=EgoyMDI2MDIyNC4wIKXMDSoASAFQAw%3D%3D">Google Maps</a> | AJ7: =HYPERLINK(AI7,"LINK") -> LINK
C8: ALBYKYXA | D8: WNS1699 | E8: Owned | F8: Building | G8: Central Office | I8: 36.693022 | J8: -85.134498 | K8: 400 N Washington | L8: Albany | M8: KY | N8: ON219-KY-001 | P8: WIN_ILEC | Q8: Windstream Kentucky East| LLC | R8: ABS 1 | S8: 12426.38 | T8: 39268.07 | U8: 845.98 | V8: 14894.06 | W8: 3680 | X8: 38 | Y8: 353 | Z8: 610 | AA8: 963 | AB8: 1940 | AC8: 21598.18 | AD8: 32660.33 | AE8: 23538.18 | AF8: 0 | AG8: 23538.18 | AI8: https://www.sitefotos.com/vpics/guestmapdev?h7c8f3 | AJ8: =HYPERLINK(AI8,"LINK") -> LINK
C9: ALBMNCXA | D9: WNS1901 | E9: Owned | F9: Building | G9: Central Office | H9: Tower | I9: 35.354042 | J9: -80.199092 | K9: 250 North 1st Street | L9: Albemarle | M9: NC | N9: B018200 | O9: 2508 | P9: REIT_ILEC | Q9: Windstream Concord Telephone| LLC | R9: ABS 2 | S9: 34465.89 | T9: 57466.96 | U9: 8877.62 | V9: 2845.28 | W9: 8000 | X9: 55 | Y9: 617 | Z9: 1991 | AA9: 2608 | AB9: 12968.9 | AC9: 17608.62 | AD9: 6325.38 | AE9: 30577.52 | AF9: 0 | AG9: 30577.52 | AH9: 41883 | AI9: https://www.sitefotos.com/vpics/guestmapdev?l2v3o8 | AJ9: =HYPERLINK(AI9,"LINK") -> LINK
C10: ALBIIAXO | D10: WNS0435 | E10: Owned | F10: Building | G10: Central Office | I10: 41.025959 | J10: -92.805646 | K10: 202 Washington Avenue E | L10: Albia | M10: IA | N10: ON132-IA-1009 | O10: 1643 | P10: REIT_ILEC | Q10: Windstream Iowa Communications| Inc. | R10: ABS 2 | S10: 4611.78 | T10: 8454.1 | U10: 1202.44 | V10: 2008.76 | W10: 4650 | X10: 13 | Y10: 469 | Z10: 269 | AA10: 738 | AB10: 860.5 | AC10: 6964.3 | AD10: 6047.8 | AE10: 7824.8 | AF10: 21 | AG10: 7845.8 | AI10: https://www.sitefotos.com/vpics/guestmapdev?c3k1y8 | AJ10: =HYPERLINK(AI10,"LINK") -> LINK
C11: ANDRTXXA | D11: WNS2514 | E11: Owned | F11: Building | G11: Central Office | I11: 32.317614 | J11: -102.54772 | K11: 112 Southwest 1st | L11: Andrews | M11: TX | N11: ON400-TX-012 | O11: 2824 | P11: REIT_ILEC | Q11: Valor Telecommunications of Texas| LLC | R11: ABS 1 | S11: 54750.84 | T11: 33972.51 | U11: 17661.46 | V11: 10902.59 | W11: 7280 | X11: 46 | Y11: 434 | Z11: 2113 | AA11: 2547 | AB11: 6552.65 | AC11: 15910.17 | AD11: 89613.87 | AE11: 22462.82 | AF11: 0 | AG11: 22462.82 | AI11: https://www.sitefotos.com/vpics/guestmapdev?r3x0w5 | AJ11: =HYPERLINK(AI11,"LINK") -> LINK
B12: Yes: 12k sqft + Owned | C12: ASLDKYXA | D12: WNS1701 | E12: Owned | F12: Building | G12: Central Office | I12: 38.4758 | J12: -82.64385 | K12: 619 15th Street | L12: Ashland | M12: KY | N12: B2193221111 | O12: 3469 | P12: REIT_ILEC | Q12: Windstream Kentucky East| LLC | R12: ABS 1 | S12: 80399.73 | T12: 247287.21 | U12: 15495.96 | V12: 97031.63 | W12: 34184 | X12: 232 | Y12: 223 | Z12: 1165 | AA12: 1388 | AB12: 23231.37 | AC12: 120711.48 | AD12: 101921.69 | AE12: 143942.85 | AF12: 0 | AG12: 143942.85 | AH12: 42881 | AI12: https://www.sitefotos.com/vpics/guestmapdev?c2k3m2 | AJ12: =HYPERLINK(AI12,"LINK") -> LINK
B13: Yes: 12k sqft + Owned | C13: MEDSKYXA | D13: WNS1703 | E13: Owned | F13: Building | G13: Central Office | I13: 38.40965 | J13: -82.713032 | K13: 9216 Highway 60 | L13: Ashland | M13: KY | N13: ON216-KY-002 | P13: WIN_ILEC | Q13: Windstream Kentucky East| LLC | R13: ABS 1 | S13: 56902.92 | T13: 87147.61 | U13: 18735.57 | V13: 34174.83 | W13: 12209 | X13: 76 | Y13: 281 | Z13: 1025 | AA13: 1306 | AB13: 16039.46 | AC13: 39822.17 | AD13: 92545.24 | AE13: 55861.63 | AF13: 0 | AG13: 55861.63 | AI13: https://www.sitefotos.com/vpics/guestmapdev?r3f5f4 | AJ13: =HYPERLINK(AI13,"LINK") -> LINK
C14: ADBNIAXO | D14: WNS1601 | E14: Owned | F14: Building | G14: Central Office | I14: 41.721272 | J14: -94.929383 | K14: 620 LEROY | L14: Audubon | M14: IA | N14: ON132-IA-1023 | O14: 2381 | P14: REIT_ILEC | Q14: Windstream Iowa Communications| Inc. | R14: ABS 2 | S14: 15615.69 | T14: 14045 | U14: 2820.67 | V14: 3549.97 | W14: 3744 | X14: 30 | Y14: 250 | Z14: 434 | AA14: 684 | AB14: 2819 | AC14: 6105.57 | AD14: 7682.1 | AE14: 8924.57 | AF14: 0 | AG14: 8924.57 | AI14: https://www.sitefotos.com/vpics/guestmapdev?u7n0l8 | AJ14: =HYPERLINK(AI14,"LINK") -> LINK
C15: AURROHXA | D15: WNS2239 | E15: Owned | F15: Building | G15: Central Office | I15: 41.317158 | J15: -81.346599 | K15: 27 East Garfield Road | L15: Aurora | M15: OH | N15: ON080-OH-001 | O15: 135 | P15: REIT_ILEC | Q15: Windstream Western Reserve| Inc. | R15: ABS 1 | S15: 50923.85 | T15: 58199.56 | U15: 22396.81 | V15: 12206.46 | W15: 5726 | X15: 70 | Y15: 391 | Z15: 288 | AA15: 679 | AB15: 12890.14 | AC15: 13102.87 | AD15: 44705.6 | AE15: 25993.01 | AF15: 0 | AG15: 25993.01 | AI15: https://www.sitefotos.com/vpics/guestmapdev?g8w0j7 | AJ15: =HYPERLINK(AI15,"LINK") -> LINK
B16: Yes: 12k sqft + Owned | C16: BNBGOHXA | D16: WNS1052 | E16: Owned | F16: Building | G16: Central Office | I16: 41.385699 | J16: -81.340629 | K16: 8425 Baindridge Road | L16: Bainbridge | M16: OH | N16: ON080-OH-003 | O16: 2020 | P16: REIT_ILEC | Q16: Windstream Western Reserve| Inc. | R16: ABS 1 | S16: 31055.14 | T16: 57971.48 | U16: 12785.38 | V16: 19898.04 | W16: 14355 | X16: 64 | Y16: 285 | Z16: 474 | AA16: 759 | AB16: 1021 | AC16: 7569.59 | AD16: 18040.8 | AE16: 8590.59 | AF16: 0 | AG16: 8590.59 | AI16: https://www.google.com/maps/place/8425+Bainbridge+Rd,+Chagrin+Falls,+OH+44023/@41.385724,-81.3409919,102m/data=!3m1!1e3!4m12!1m5!3m4!2zNDHCsDIzJzA4LjYiTiA4McKwMjAnMjYuNCJX!8m2!3d41.38572!4d-81.34067!3m5!1s0x88311a7811e73ce9:0x8ae504c98819a4a0!8m2!3d41.3857038!4d-81.3406819!16s%2Fg%2F11b8v5dgqb?entry=ttu&amp;g_ep=EgoyMDI1MTAwNy4wIKXMDSoASAFQAw%3D%3D">Google Maps</a> | AJ16: https://www.google.com/maps/place/8425+Bainbridge+Rd,+Chagrin+Falls,+OH+44023/@41.385724,-81.3409919,102m/data=!3m1!1e3!4m12!1m5!3m4!2zNDHCsDIzJzA4LjYiTiA4McKwMjAnMjYuNCJX!8m2!3d41.38572!4d-81.34067!3m5!1s0x88311a7811e73ce9:0x8ae504c98819a4a0!8m2!3d41.3857038!4d-81.3406819!16s%2Fg%2F11b8v5dgqb?entry=ttu&amp;g_ep=EgoyMDI1MTAwNy4wIKXMDSoASAFQAw%3D%3D">Google Maps</a>
B17: Yes: 12k sqft + Owned | C17: CRNLGA01 | D17: WNS0048 | E17: Owned | F17: Building | G17: Central Office | I17: 34.497208 | J17: -83.549978 | K17: 2000 Communications Boulevard | L17: Baldwin | M17: GA | N17: B040009 | O17: 3405 | P17: REIT_ILEC | Q17: Windstream Standard| LLC | R17: ABS 2 | S17: 0 | T17: 131239.21 | U17: 0 | V17: 35861.89 | W17: 55823 | X17: 11 | Y17: 541 | Z17: 0 | AA17: 541 | AB17: 0 | AC17: 0 | AD17: 1299 | AE17: 0 | AF17: 0 | AG17: 0 | AH17: 31383 | AI17: https://sitefotos.com/vpics/guestmapdev?g4t5f6 | AJ17: =HYPERLINK(AI17,"LINK") -> LINK
C18: BBVLKYXA | D18: WNS1705 | E18: Owned | F18: Building | G18: Central Office | I18: 36.865334 | J18: -83.888273 | K18: 207 South Main Street | L18: Barbourville | M18: KY | N18: ON220-KY-003 | O18: 191 | P18: REIT_ILEC | Q18: Windstream Kentucky East| LLC | R18: ABS 2 | S18: 18265.79 | T18: 34171.06 | U18: 7969.43 | V18: 9965.19 | W18: 3855 | X18: 28 | Y18: 237 | Z18: 405 | AA18: 642 | AB18: 6749 | AC18: 14920.37 | AD18: 47332.4 | AE18: 21669.37 | AF18: 0 | AG18: 21669.37 | AH18: 42767 | AI18: https://www.sitefotos.com/vpics/guestmapdev?j0l6w3 | AJ18: =HYPERLINK(AI18,"LINK") -> LINK
C19: FRVWOHXA | D19: WNS2241 | E19: Owned | F19: Building | G19: Central Office | I19: 40.059497 | J19: -81.220419 | K19: 32699 Old National Road | L19: Barnesville | M19: OH | N19: ON080-OH-041 | O19: 792 | P19: REIT_ILEC | Q19: Windstream Western Reserve| Inc. | R19: ABS 1 | S19: 17118.82 | T19: 21141.46 | U19: 9412.8 | V19: 11989.69 | W19: 3022 | X19: 28 | Y19: 113 | Z19: 0 | AA19: 113 | AB19: 1450 | AC19: 6356.9 | AD19: 46411.56 | AE19: 7806.9 | AF19: 0 | AG19: 7806.9 | AH19: 42767 | AI19: https://www.sitefotos.com/vpics/guestmapdev?x4v1m2 | AJ19: =HYPERLINK(AI19,"LINK") -> LINK
B20: Yes - High Rack count | C20: BEREKYXA | D20: WNS1709 | E20: Owned | F20: Building | G20: Central Office | H20: Switch | I20: 37.573344 | J20: -84.285739 | K20: 310 Center Street | L20: Berea | M20: KY | N20: ON219-KY-003 | O20: 227 | P20: REIT_ILEC | Q20: Windstream Kentucky East| LLC | R20: ABS 1 | S20: 17800.04 | T20: 51712.55 | U20: 4044.87 | V20: 16119.02 | W20: 3242 | X20: 90 | Y20: 166 | Z20: 846 | AA20: 1012 | AB20: 15989.08 | AC20: 57335.17 | AD20: 59842.41 | AE20: 73324.25 | AF20: 0 | AG20: 73324.25 | AH20: 42881 | AI20: https://www.sitefotos.com/vpics/guestmapdev?q6e1d4 | AJ20: =HYPERLINK(AI20,"LINK") -> LINK
C21: SHBGKYAB | E21: Owned | F21: Building | G21: Central Office | H21: Switch | I21: 38.242606 | J21: -83.874479 | K21: 160 Old Highway 11 | L21: BETHEL | M21: KY | N21: ON219-KY-060 | O21: 1306 | P21: REIT_ILEC | Q21: Windstream Kentucky East| LLC | R21: ABS 1 | S21: 0 | T21: 0 | U21: 0 | V21: 0 | W21: 10084 | X21: 3 | Y21: 41 | Z21: 85 | AA21: 126 | AB21: 0 | AC21: 295 | AD21: 0 | AE21: 295 | AF21: 0 | AG21: 295 | AI21: https://www.google.com/maps/place/4949+Summer+Shade+Rd,+Summer+Shade,+KY+42166/@36.8759171,-85.6601021,3a,37.5y,191.64h,87.75t/data=!3m7!1e1!3m5!1svrYjBVqy23or2j3c9KfHwQ!2e0!6shttps:%2F%2Fstreetviewpixels-pa.googleapis.com%2Fv1%2Fthumbnail%3Fcb_client%3Dmaps_sv.tactile%26w%3D900%26h%3D600%26pitch%3D2.2512462931385926%26panoid%3DvrYjBVqy23or2j3c9KfHwQ%26yaw%3D191.63699463385655!7i16384!8i8192!4m6!3m5!1s0x8866358a744ec2cf:0xf0cf40749a9898c2!8m2!3d36.875317!4d-85.6604178!16s%2Fg%2F11gwmr6b4p?entry=ttu&amp;g_ep=EgoyMDI1MDkxNC4wIKXMDSoASAFQAw%3D%3D">Google Maps</a> | AJ21: https://www.google.com/maps/place/4949+Summer+Shade+Rd,+Summer+Shade,+KY+42166/@36.8759171,-85.6601021,3a,37.5y,191.64h,87.75t/data=!3m7!1e1!3m5!1svrYjBVqy23or2j3c9KfHwQ!2e0!6shttps:%2F%2Fstreetviewpixels-pa.googleapis.com%2Fv1%2Fthumbnail%3Fcb_client%3Dmaps_sv.tactile%26w%3D900%26h%3D600%26pitch%3D2.2512462931385926%26panoid%3DvrYjBVqy23or2j3c9KfHwQ%26yaw%3D191.63699463385655!7i16384!8i8192!4m6!3m5!1s0x8866358a744ec2cf:0xf0cf40749a9898c2!8m2!3d36.875317!4d-85.6604178!16s%2Fg%2F11gwmr6b4p?entry=ttu&amp;g_ep=EgoyMDI1MDkxNC4wIKXMDSoASAFQAw%3D%3D">Google Maps</a>
C22: BLVIGABW | D22: WNS3282 | E22: Owned | F22: Building | G22: Central Office | H22: Warehouse | I22: 34.864025 | J22: -83.984809 | K22: 40 River Road Connector | L22: Blairsville | M22: GA | N22: B040040 | O22: 3293 | P22: REIT_ILEC | Q22: Windstream Standard| LLC | R22: ABS 1 | S22: 22270.31 | T22: 9585.47 | U22: 4510 | V22: 3953.58 | W22: 5000 | X22: 2 | Y22: 0 | Z22: 0 | AA22: 0 | AB22: 0 | AC22: 0 | AD22: 0 | AE22: 0 | AF22: 0 | AG22: 0 | AI22: https://sitefotos.com/vpics/guestmapdev?w0s7t4 | AJ22: =HYPERLINK(AI22,"LINK") -> LINK
C23: BLKLGAXA | D23: WNS0261 | E23: Owned | F23: Building | G23: Central Office | I23: 31.38254 | J23: -84.957519 | K23: 15166 River St | L23: Blakely | M23: GA | N23: ON049-GA-1001 | O23: 2356 | P23: REIT_ILEC | Q23: Windstream Georgia Telephone | R23: ABS 1 | S23: 13697.58 | T23: 39609.5 | U23: 2991.03 | V23: 13508.58 | W23: 5652 | X23: 35 | Y23: 994 | Z23: 352 | AA23: 1346 | AB23: 5815.9 | AC23: 8504.4 | AD23: 34336.85 | AE23: 14320.3 | AF23: 0 | AG23: 14320.3 | AI23: https://sitefotos.com/vpics/guestmapdev?m8q5k5 | AJ23: =HYPERLINK(AI23,"LINK") -> LINK
C24: BRFRFLXA | E24: Owned | F24: Building | G24: Central Office | I24: 29.960083 | J24: -82.927998 | K24: 108 Drane St Nw| Branford| FL| 32008 | L24: Branford | M24: FL | N24: ON047-FL-001 | P24: WIN_ILEC | Q24: Windstream Florida| Inc. | R24: ABS 2 | S24: 0 | T24: 0 | U24: 0 | V24: 0 | W24: 10685 | X24: 20 | Y24: 307 | Z24: 149 | AA24: 456 | AB24: 7600 | AC24: 17521.53 | AD24: 36194.05 | AE24: 25121.53 | AF24: 0 | AG24: 25121.53 | AI24: https://www.google.com/maps/place/34%C2%B002'16.7%22N+94%C2%B020'31.6%22W/@34.0379733,-94.3427548,136m/data=!3m2!1e3!4b1!4m4!3m3!8m2!3d34.0379722!4d-94.3421111?entry=ttu&amp;g_ep=EgoyMDI2MDMwMS4xIKXMDSoASAFQAw%3D%3D">Google Maps</a> | AJ24: =HYPERLINK(AI24,"LINK") -> LINK
C25: BRHDKYXA | E25: Owned | F25: Building | G25: Central Office | I25: 37.341683 | J25: -84.449908 | K25: 4297 Highway 70 | L25: BRODHEAD | M25: KY | N25: ON220-KY-038 | O25: 3951 | P25: REIT_ILEC | Q25: Windstream Kentucky East| LLC | R25: ABS 2 | S25: 0 | T25: 0 | U25: 0 | V25: 0 | W25: 10084 | X25: 14 | Y25: 115 | Z25: 147 | AA25: 262 | AB25: 0 | AC25: 7379 | AD25: 0 | AE25: 7379 | AF25: 0 | AG25: 7379 | AI25: https://www.google.com/maps/place/4949+Summer+Shade+Rd,+Summer+Shade,+KY+42166/@36.8759171,-85.6601021,3a,37.5y,191.64h,87.75t/data=!3m7!1e1!3m5!1svrYjBVqy23or2j3c9KfHwQ!2e0!6shttps:%2F%2Fstreetviewpixels-pa.googleapis.com%2Fv1%2Fthumbnail%3Fcb_client%3Dmaps_sv.tactile%26w%3D900%26h%3D600%26pitch%3D2.2512462931385926%26panoid%3DvrYjBVqy23or2j3c9KfHwQ%26yaw%3D191.63699463385655!7i16384!8i8192!4m6!3m5!1s0x8866358a744ec2cf:0xf0cf40749a9898c2!8m2!3d36.875317!4d-85.6604178!16s%2Fg%2F11gwmr6b4p?entry=ttu&amp;g_ep=EgoyMDI1MDkxNC4wIKXMDSoASAFQAw%3D%3D">Google Maps</a> | AJ25: https://www.google.com/maps/place/4949+Summer+Shade+Rd,+Summer+Shade,+KY+42166/@36.8759171,-85.6601021,3a,37.5y,191.64h,87.75t/data=!3m7!1e1!3m5!1svrYjBVqy23or2j3c9KfHwQ!2e0!6shttps:%2F%2Fstreetviewpixels-pa.googleapis.com%2Fv1%2Fthumbnail%3Fcb_client%3Dmaps_sv.tactile%26w%3D900%26h%3D600%26pitch%3D2.2512462931385926%26panoid%3DvrYjBVqy23or2j3c9KfHwQ%26yaw%3D191.63699463385655!7i16384!8i8192!4m6!3m5!1s0x8866358a744ec2cf:0xf0cf40749a9898c2!8m2!3d36.875317!4d-85.6604178!16s%2Fg%2F11gwmr6b4p?entry=ttu&amp;g_ep=EgoyMDI1MDkxNC4wIKXMDSoASAFQAw%3D%3D">Google Maps</a>
B26: Yes: 12k sqft + Owned | C26: BRAROKXA | D26: WNS2324 | E26: Owned | F26: Building | G26: Central Office | H26: Switch | I26: 36.052614 | J26: -95.791826 | K26: 114 West Broadway | L26: Broken Arrow | M26: OK | N26: ON200-OK-005 | O26: 34 | P26: REIT_ILEC | Q26: Valor Telecommunications of Texas| LLC | R26: ABS 2 | S26: 42692.94 | T26: 104993.98 | U26: 18556.6 | V26: 34474.51 | W26: 17085 | X26: 150 | Y26: 526 | Z26: 1508 | AA26: 2034 | AB26: 14122.6 | AC26: 13377.91 | AD26: 45891.26 | AE26: 27500.51 | AF26: 1011.97 | AG26: 28512.48 | AI26: https://www.sitefotos.com/vpics/guestmapdev?p2x4k3 | AJ26: =HYPERLINK(AI26,"LINK") -> LINK
B27: Yes: 12k sqft + Owned | C27: BRAROKXC | D27: WNS2325 | E27: Owned | F27: Building | G27: Central Office | H27: Switch | I27: 35.998678 | J27: -95.796852 | K27: 5301 South Elm Place W | L27: Broken Arrow | M27: OK | N27: ON200-OK-007 | O27: 41 | P27: REIT_ILEC | Q27: Valor Telecommunications of Texas| LLC | R27: ABS 2 | S27: 91043.67 | T27: 89430.4 | U27: 26395.93 | V27: 28858.43 | W27: 14330 | X27: 109 | Y27: 532 | Z27: 362 | AA27: 894 | AB27: 12002.37 | AC27: 3547.06 | AD27: 39317.23 | AE27: 15549.43 | AF27: 0 | AG27: 15549.43 | AI27: https://www.sitefotos.com/vpics/guestmapdev?w7d2n3 | AJ27: =HYPERLINK(AI27,"LINK") -> LINK
B28: Yes - High Rack count | C28: BRAROKXD | D28: WNS2327 | E28: Owned | F28: Building | G28: Central Office | H28: Switch | I28: 36.089602 | J28: -95.790558 | K28: 201 East Omaha Street | L28: Broken Arrow | M28: OK | N28: ON200-OK-009 | O28: 178 | P28: REIT_ILEC | Q28: Valor Telecommunications of Texas| LLC | R28: ABS 2 | S28: 38650.16 | T28: 47222.1 | U28: 2055.36 | V28: 21691.28 | W28: 4300 | X28: 106 | Y28: 396 | Z28: 404 | AA28: 800 | AB28: 13778.5 | AC28: 35254.89 | AD28: 35210.86 | AE28: 49033.39 | AF28: 0 | AG28: 49033.39 | AI28: https://www.sitefotos.com/vpics/guestmapdev?r2t1s4 | AJ28: =HYPERLINK(AI28,"LINK") -> LINK
C29: BRAROKXE | D29: WNS2326 | E29: Owned | F29: Building | G29: Central Office | H29: Switch | I29: 36.061524 | J29: -95.684298 | K29: 1025 North 84th Street | L29: Broken Arrow | M29: OK | N29: ON200-OK-008 | O29: 209 | P29: REIT_ILEC | Q29: Valor Telecommunications of Texas| LLC | R29: ABS 2 | S29: 15031.55 | T29: 40110.63 | U29: 1375.36 | V29: 18663.89 | W29: 3565 | X29: 38 | Y29: 255 | Z29: 457 | AA29: 712 | AB29: 2752.63 | AC29: 3798.56 | AD29: 40926.36 | AE29: 6551.19 | AF29: 0 | AG29: 6551.19 | AI29: https://www.sitefotos.com/vpics/guestmapdev?q8o0x5 | AJ29: =HYPERLINK(AI29,"LINK") -> LINK
C30: BKVLKYXA | D30: WNS1712 | E30: Owned | F30: Building | G30: Central Office | I30: 38.682502 | J30: -84.067487 | K30: 202 Madison St | L30: Brooksville | M30: KY | N30: ON220-KY-091 | P30: WIN_ILEC | Q30: Windstream Kentucky East| LLC | R30: ABS 1 | S30: 10535.54 | T30: 20537.39 | U30: 2580.34 | V30: 6646.59 | W30: 3062 | X30: 16 | Y30: 278 | Z30: 112 | AA30: 390 | AB30: 2080.92 | AC30: 13913.88 | AD30: 0 | AE30: 15994.8 | AF30: 0 | AG30: 15994.8 | AI30: https://www.sitefotos.com/vpics/guestmapdev?j4y4w6 | AJ30: =HYPERLINK(AI30,"LINK") -> LINK
B31: Yes: 12k sqft + Owned | C31: BWFDTXXA | E31: Owned | F31: Building | G31: Central Office | H31: Tower | I31: 33.17722 | J31: -102.27442 | K31: 101 East Tate | L31: Brownfield | M31: TX | N31: ON400-TX-1001 | O31: 2835 | P31: REIT_ILEC | R31: ABS 2 | S31: 0 | T31: 0 | U31: 0 | V31: 0 | W31: 12000 | X31: 93 | Y31: 291 | Z31: 714 | AA31: 1005 | AB31: 11734.8 | AC31: 39179.17 | AD31: 114449.47 | AE31: 50913.97 | AF31: 0 | AG31: 50913.97 | AH31: 42339 | AI31: https://www.sitefotos.com/vpics/guestmapdev?v4r7w8 | AJ31: =HYPERLINK(AI31,"LINK") -> LINK
C32: BRSDKYXA | D32: WNS1715 | E32: Owned | F32: Building | G32: Central Office | I32: 36.989789 | J32: -84.599373 | K32: 53 E French Ave 03 | L32: BURNSIDE | M32: KY | N32: ON219-KY-007 | O32: 182 | P32: REIT_ILEC | Q32: Windstream Kentucky East| LLC | R32: ABS 2 | S32: 17561.21 | T32: 45983.2 | U32: 2415.46 | V32: 18602.01 | W32: 4096 | X32: 41 | Y32: 131 | Z32: 534 | AA32: 665 | AB32: 0 | AC32: 12671.67 | AD32: 35664.33 | AE32: 12671.67 | AF32: 0 | AG32: 12671.67 | AI32: https://www.sitefotos.com/vpics/guestmapdev?m6f5w8 | AJ32: =HYPERLINK(AI32,"LINK") -> LINK
C33: CAIRGAXA | D33: WNS1480 | E33: Owned | F33: Building | G33: Central Office | H33: Switch | I33: 30.878532 | J33: -84.208973 | K33: 48 2nd Avenue | L33: Cairo | M33: GA | N33: ON041-GA-023 | O33: 238 | P33: REIT_ILEC | Q33: Windstream Georgia| LLC | R33: ABS 2 | S33: 18938.69 | T33: 61805.1 | U33: 3843.93 | V33: 23790.79 | W33: 3592 | X33: 37 | Y33: 425 | Z33: 1243 | AA33: 1668 | AB33: 8770.4 | AC33: 15857.7 | AD33: 29131.83 | AE33: 24628.1 | AF33: 0 | AG33: 24628.1 | AI33: https://sitefotos.com/vpics/guestmapdev?a6c5j7 | AJ33: =HYPERLINK(AI33,"LINK") -> LINK
C34: CLHNFLXA | D34: WNS1430 | E34: Owned | F34: Building | G34: Central Office | I34: 30.564356 | J34: -81.831421 | K34: 45403 Green Avenue | L34: Callahan | M34: FL | N34: ON047-FL-010 | O34: 2338 | P34: REIT_ILEC | Q34: Windstream Florida| Inc. | R34: ABS 2 | S34: 19452.03 | T34: 32431.16 | U34: 4816.32 | V34: 11011.12 | W34: 4560 | X34: 44 | Y34: 191 | Z34: 841 | AA34: 1032 | AB34: 4654.75 | AC34: 41608.82 | AD34: 14391 | AE34: 46263.57 | AF34: 0 | AG34: 46263.57 | AI34: https://www.google.com/maps/place/30%C2%B033'51.7%22N+81%C2%B049'53.1%22W/@30.5643623,-81.8320604,234m/data=!3m2!1e3!4b1!4m4!3m3!8m2!3d30.5643611!4d-81.8314167?entry=ttu&amp;g_ep=EgoyMDI2MDIyNC4wIKXMDSoASAFQAw%3D%3D">Google Maps</a> | AJ34: =HYPERLINK(AI34,"LINK") -> LINK
B35: Yes - High Rack count | C35: CMVLKYXA | D35: WNS1718 | E35: Owned | F35: Building | G35: Central Office | I35: 37.342599 | J35: -85.343916 | K35: 303 E Broadway | L35: Campbellsville | M35: KY | N35: ON219-KY-008 | P35: WIN_ILEC | Q35: Windstream Kentucky East| LLC | R35: ABS 2 | S35: 22230.25 | T35: 58783.53 | U35: 8095.15 | V35: 21965.42 | W35: 8877 | X35: 85 | Y35: 471 | Z35: 2243 | AA35: 2714 | AB35: 12345.65 | AC35: 70247.22 | AD35: 23338.55 | AE35: 82592.87 | AF35: 0 | AG35: 82592.87 | AH35: 42881 | AI35: https://www.google.com/maps/place/37%C2%B020'33.3%22N+85%C2%B020'38.1%22W/@37.3425844,-85.3445604,216m/data=!3m1!1e3!4m4!3m3!8m2!3d37.3425833!4d-85.3439167?entry=ttu&amp;g_ep=EgoyMDI1MTExNy4wIKXMDSoASAFQAw%3D%3D">Google Maps</a> | AJ35: =HYPERLINK(AI35,"LINK") -> LINK
B36: Yes - High Rack count | C36: CNTNGAXA | D36: WNS1482 | E36: Owned | F36: Building | G36: Central Office | I36: 34.23611 | J36: -84.490655 | K36: 190 South Church Street | L36: Canton | M36: GA | N36: ON042-GA-105 | O36: 106 | P36: REIT_ILEC | Q36: Windstream Georgia Communications| LLC | R36: ABS 1 | S36: 30559.41 | T36: 126734.91 | U36: 11829.91 | V36: 41202.68 | W36: 7075 | X36: 81 | Y36: 602 | Z36: 368 | AA36: 970 | AB36: 30521.33 | AC36: 44090.74 | AD36: 38562.74 | AE36: 74612.07 | AF36: 0 | AG36: 74612.07 | AH36: 43137 | AI36: https://www.google.com/maps/place/Kinetic+Fiber+Internet+-+Canton+GA/@34.2301179,-84.4892039,112m/data=!3m1!1e3!4m15!1m8!3m7!1s0x88f565bbe68ef9af:0xbf14ffe07e1ed3ad!2s206+Longview+St,+Canton,+GA+30114!3b1!8m2!3d34.2301135!4d-84.488882!16s%2Fg%2F11l0nhqjn7!3m5!1s0x88f6c7e1263eea59:0x4040cd808668f9ea!8m2!3d34.2300248!4d-84.4881739!16s%2Fg%2F1vc6f7d_?entry=ttu&amp;g_ep=EgoyMDI1MTExNy4wIKXMDSoASAFQAw%3D%3D">Google Maps</a> | AJ36: https://www.google.com/maps/place/Kinetic+Fiber+Internet+-+Canton+GA/@34.2301179,-84.4892039,112m/data=!3m1!1e3!4m15!1m8!3m7!1s0x88f565bbe68ef9af:0xbf14ffe07e1ed3ad!2s206+Longview+St,+Canton,+GA+30114!3b1!8m2!3d34.2301135!4d-84.488882!16s%2Fg%2F11l0nhqjn7!3m5!1s0x88f6c7e1263eea59:0x4040cd808668f9ea!8m2!3d34.2300248!4d-84.4881739!16s%2Fg%2F1vc6f7d_?entry=ttu&amp;g_ep=EgoyMDI1MTExNy4wIKXMDSoASAFQAw%3D%3D">Google Maps</a>
C37: CECLOHXA | D37: WNS2243 | E37: Owned | F37: Building | G37: Central Office | I37: 41.218146 | J37: -84.602126 | K37: 105 North Main Street | L37: CECIL | M37: OH | N37: ON158-OH-020 | O37: 2658 | P37: REIT_ILEC | Q37: Windstream Ohio| LLC | R37: ABS 2 | S37: 1685.44 | T37: 3350.59 | U37: 360.8 | V37: 2687.74 | W37: 4994 | X37: 5 | Y37: 48 | Z37: 0 | AA37: 48 | AB37: 0 | AC37: 0 | AD37: 0 | AE37: 0 | AF37: 0 | AG37: 0 | AI37: https://www.google.com/maps/place/41%C2%B013'05.3%22N+84%C2%B036'07.7%22W/@41.218151,-84.6027937,124m/data=!3m2!1e3!4b1!4m4!3m3!8m2!3d41.21815!4d-84.60215?entry=ttu&amp;g_ep=EgoyMDI1MTEyMy4xIKXMDSoASAFQAw%3D%3D">Google Maps</a> | AJ37: =HYPERLINK(AI37,"LINK") -> LINK
C38: CNVLIAXO | D38: WNS0461 | E38: Owned | F38: Building | G38: Central Office | I38: 40.732267 | J38: -92.876119 | K38: 236 West Maple Street | L38: Centerville | M38: IA | N38: ON132-IA-1064 | O38: 1659 | P38: REIT_ILEC | Q38: Windstream Iowa Communications| Inc. | R38: ABS 2 | S38: 13556.16 | T38: 35810.56 | U38: 3065.11 | V38: 12367.51 | W38: 9042 | X38: 19 | Y38: 422 | Z38: 557 | AA38: 979 | AB38: 1857 | AC38: 7733.11 | AD38: 3834.8 | AE38: 9590.11 | AF38: 0 | AG38: 9590.11 | AI38: https://www.sitefotos.com/vpics/guestmapdev?e6u3n8 | AJ38: =HYPERLINK(AI38,"LINK") -> LINK
C39: CNVLGAXA | D39: WNS1487 | E39: Owned | F39: Building | G39: Central Office | H39: Switch | I39: 32.623499 | J39: -83.687999 | K39: 109 Gunn Road | L39: Centerville | M39: GA | N39: ON041-GA-006 | O39: 252 | P39: REIT_ILEC | Q39: Windstream Georgia| LLC | R39: ABS 2 | S39: 8895.33 | T39: 23424.35 | U39: 1180.62 | V39: 5501.25 | W39: 2976 | X39: 23 | Y39: 261 | Z39: 190 | AA39: 451 | AB39: 14731.4 | AC39: 13827.45 | AD39: 11867.2 | AE39: 28558.85 | AF39: 0 | AG39: 28558.85 | AI39: https://sitefotos.com/vpics/guestmapdev?b2k2p1 | AJ39: =HYPERLINK(AI39,"LINK") -> LINK
B40: Yes: 12k sqft + Owned | C40: CHRDOHXA | D40: WNS2244 | E40: Owned | F40: Building | G40: Central Office | I40: 41.581285 | J40: -81.202133 | K40: 205 South Hambden Street | L40: Chardon | M40: OH | N40: ON080-OH-044 | O40: 2659 | P40: REIT_ILEC | Q40: Windstream Western Reserve| Inc. | R40: ABS 1 | S40: 82937.03 | T40: 102360.37 | U40: 30699.82 | V40: 32185.13 | W40: 12446 | X40: 100 | Y40: 647 | Z40: 575 | AA40: 1222 | AB40: 4888.4 | AC40: 90111.32 | AD40: 14874.4 | AE40: 94999.72 | AF40: 0 | AG40: 94999.72 | AI40: https://www.sitefotos.com/vpics/guestmapdev?k0u2x5 | AJ40: =HYPERLINK(AI40,"LINK") -> LINK
C41: CHRTIAXC | D41: WNS1606 | E41: Owned | F41: Building | G41: Central Office | I41: 41.016249 | J41: -93.306426 | K41: 220 North Grand Chariton | L41: Chariton | M41: IA | N41: ON132-IA-1068 | O41: 2384 | P41: REIT_ILEC | Q41: Windstream Iowa Communications| Inc. | R41: ABS 2 | S41: 25470.95 | T41: 34889.86 | U41: 3645.28 | V41: 12426.19 | W41: 7432 | X41: 32 | Y41: 515 | Z41: 602 | AA41: 1117 | AB41: 1515 | AC41: 4565.5 | AD41: 7252.3 | AE41: 6080.5 | AF41: 21 | AG41: 6101.5 | AI41: https://www.sitefotos.com/vpics/guestmapdev?o6h7v3 | AJ41: =HYPERLINK(AI41,"LINK") -> LINK
C42: CHWOGAXA | D42: WNS1488 | E42: Owned | F42: Building | G42: Central Office | I42: 34.768338 | J42: -84.768209 | K42: 220 North 2nd Avenue | L42: Chatsworth | M42: GA | N42: ON042-GA-095 | O42: 119 | P42: REIT_ILEC | Q42: Windstream Georgia Communications| LLC | R42: ABS 2 | S42: 22394.68 | T42: 98417.06 | U42: 5684.32 | V42: 31990.46 | W42: 6372 | X42: 40 | Y42: 472 | Z42: 410 | AA42: 882 | AB42: 16108.9 | AC42: 97744.11 | AD42: 13929.69 | AE42: 113853.01 | AF42: 0 | AG42: 113853.01 | AH42: 42881 | AI42: https://sitefotos.com/vpics/guestmapdev?e8r6u8 | AJ42: =HYPERLINK(AI42,"LINK") -> LINK
B43: Yes: 12k sqft + Owned | C43: CHTHOKXD | E43: Owned | F43: Building | G43: Central Office | I43: 35.470961 | J43: -95.523631 | K43: 115 Northwest 1st Street | L43: Checotah | M43: OK | N43: ON200-OK-010 | O43: 302 | P43: REIT_ILEC | Q43: Valor Telecommunications of Texas| LLC | R43: ABS 2 | S43: 0 | T43: 0 | U43: 0 | V43: 0 | W43: 20000 | X43: 21 | Y43: 290 | Z43: 499 | AA43: 789 | AB43: 3684 | AC43: 3256.33 | AD43: 1292 | AE43: 6940.33 | AF43: 0 | AG43: 6940.33 | AH43: 42339 | AI43: https://www.google.com/maps/place/130+Howell+Dr,+Elizabethtown,+KY+42701/@37.7137354,-85.8271202,860m/data=!3m2!1e3!4b1!4m6!3m5!1s0x8868ef14cb372ebf:0xa1909efe4828c1f5!8m2!3d37.7137312!4d-85.8245453!16s%2Fg%2F11bw4nx7h4?entry=ttu&amp;g_ep=EgoyMDI2MDIwNC4wIKXMDSoASAFQAw%3D%3D">Google Maps</a> | AJ43: https://www.google.com/maps/place/130+Howell+Dr,+Elizabethtown,+KY+42701/@37.7137354,-85.8271202,860m/data=!3m2!1e3!4b1!4m6!3m5!1s0x8868ef14cb372ebf:0xa1909efe4828c1f5!8m2!3d37.7137312!4d-85.8245453!16s%2Fg%2F11bw4nx7h4?entry=ttu&amp;g_ep=EgoyMDI2MDIwNC4wIKXMDSoASAFQAw%3D%3D">Google Maps</a>
B44: Yes: 12k sqft + Owned | C44: CHGVNCXA | D44: WNS1906 | E44: Owned | F44: Building | G44: Central Office | I44: 35.556922 | J44: -80.595882 | K44: 1525 South Main Street | L44: China Grove | M44: NC | N44: B018190 | O44: 2511 | P44: REIT_ILEC | Q44: Windstream Concord Telephone| LLC | R44: ABS 2 | S44: 16498.61 | T44: 24010.91 | U44: 17096.62 | V44: 7610.97 | W44: 12000 | X44: 38 | Y44: 184 | Z44: 1898 | AA44: 2082 | AB44: 6142 | AC44: 3830.7 | AD44: 85095.52 | AE44: 9972.7 | AF44: 0 | AG44: 9972.7 | AH44: 41883 | AI44: https://www.sitefotos.com/vpics/guestmapdev?n7j7q5 | AJ44: =HYPERLINK(AI44,"LINK") -> LINK
C45: CLRDIAXT | D45: WNS1607 | E45: Owned | F45: Building | G45: Central Office | I45: 40.740547 | J45: -95.038732 | K45: 115 West Chestnut Street | L45: Clarinda | M45: IA | N45: ON132-IA-1078 | O45: 2385 | P45: REIT_ILEC | Q45: Windstream Iowa Communications| Inc. | R45: ABS 2 | S45: 28867.2 | T45: 29670.45 | U45: 30897.21 | V45: 7907.12 | W45: 7280 | X45: 24 | Y45: 153 | Z45: 892 | AA45: 1045 | AB45: 992 | AC45: 1787.1 | AD45: 1058 | AE45: 2779.1 | AF45: 0 | AG45: 2779.1 | AI45: https://www.sitefotos.com/vpics/guestmapdev?s0n5g1 | AJ45: =HYPERLINK(AI45,"LINK") -> LINK
C46: CLVLGAXA | D46: WNS1489 | E46: Owned | F46: Building | G46: Central Office | I46: 34.614838 | J46: -83.524356 | K46: 390 Jefferson Street | L46: Clarkesville | M46: GA | N46: ON040-GA-020 | O46: 98 | P46: REIT_ILEC | Q46: Windstream Standard| LLC | R46: ABS 1 | S46: 6123.5 | T46: 42709.7 | U46: 14430.29 | V46: 13796.37 | W46: 7500 | X46: 25 | Y46: 670 | Z46: 320 | AA46: 990 | AB46: 4949 | AC46: 28775.84 | AD46: 13290.9 | AE46: 33724.84 | AF46: 0 | AG46: 33724.84 | AI46: https://sitefotos.com/vpics/guestmapdev?j1r0g2 | AJ46: =HYPERLINK(AI46,"LINK") -> LINK
B47: Yes - High Rack count | C47: CLEVGAXA | D47: WNS1491 | E47: Owned | F47: Building | G47: Central Office | I47: 34.597027 | J47: -83.766127 | K47: 158 West Kytle Street | L47: Cleveland | M47: GA | N47: ON040-GA-120 | O47: 200 | P47: REIT_ILEC | Q47: Windstream Standard| LLC | R47: ABS 1 | S47: 11195.13 | T47: 113494.35 | U47: 5552.62 | V47: 37854.63 | W47: 3688 | X47: 124 | Y47: 1025 | Z47: 257 | AA47: 1282 | AB47: 10847.39 | AC47: 71876.55 | AD47: 64725.86 | AE47: 82723.94 | AF47: 0 | AG47: 82723.94 | AH47: 42881 | AI47: https://sitefotos.com/vpics/guestmapdev?e5b4u1 | AJ47: =HYPERLINK(AI47,"LINK") -> LINK
C48: CLSTOHXA | D48: WNS2248 | E48: Owned | F48: Building | G48: Central Office | I48: 41.312906 | J48: -81.916151 | K48: 25038 Royalton Road | L48: Columbia Station | M48: OH | N48: ON158-OH-001 | O48: 2663 | P48: REIT_ILEC | Q48: Windstream Ohio| LLC | R48: ABS 1 | S48: 16867.98 | T48: 24384.76 | U48: 6592.55 | V48: 3271.94 | W48: 3917 | X48: 24 | Y48: 180 | Z48: 62 | AA48: 242 | AB48: 0 | AC48: 1052 | AD48: 565 | AE48: 1052 | AF48: 0 | AG48: 1052 | AI48: https://www.sitefotos.com/vpics/guestmapdev?u4j5r8 | AJ48: =HYPERLINK(AI48,"LINK") -> LINK
C49: CLJTIAWH | D49: WNS3288 | E49: Owned | F49: Building | G49: Central Office | H49: Warehouse | I49: 41.281893 | J49: -91.381209 | K49: 326 Hilltop Drive | L49: Columbus Junction | M49: IA | N49: B0133029 | O49: 3055 | P49: REIT_ILEC | Q49: Windstream Iowa Communications| Inc. | R49: ABS 2 | S49: 0 | T49: 0 | U49: 0 | V49: 0 | W49: 10084 | X49: 2 | Y49: 0 | Z49: 0 | AA49: 0 | AB49: 0 | AC49: 0 | AD49: 0 | AE49: 0 | AF49: 0 | AG49: 0 | AJ49: =HYPERLINK(AI49,"LINK") -> LINK
B50: Yes - High Rack count | C50: CMRCGAXA | D50: WNS1495 | E50: Owned | F50: Building | G50: Central Office | I50: 34.203976 | J50: -83.459471 | K50: 45 Georgia Avenue | L50: Commerce | M50: GA | N50: ON041-GA-001 | O50: 76 | P50: REIT_ILEC | Q50: Windstream Georgia| LLC | R50: ABS 1 | S50: 52795.68 | T50: 300789.85 | U50: 21756.39 | V50: 113603.09 | W50: 9417 | X50: 128 | Y50: 815 | Z50: 465 | AA50: 1280 | AB50: 192014.29 | AC50: 208054.34 | AD50: 263492.71 | AE50: 400068.63 | AF50: 0 | AG50: 400068.63 | AH50: 42881 | AI50: https://sitefotos.com/vpics/guestmapdev?o0d4c1 | AJ50: =HYPERLINK(AI50,"LINK") -> LINK
C51: CLDGTXXA | D51: WNS2557 | E51: Owned | F51: Building | G51: Central Office | I51: 31.754039 | J51: -96.649334 | K51: 102 S Second | L51: Coolidge | M51: TX | N51: ON209-TX-002 | P51: WIN_ILEC | Q51: Windstream Sugar Land| Inc. | R51: ABS 2 | S51: 11034.73 | T51: 12351.94 | U51: 1912.62 | V51: 1619.34 | W51: 4000 | X51: 23 | Y51: 273 | Z51: 0 | AA51: 273 | AB51: 2735 | AC51: 349 | AD51: 0 | AE51: 3084 | AF51: 0 | AG51: 3084 | AH51: 24737 | AI51: https://www.sitefotos.com/vpics/guestmapdev?l0i8t2 | AJ51: =HYPERLINK(AI51,"LINK") -> LINK
C52: CRNLGAXA | D52: WNS3179 | E52: Owned | F52: Building | G52: Central Office | I52: 34.514516 | J52: -83.52818 | K52: 350 North Main Street | L52: Cornelia | M52: GA | N52: ON040-GA-117 | O52: 75 | P52: REIT_ILEC | Q52: Windstream Standard| LLC | R52: ABS 2 | S52: 22792.16 | T52: 88725.02 | U52: 8023.29 | V52: 29253.71 | W52: 9500 | X52: 77 | Y52: 1206 | Z52: 301 | AA52: 1507 | AB52: 15657.55 | AC52: 15819.38 | AD52: 84047.25 | AE52: 31476.93 | AF52: 0 | AG52: 31476.93 | AH52: 35916 | AI52: https://sitefotos.com/vpics/guestmapdev?c3u3s6 | AJ52: =HYPERLINK(AI52,"LINK") -> LINK
C53: COWTOKXB | D53: WNS2335 | E53: Owned | F53: Building | G53: Central Office | I53: 35.950758 | J53: -95.651616 | K53: 124 West Sycamore Street | L53: Coweta | M53: OK | N53: ON200-OK-011 | O53: 173 | P53: REIT_ILEC | Q53: Valor Telecommunications of Texas| LLC | R53: ABS 2 | S53: 42239.99 | T53: 54657.32 | U53: 5546.74 | V53: 11389.13 | W53: 4400 | X53: 49 | Y53: 314 | Z53: 913 | AA53: 1227 | AB53: 17760.5 | AC53: 5292.56 | AD53: 38154.73 | AE53: 23053.06 | AF53: 0 | AG53: 23053.06 | AH53: 42339 | AI53: https://www.sitefotos.com/vpics/guestmapdev?w6y5t8 | AJ53: =HYPERLINK(AI53,"LINK") -> LINK
C54: CRESIAXO | D54: WNS1610 | E54: Owned | F54: Building | G54: Central Office | I54: 43.373961 | J54: -92.117349 | K54: 118 2nd Avenue W | L54: Cresco | M54: IA | N54: ON132-IA-1101 | O54: 222 | P54: REIT_ILEC | Q54: Windstream Iowa Communications| Inc. | R54: ABS 2 | S54: 27837.07 | T54: 25985.54 | U54: 5301.2 | V54: 8665.62 | W54: 3304 | X54: 20 | Y54: 380 | Z54: 724 | AA54: 1104 | AB54: 1840 | AC54: 2996 | AD54: 1712 | AE54: 4836 | AF54: 21 | AG54: 4857 | AI54: https://www.google.com/maps/place/43%C2%B022'26.2%22N+92%C2%B007'02.4%22W/@43.3739454,-92.117977,197m/data=!3m2!1e3!4b1!4m4!3m3!8m2!3d43.3739444!4d-92.1173333?entry=ttu&amp;g_ep=EgoyMDI1MTExNy4wIKXMDSoASAFQAw%3D%3D">Google Maps</a> | AJ54: =HYPERLINK(AI54,"LINK") -> LINK
C55: CETNIAXC | D55: WNS0057 | E55: Owned | F55: Building | G55: Central Office | I55: 41.058173 | J55: -94.363594 | K55: 117 North Elm Street | L55: Creston | M55: IA | N55: B0133037 | O55: 1415 | P55: REIT_ILEC | Q55: Windstream Iowa Communications| Inc. | R55: ABS 2 | S55: 19463.51 | T55: 37985.32 | U55: 4671.01 | V55: 13916.33 | W55: 7789 | X55: 24 | Y55: 977 | Z55: 671 | AA55: 1648 | AB55: 6983.8 | AC55: 4364.8 | AD55: 7552.5 | AE55: 11348.6 | AF55: 0 | AG55: 11348.6 | AI55: https://www.sitefotos.com/vpics/guestmapdev?q0g2p5 | AJ55: =HYPERLINK(AI55,"LINK") -> LINK
C56: CRSTARXA | D56: WNS1356 | E56: Owned | F56: Building | G56: Central Office | H56: Warehouse | I56: 33.128257 | J56: -91.962291 | K56: 104 West 6th Avenue | L56: Crossett | M56: AR | N56: ON202-AR-063 | O56: 148 | P56: REIT_ILEC | Q56: Windstream Arkansas| LLC | R56: ABS 1 | S56: 63821.07 | T56: 71406.75 | U56: 23866.51 | V56: 18436.67 | W56: 5145 | X56: 36 | Y56: 549 | Z56: 1522 | AA56: 2071 | AB56: 6422 | AC56: 18140.5 | AD56: 3064.27 | AE56: 24562.5 | AF56: 0 | AG56: 24562.5 | AH56: 42984 | AI56: https://www.google.com/maps/place/104+W+6th+Ave,+Crossett,+AR+71635/@33.1285045,-91.9626419,114m/data=!3m1!1e3!4m12!1m5!3m4!2zMzPCsDA3JzQyLjYiTiA5McKwNTcnNDQuNCJX!8m2!3d33.1285!4d-91.96232!3m5!1s0x862dd7165e613c93:0x9d6fd601f14e7437!8m2!3d33.1284789!4d-91.9623317!16s%2Fg%2F11c1hc9zn8?entry=ttu&amp;g_ep=EgoyMDI1MTExNy4wIKXMDSoASAFQAw%3D%3D">Google Maps</a> | AJ56: https://www.google.com/maps/place/104+W+6th+Ave,+Crossett,+AR+71635/@33.1285045,-91.9626419,114m/data=!3m1!1e3!4m12!1m5!3m4!2zMzPCsDA3JzQyLjYiTiA5McKwNTcnNDQuNCJX!8m2!3d33.1285!4d-91.96232!3m5!1s0x862dd7165e613c93:0x9d6fd601f14e7437!8m2!3d33.1284789!4d-91.9623317!16s%2Fg%2F11c1hc9zn8?entry=ttu&amp;g_ep=EgoyMDI1MTExNy4wIKXMDSoASAFQAw%3D%3D">Google Maps</a>
C57: CMLDKYXA | D57: WNS1724 | E57: Owned | F57: Building | G57: Central Office | I57: 36.977209 | J57: -82.990184 | K57: 309 Main Street | L57: Cumberland | M57: KY | N57: ON220-KY-011 | O57: 165 | P57: REIT_ILEC | Q57: Windstream Kentucky East| LLC | R57: ABS 1 | S57: 20142.36 | T57: 46211.57 | U57: 1924.17 | V57: 20457.14 | W57: 4580 | X57: 26 | Y57: 180 | Z57: 498 | AA57: 678 | AB57: 1795 | AC57: 3146.4 | AD57: 1195 | AE57: 4941.4 | AF57: 0 | AG57: 4941.4 | AI57: https://www.sitefotos.com/vpics/guestmapdev?i1x5l6 | AJ57: =HYPERLINK(AI57,"LINK") -> LINK
C58: DHLNGAXA | D58: WNS1498 | E58: Owned | F58: Building | G58: Central Office | I58: 34.535424 | J58: -83.982514 | K58: 200 Boyd Circle | L58: Dahlonega | M58: GA | N58: ON040-GA-047 | O58: 150 | P58: REIT_ILEC | Q58: Windstream Standard| LLC | R58: ABS 1 | S58: 7774.44 | T58: 64659.55 | U58: 1685 | V58: 21018.76 | W58: 5000 | X58: 50 | Y58: 821 | Z58: 464 | AA58: 1285 | AB58: 17216.56 | AC58: 35049.37 | AD58: 68037.89 | AE58: 52265.93 | AF58: 0 | AG58: 52265.93 | AH58: 42881 | AI58: https://sitefotos.com/vpics/guestmapdev?s4s3u5 | AJ58: =HYPERLINK(AI58,"LINK") -> LINK
C59: DLRKARXA | D59: WNS1358 | E59: Leased/Easement | F59: Building | G59: Central Office | I59: 34.038112 | J59: -92.887379 | K59: 13 Dallas 311 | L59: Dalark | M59: AR | N59: ON202-AR-1001 | P59: WIN_ILEC | Q59: Windstream Arkansas| LLC | R59: ABS 1 | S59: 5313.36 | T59: 8042.21 | U59: 192.56 | V59: 3098.14 | W59: 14355 | X59: 6 | Y59: 17 | Z59: 0 | AA59: 17 | AB59: 0 | AC59: 2497 | AD59: 43985.71 | AE59: 2497 | AF59: 0 | AG59: 2497 | AI59: https://www.google.com/maps/place/11+Dallas+311,+Arkadelphia,+AR+71923/@34.0381252,-92.887999,225m/data=!3m2!1e3!4b1!4m6!3m5!1s0x8632e92e3ea991cb:0xb86be4a0c450aca2!8m2!3d34.0381241!4d-92.8873553!16s%2Fg%2F11dzn71cvv?entry=ttu&amp;g_ep=EgoyMDI1MTExNy4wIKXMDSoASAFQAw%3D%3D">Google Maps</a> | AJ59: https://www.google.com/maps/place/11+Dallas+311,+Arkadelphia,+AR+71923/@34.0381252,-92.887999,225m/data=!3m2!1e3!4b1!4m6!3m5!1s0x8632e92e3ea991cb:0xb86be4a0c450aca2!8m2!3d34.0381241!4d-92.8873553!16s%2Fg%2F11dzn71cvv?entry=ttu&amp;g_ep=EgoyMDI1MTExNy4wIKXMDSoASAFQAw%3D%3D">Google Maps</a>
C60: DLHRTXXA | D60: WNS2567 | E60: Owned | F60: Building | G60: Central Office | I60: 36.060146 | J60: -102.5215 | K60: 601 Denver Avenue | L60: Dalhart | M60: TX | N60: ON400-TX-049 | O60: 4041 | P60: REIT_ILEC | Q60: Valor Telecommunications of Texas| LLC | R60: ABS 2 | S60: 20086.32 | T60: 9221.18 | U60: 6594.23 | V60: 2997.52 | W60: 9500 | X60: 20 | Y60: 189 | Z60: 491 | AA60: 680 | AB60: 5993 | AC60: 18864.78 | AD60: 5843.9 | AE60: 24857.78 | AF60: 0 | AG60: 24857.78 | AI60: https://www.sitefotos.com/vpics/guestmapdev?l3n8d0 | AJ60: =HYPERLINK(AI60,"LINK") -> LINK
C61: DLTNGAXD | D61: WNS1500 | E61: Owned | F61: Building | G61: Central Office | I61: 34.675055 | J61: -84.966388 | K61: 350 Cross Plains Blvd | L61: Dalton | M61: GA | N61: ON042-GA-036 | O61: 93 | P61: REIT_ILEC | Q61: Windstream Georgia Communications| LLC | R61: ABS 2 | S61: 46209.73 | T61: 711.41 | U61: 19703.58 | V61: 273.46 | W61: 7717 | X61: 18 | Y61: 84 | Z61: 35 | AA61: 119 | AB61: 3824.1 | AC61: 4380.3 | AD61: 11658.8 | AE61: 8204.4 | AF61: 0 | AG61: 8204.4 | AI61: https://sitefotos.com/vpics/guestmapdev?l1c4e5 | AJ61: =HYPERLINK(AI61,"LINK") -> LINK
C62: DWSNGAXA | D62: WNS1504 | E62: Owned | F62: Building | G62: Central Office | I62: 31.774245 | J62: -84.445644 | K62: 163 Stonewall Street NE | L62: Dawson | M62: GA | N62: ON042-GA-106 | O62: 163 | P62: REIT_ILEC | Q62: Windstream Georgia Communications| LLC | R62: ABS 1 | S62: 23180.99 | T62: 48521.98 | U62: 18953.08 | V62: 15730.05 | W62: 4648 | X62: 35 | Y62: 349 | Z62: 1161 | AA62: 1510 | AB62: 14106.17 | AC62: 14093.65 | AD62: 72221.16 | AE62: 28199.82 | AF62: 0 | AG62: 28199.82 | AH62: 42881 | AI62: https://sitefotos.com/vpics/guestmapdev?l8t2l3 | AJ62: =HYPERLINK(AI62,"LINK") -> LINK
C63: DELTOHXA | D63: WNS2259 | E63: Owned | F63: Building | G63: Central Office | I63: 41.574908 | J63: -84.007659 | K63: 201 Monroe Street | L63: Delta | M63: OH | N63: ON158-OH-003 | O63: 2672 | P63: REIT_ILEC | Q63: Windstream Ohio| LLC | R63: ABS 1 | S63: 16998.42 | T63: 20218.09 | U63: 5196.68 | V63: 5570.33 | W63: 4400 | X63: 26 | Y63: 241 | Z63: 328 | AA63: 569 | AB63: 400 | AC63: 2717 | AD63: 1951 | AE63: 3117 | AF63: 0 | AG63: 3117 | AI63: https://www.sitefotos.com/vpics/guestmapdev?o5u2t0 | AJ63: =HYPERLINK(AI63,"LINK") -> LINK
C64: DMMTTXXA | D64: WNS2575 | E64: Owned | F64: Building | G64: Central Office | I64: 34.551706 | J64: -102.31128 | K64: 113 Northeast 2nd Street | L64: Dimmitt | M64: TX | N64: ON400-TX-057 | O64: 3644 | P64: REIT_ILEC | Q64: Valor Telecommunications of Texas| LLC | R64: ABS 2 | S64: 27720.37 | T64: 19548.58 | U64: 1665.26 | V64: 6297.54 | W64: 5913 | X64: 28 | Y64: 343 | Z64: 505 | AA64: 848 | AB64: 5273 | AC64: 6313.84 | AD64: 999 | AE64: 11586.84 | AF64: 0 | AG64: 11586.84 | AH64: 42881 | AI64: https://www.sitefotos.com/vpics/guestmapdev?r4h2u6 | AJ64: =HYPERLINK(AI64,"LINK") -> LINK
C65: DNVLGAXA | D65: WNS1509 | E65: Owned | F65: Building | G65: Central Office | I65: 31.041347 | J65: -84.884544 | K65: 202 Knox Street | L65: Donalsonville | M65: GA | N65: ON043-GA-009 | O65: 259 | P65: REIT_ILEC | Q65: Georgia Windstream| LLC | R65: ABS 2 | S65: 7039.77 | T65: 32831.04 | U65: 2707.85 | V65: 10936.67 | W65: 2874 | X65: 30 | Y65: 369 | Z65: 597 | AA65: 966 | AB65: 10750.42 | AC65: 11450.28 | AD65: 26957.53 | AE65: 22200.7 | AF65: 0 | AG65: 22200.7 | AI65: https://sitefotos.com/vpics/guestmapdev?t2s2j3 | AJ65: =HYPERLINK(AI65,"LINK") -> LINK
C66: DNSNIAXO | D66: WNS0481 | E66: Owned | F66: Building | G66: Central Office | I66: 40.642822 | J66: -91.565325 | K66: 517 Elm Street | L66: Donnellson | M66: IA | N66: ON132-IA-2120 | O66: 139 | P66: REIT_ILEC | Q66: Windstream Iowa Communications| Inc. | R66: ABS 2 | S66: 12380.16 | T66: 18974.34 | U66: 3222.63 | V66: 6871.13 | W66: 5511 | X66: 21 | Y66: 83 | Z66: 220 | AA66: 303 | AB66: 0 | AC66: 5333.66 | AD66: 9220.66 | AE66: 5333.66 | AF66: 0 | AG66: 5333.66 | AI66: https://www.google.com/maps/place/40%C2%B038'34.2%22N+91%C2%B033'55.4%22W/@40.6428343,-91.5660326,206m/data=!3m2!1e3!4b1!4m4!3m3!8m2!3d40.6428333!4d-91.5653889?entry=ttu&amp;g_ep=EgoyMDI1MTAyNi4wIKXMDSoASAFQAw%3D%3D">Google Maps</a> | AJ66: =HYPERLINK(AI66,"LINK") -> LINK
C67: DUMSTXXA | D67: WNS2579 | E67: Owned | F67: Building | G67: Central Office | I67: 35.859042 | J67: -101.97412 | K67: 116 West 7th Street | L67: Dumas | M67: TX | N67: ON400-TX-060 | O67: 79 | P67: REIT_ILEC | Q67: Valor Telecommunications of Texas| LLC | R67: ABS 1 | S67: 99052.97 | T67: 45461.67 | U67: 17960.15 | V67: 18406.14 | W67: 5870 | X67: 74 | Y67: 653 | Z67: 1693 | AA67: 2346 | AB67: 40611.57 | AC67: 86529.49 | AD67: 14975.94 | AE67: 127141.06 | AF67: 0 | AG67: 127141.06 | AH67: 42339 | AI67: https://www.sitefotos.com/vpics/guestmapdev?i3c0y4 | AJ67: =HYPERLINK(AI67,"LINK") -> LINK
C68: DYVLIAXO | D68: WNS1624 | E68: Owned | F68: Building | G68: Central Office | I68: 42.484061 | J68: -91.123057 | K68: 116 2nd Street | L68: Dyersville | M68: IA | N68: ON132-IA-2127 | O68: 103 | P68: REIT_ILEC | Q68: Windstream Iowa Communications| Inc. | R68: ABS 2 | S68: 0 | T68: 23699.91 | U68: 0 | V68: 11246.69 | W68: 7271 | X68: 26 | Y68: 399 | Z68: 286 | AA68: 685 | AB68: 1886.01 | AC68: 10123.5 | AD68: 25716.46 | AE68: 12009.51 | AF68: 0 | AG68: 12009.51 | AI68: https://www.sitefotos.com/vpics/guestmapdev?w3a6l4 | AJ68: =HYPERLINK(AI68,"LINK") -> LINK
C69: EDWDIAXO | E69: Owned | F69: Building | G69: Central Office | I69: 42.645186 | J69: -91.400568 | K69: 105 E MAIN | L69: Edgewood | M69: IA | N69: ON132-IA-2130 | P69: WIN_ILEC | R69: ABS 2 | S69: 0 | T69: 0 | U69: 0 | V69: 0 | W69: 10084 | X69: 4 | Y69: 141 | Z69: 128 | AA69: 269 | AB69: 0 | AC69: 0 | AD69: 1450 | AE69: 0 | AF69: 0 | AG69: 0 | AJ69: =HYPERLINK(AI69,"LINK") -> LINK
B70: Yes: 12k sqft + Owned | C70: ELYROHXA | D70: WNS2262 | E70: Owned | F70: Building | G70: Central Office | I70: 41.365741 | J70: -82.109993 | K70: 363 3rd Street | L70: Elyria | M70: OH | N70: B158010 | O70: 2674 | P70: REIT_ILEC | Q70: Windstream Ohio| LLC | R70: ABS 1 | S70: 94411.73 | T70: 341674.15 | U70: 37852.57 | V70: 100578.63 | W70: 73218 | X70: 159 | Y70: 1304 | Z70: 1087 | AA70: 2391 | AB70: 2448.53 | AC70: 61314.71 | AD70: 48268.88 | AE70: 63763.24 | AF70: 0 | AG70: 63763.24 | AH70: 42881 | AI70: https://www.sitefotos.com/vpics/guestmapdev?i3h7y0 | AJ70: =HYPERLINK(AI70,"LINK") -> LINK
C71: ELYROHXB | D71: WNS2263 | E71: Owned | F71: Building | G71: Central Office | H71: Tower | I71: 41.38464 | J71: -82.077996 | K71: 400 Abbe Norht Road | L71: Elyria | M71: OH | N71: ON158-OH-005 | O71: 2675 | P71: REIT_ILEC | Q71: Windstream Ohio| LLC | R71: ABS 1 | S71: 46204.23 | T71: 54845.15 | U71: 9764.28 | V71: 14156.78 | W71: 7334 | X71: 52 | Y71: 368 | Z71: 1321 | AA71: 1689 | AB71: 0 | AC71: 4422.22 | AD71: 1614 | AE71: 4422.22 | AF71: 0 | AG71: 4422.22 | AI71: https://www.sitefotos.com/vpics/guestmapdev?s7j1g2 | AJ71: =HYPERLINK(AI71,"LINK") -> LINK
C72: ELYROHXE | D72: WNS2264 | E72: Owned | F72: Building | G72: Central Office | I72: 41.399902 | J72: -82.132505 | K72: 41786 Griswald Road | L72: Elyria | M72: OH | N72: ON158-OH-004 | O72: 2676 | P72: REIT_ILEC | Q72: Windstream Ohio| LLC | R72: ABS 1 | S72: 19656.17 | T72: 30438.91 | U72: 6616.28 | V72: 8946.71 | W72: 5469 | X72: 33 | Y72: 340 | Z72: 554 | AA72: 894 | AB72: 1124 | AC72: 6838.97 | AD72: 1056.2 | AE72: 7962.97 | AF72: 0 | AG72: 7962.97 | AI72: https://www.sitefotos.com/vpics/guestmapdev?t8f6t7 | AJ72: =HYPERLINK(AI72,"LINK") -> LINK
C73: EMBGIAXP | D73: WNS3292 | E73: Owned | F73: Building | G73: Central Office | I73: 43.110806 | J73: -94.667386 | K73: 1301 10th Street | L73: Emmetsburg | M73: IA | N73: B0133032 | O73: 3299 | P73: REIT_ILEC | Q73: Windstream Iowa Communications| Inc. | R73: ABS 2 | S73: 0 | T73: 0 | U73: 0 | V73: 0 | W73: 10084 | X73: 23 | Y73: 334 | Z73: 453 | AA73: 787 | AB73: 3300 | AC73: 1806 | AD73: 19481 | AE73: 5106 | AF73: 0 | AG73: 5106 | AJ73: =HYPERLINK(AI73,"LINK") -> LINK
C74: EVRSKYXA | D74: WNS1728 | E74: Owned | F74: Building | G74: Central Office | I74: 36.861869 | J74: -83.182402 | K74: 159 E. Main St | L74: EVARTS | M74: KY | N74: ON220-KY-014 | O74: 225 | P74: REIT_ILEC | Q74: Windstream Kentucky East| LLC | R74: ABS 1 | S74: 15416.46 | T74: 26449 | U74: 3624.17 | V74: 10635.18 | W74: 3283 | X74: 42 | Y74: 100 | Z74: 434 | AA74: 534 | AB74: 2100 | AC74: 1649.86 | AD74: 0 | AE74: 3749.86 | AF74: 0 | AG74: 3749.86 | AI74: https://www.sitefotos.com/vpics/guestmapdev?b4f3l3 | AJ74: =HYPERLINK(AI74,"LINK") -> LINK
C75: FRFDIAXC | D75: WNS1627 | E75: Owned | F75: Building | G75: Central Office | I75: 41.007423 | J75: -91.965878 | K75: 204 West Broadway | L75: Fairfield | M75: IA | N75: ON132-IA-1150 | O75: 2396 | P75: REIT_ILEC | Q75: Windstream Iowa Communications| Inc. | R75: ABS 2 | S75: 31149.91 | T75: 37674.65 | U75: 40414.61 | V75: 14932.98 | W75: 4700 | X75: 40 | Y75: 481 | Z75: 403 | AA75: 884 | AB75: 9874 | AC75: 7074.9 | AD75: 242381.36 | AE75: 16948.9 | AF75: 389.52 | AG75: 17338.42 | AI75: https://www.google.com/maps/place/41%C2%B000'26.5%22N+91%C2%B057'57.0%22W/@41.0073621,-91.966477,205m/data=!3m2!1e3!4b1!4m4!3m3!8m2!3d41.0073611!4d-91.9658333?entry=ttu&amp;g_ep=EgoyMDI1MTExNy4wIKXMDSoASAFQAw%3D%3D">Google Maps</a> | AJ75: =HYPERLINK(AI75,"LINK") -> LINK
B76: Yes: 12k sqft + Owned | C76: FTZGGAXA | D76: WNS1514 | E76: Owned | F76: Building | G76: Central Office | I76: 31.715144 | J76: -83.253794 | K76: 110 East Central | L76: Fitzgerald | M76: GA | N76: ON042-GA-132 | O76: 35 | P76: REIT_ILEC | Q76: Windstream Georgia Communications| LLC | R76: ABS 2 | S76: 46961.1 | T76: 316512.79 | U76: 15698.45 | V76: 74237.68 | W76: 16821 | X76: 92 | Y76: 442 | Z76: 1527 | AA76: 1969 | AB76: 242075.11 | AC76: 312077.57 | AD76: 173549.1 | AE76: 554152.68 | AF76: 0 | AG76: 554152.68 | AH76: 42767 | AI76: https://sitefotos.com/vpics/guestmapdev?g7s2j2 | AJ76: =HYPERLINK(AI76,"LINK") -> LINK
C77: RSSLKYXB | D77: WNS1730 | E77: Owned | F77: Building | G77: Central Office | I77: 38.51718 | J77: -82.722061 | K77: 2400 Argillite Road | L77: FLATWOODS | M77: KY | N77: ON219-KY-015 | O77: 2446 | P77: REIT_ILEC | Q77: Windstream Kentucky East| LLC | R77: ABS 1 | S77: 16777.88 | T77: 67530.24 | U77: 4237.28 | V77: 22311.84 | W77: 3600 | X77: 73 | Y77: 107 | Z77: 1289 | AA77: 1396 | AB77: 9841.98 | AC77: 18176.45 | AD77: 70713.88 | AE77: 28018.43 | AF77: 0 | AG77: 28018.43 | AI77: https://www.sitefotos.com/vpics/guestmapdev?p0q8s1 | AJ77: =HYPERLINK(AI77,"LINK") -> LINK
C78: FMBGKYXA | D78: WNS1732 | E78: Owned | F78: Building | G78: Central Office | I78: 38.424916 | J78: -83.736666 | K78: 226 West Water Street | L78: FLEMINGSBURG | M78: KY | N78: ON219-KY-016 | O78: 177 | P78: REIT_ILEC | Q78: Windstream Kentucky East| LLC | R78: ABS 1 | S78: 24784.11 | T78: 43500.95 | U78: 4109.85 | V78: 16507.9 | W78: 4309 | X78: 69 | Y78: 385 | Z78: 432 | AA78: 817 | AB78: 3474.66 | AC78: 20515.71 | AD78: 86995.51 | AE78: 23990.37 | AF78: 0 | AG78: 23990.37 | AH78: 42984 | AI78: https://www.sitefotos.com/vpics/guestmapdev?h2t4s4 | AJ78: =HYPERLINK(AI78,"LINK") -> LINK
C79: FLTNGAXA | D79: WNS1515 | E79: Owned | F79: Building | G79: Central Office | I79: 30.829452 | J79: -82.005217 | K79: 201 East Martin Street | L79: Folkston | M79: GA | N79: ON043-GA-053 | O79: 193 | P79: REIT_ILEC | Q79: Georgia Windstream| LLC | R79: ABS 2 | S79: 10023.2 | T79: 41225.81 | U79: 11440.53 | V79: 13609.11 | W79: 5060 | X79: 25 | Y79: 436 | Z79: 350 | AA79: 786 | AB79: 11318.63 | AC79: 18922.3 | AD79: 8690.3 | AE79: 30240.93 | AF79: 0 | AG79: 30240.93 | AH79: 42881 | AI79: https://sitefotos.com/vpics/guestmapdev?s8m2q1 | AJ79: =HYPERLINK(AI79,"LINK") -> LINK
C80: FRDYARXA | D80: WNS1367 | E80: Owned | F80: Building | G80: Central Office | I80: 33.812874 | J80: -92.413513 | K80: 308 North Oak Street | L80: Fordyce | M80: AR | N80: ON202-AR-067 | O80: 167 | P80: REIT_ILEC | Q80: Windstream Arkansas| LLC | R80: ABS 1 | S80: 18695.13 | T80: 71761.75 | U80: 3647.4 | V80: 8744.84 | W80: 4517 | X80: 36 | Y80: 387 | Z80: 1018 | AA80: 1405 | AB80: 5480.4 | AC80: 26603.28 | AD80: 43431.95 | AE80: 32083.68 | AF80: 0 | AG80: 32083.68 | AH80: 42881 | AI80: https://www.sitefotos.com/vpics/guestmapdev?e6n6n6 | AJ80: =HYPERLINK(AI80,"LINK") -> LINK
C81: FRCYIAXO | D81: WNS0504 | E81: Owned | F81: Building | G81: Central Office | I81: 43.265765 | J81: -93.638938 | K81: 145 West L Street | L81: Forest City | M81: IA | N81: ON132-IA-1162 | O81: 1680 | P81: REIT_ILEC | Q81: Windstream Iowa Communications| Inc. | R81: ABS 2 | S81: 10338.83 | T81: 9296.89 | U81: 3357.21 | V81: 5383.98 | W81: 4994 | X81: 15 | Y81: 35 | Z81: 2 | AA81: 37 | AB81: 0 | AC81: 3811 | AD81: 3110 | AE81: 3811 | AF81: 0 | AG81: 3811 | AI81: https://www.sitefotos.com/vpics/guestmapdev?k0s2d2 | AJ81: =HYPERLINK(AI81,"LINK") -> LINK
B82: Yes: 12k sqft + Owned | C82: GENVOHXA | D82: WNS2267 | E82: Owned | F82: Building | G82: Central Office | I82: 41.805317 | J82: -80.945672 | K82: 37 South Forest Street | L82: Geneva | M82: OH | N82: ON080-OH-040 | O82: 51 | P82: REIT_ILEC | Q82: Windstream Western Reserve| Inc. | R82: ABS 1 | S82: 43683.77 | T82: 37088.83 | U82: 14547.93 | V82: 13944.09 | W82: 12477 | X82: 25 | Y82: 326 | Z82: 797 | AA82: 1123 | AB82: 3910 | AC82: 4547.86 | AD82: 9739.4 | AE82: 8457.86 | AF82: 0 | AG82: 8457.86 | AI82: https://www.sitefotos.com/vpics/guestmapdev?a0g2a6 | AJ82: =HYPERLINK(AI82,"LINK") -> LINK
C83: GRVIOHXA | D83: WNS2268 | E83: Owned | F83: Building | G83: Central Office | I83: 40.06756 | J83: -82.518978 | K83: 131 East Broadway | L83: Granville | M83: OH | N83: ON158-OH-023 | O83: 2679 | P83: REIT_ILEC | Q83: Windstream Ohio| LLC | R83: ABS 2 | S83: 19967.76 | T83: 26744.56 | U83: 6620.9 | V83: 8210.38 | W83: 6307 | X83: 24 | Y83: 239 | Z83: 393 | AA83: 632 | AB83: 2151.6 | AC83: 7577.5 | AD83: 7633.7 | AE83: 9729.1 | AF83: 0 | AG83: 9729.1 | AI83: https://www.sitefotos.com/vpics/guestmapdev?d2f7d8 | AJ83: =HYPERLINK(AI83,"LINK") -> LINK
B84: Yes: 12k sqft + Owned | C84: GNBRARXA | D84: WNS1370 | E84: Owned | F84: Building | G84: Central Office | I84: 35.232663 | J84: -92.388351 | K84: 9 South Broadview Street | L84: Greenbrier | M84: AR | N84: ON202-AR-013 | O84: 2298 | P84: REIT_ILEC | Q84: Windstream Arkansas| LLC | R84: ABS 1 | S84: 57457.22 | T84: 86295.67 | U84: 23436.5 | V84: 19649.56 | W84: 20000 | X84: 64 | Y84: 331 | Z84: 324 | AA84: 655 | AB84: 8811.8 | AC84: 20476.55 | AD84: 63414.33 | AE84: 29288.35 | AF84: 0 | AG84: 29288.35 | AH84: 42881 | AI84: https://www.sitefotos.com/vpics/guestmapdev?e4o1u0 | AJ84: =HYPERLINK(AI84,"LINK") -> LINK
C85: GNFDIAAJ | D85: WNS3295 | E85: Owned | F85: Building | G85: Central Office | H85: Warehouse | I85: 41.294821 | J85: -94.460172 | K85: South Townline Road | L85: Greenfield | M85: IA | N85: B0133013 | O85: 3300 | P85: REIT_ILEC | Q85: Windstream Iowa Communications| Inc. | R85: ABS 2 | S85: 0 | T85: 0 | U85: 0 | V85: 0 | W85: 10084 | X85: 0 | Y85: 0 | Z85: 0 | AA85: 0 | AB85: 0 | AC85: 0 | AD85: 0 | AE85: 0 | AF85: 0 | AG85: 0 | AJ85: =HYPERLINK(AI85,"LINK") -> LINK
C86: GNUPKYXA | D86: WNS1737 | E86: Owned | F86: Building | G86: Central Office | I86: 38.573424 | J86: -82.839627 | K86: 304 Laurel St. | L86: Greenup | M86: KY | N86: ON219-KY-020 | O86: 2450 | P86: REIT_ILEC | Q86: Windstream Kentucky East| LLC | R86: ABS 1 | S86: 24729.66 | T86: 53759.69 | U86: 17592.45 | V86: 37100.65 | W86: 4100 | X86: 52 | Y86: 148 | Z86: 421 | AA86: 569 | AB86: 4658 | AC86: 17091.11 | AD86: 75762.86 | AE86: 21749.11 | AF86: 0 | AG86: 21749.11 | AH86: 42767 | AI86: https://www.sitefotos.com/vpics/guestmapdev?j4e7p2 | AJ86: =HYPERLINK(AI86,"LINK") -> LINK
B87: Yes: 12k sqft + Owned | C87: GRNLIAXC | D87: WNS1631 | E87: Owned | F87: Building | G87: Central Office | I87: 41.74517 | J87: -92.725415 | K87: 1010 Main Street | L87: Grinnell | M87: IA | N87: ON132-IA-1181 | O87: 37 | P87: REIT_ILEC | Q87: Windstream Iowa Communications| Inc. | R87: ABS 2 | S87: 37252.22 | T87: 109942.31 | U87: 21509.57 | V87: 40362.96 | W87: 15723 | X87: 84 | Y87: 648 | Z87: 595 | AA87: 1243 | AB87: 86783.49 | AC87: 175897.93 | AD87: 71294.07 | AE87: 262681.42 | AF87: 21 | AG87: 262702.42 | AI87: https://www.sitefotos.com/vpics/guestmapdev?s1u7o1 | AJ87: =HYPERLINK(AI87,"LINK") -> LINK
B88: Yes: 12k sqft + Owned | C88: HRSNARXA | E88: Owned | F88: Building | G88: Central Office | I88: 36.214283 | J88: -93.079052 | K88: 202 Graham Street | L88: Harrison | M88: AR | N88: B202322 | O88: 1392 | P88: REIT_ILEC | Q88: Windstream Arkansas| LLC | R88: ABS 1 | S88: 149943.27 | T88: 97350.18 | U88: 58606.83 | V88: 23685.58 | W88: 21579 | X88: 81 | Y88: 472 | Z88: 144 | AA88: 616 | AB88: 12764 | AC88: 53237.64 | AD88: 52403.81 | AE88: 66001.64 | AF88: 0 | AG88: 66001.64 | AH88: 41831 | AI88: https://www.sitefotos.com/vpics/guestmapdev?o8a8x4 | AJ88: =HYPERLINK(AI88,"LINK") -> LINK
B89: Yes: 12k sqft + Owned | C89: HZRDKYXA | D89: WNS1739 | E89: Owned | F89: Building | G89: Central Office | I89: 37.249865 | J89: -83.19392 | K89: 101 Winterberry Drive | L89: Hazard | M89: KY | N89: ON219-KY-021 | O89: 42 | P89: REIT_ILEC | Q89: Windstream Kentucky East| LLC | R89: ABS 1 | S89: 46258.55 | T89: 118939.09 | U89: 9698.41 | V89: 42853.88 | W89: 14149 | X89: 133 | Y89: 624 | Z89: 1401 | AA89: 2025 | AB89: 48976.38 | AC89: 165196.62 | AD89: 31654.32 | AE89: 214173 | AF89: 0 | AG89: 214173 | AH89: 42614 | AI89: https://www.sitefotos.com/vpics/guestmapdev?i6e5b4 | AJ89: =HYPERLINK(AI89,"LINK") -> LINK
C90: HWSSGAXA | D90: WNS1525 | E90: Owned | F90: Building | G90: Central Office | I90: 34.951738 | J90: -83.758306 | K90: 228 North Main Street | L90: Hiawassee | M90: GA | N90: ON040-GA-01048 | O90: 3779 | P90: REIT_ILEC | Q90: Windstream Standard| LLC | R90: ABS 1 | S90: 8458.5 | T90: 197507.04 | U90: 5530.89 | V90: 53358.24 | W90: 3026 | X90: 19 | Y90: 417 | Z90: 61 | AA90: 478 | AB90: 9336.66 | AC90: 23396.36 | AD90: 15434 | AE90: 32733.02 | AF90: 0 | AG90: 32733.02 | AH90: 43190 | AI90: https://sitefotos.com/vpics/guestmapdev?a1r2b1 | AJ90: =HYPERLINK(AI90,"LINK") -> LINK
C91: HLRDFLXA | D91: WNS1438 | E91: Owned | F91: Building | G91: Central Office | I91: 30.689733 | J91: -81.918661 | K91: 3745 Pecan Street | L91: Hilliard | M91: FL | N91: ON047-FL-023 | O91: 2341 | P91: REIT_ILEC | Q91: Windstream Florida| Inc. | R91: ABS 2 | S91: 15654.69 | T91: 25401.3 | U91: 20548.17 | V91: 6312.98 | W91: 4360 | X91: 30 | Y91: 187 | Z91: 219 | AA91: 406 | AB91: 4530 | AC91: 18102.56 | AD91: 0 | AE91: 22632.56 | AF91: 0 | AG91: 22632.56 | AH91: 42984 | AI91: https://www.google.com/maps/place/30%C2%B041'23.0%22N+81%C2%B055'07.3%22W/@30.6897234,-81.9193381,234m/data=!3m2!1e3!4b1!4m4!3m3!8m2!3d30.6897222!4d-81.9186944?entry=ttu&amp;g_ep=EgoyMDI2MDIyNC4wIKXMDSoASAFQAw%3D%3D">Google Maps</a> | AJ91: =HYPERLINK(AI91,"LINK") -> LINK
C92: HIRMOHXA | D92: WNS2272 | E92: Owned | F92: Building | G92: Central Office | I92: 41.310006 | J92: -81.146041 | K92: 11677 Hayden Street Rear | L92: Hiram | M92: OH | N92: ON080-OH-013 | O92: 2683 | P92: REIT_ILEC | Q92: Windstream Western Reserve| Inc. | R92: ABS 1 | S92: 23926.8 | T92: 14889.72 | U92: 8424.15 | V92: 7045.41 | W92: 10605 | X92: 14 | Y92: 73 | Z92: 99 | AA92: 172 | AB92: 0 | AC92: 2907.5 | AD92: 20485.1 | AE92: 2907.5 | AF92: 0 | AG92: 2907.5 | AI92: https://sitefotos.com/vpics/guestmapdev?f1y0i4 | AJ92: =HYPERLINK(AI92,"LINK") -> LINK
C93: HLCRIAXP | D93: WNS1638 | E93: Owned | F93: Building | G93: Central Office | I93: 42.599216 | J93: -90.992189 | K93: 5778 MAPLE RD | L93: Holy Cross | M93: IA | N93: B0133018 | O93: 930 | P93: REIT_ILEC | Q93: Windstream Iowa Communications| Inc. | R93: ABS 2 | S93: 2042.35 | T93: 4283.42 | U93: 5775.07 | V93: 817.65 | W93: 2770 | X93: 6 | Y93: 42 | Z93: 68 | AA93: 110 | AB93: 0 | AC93: 239 | AD93: 0 | AE93: 239 | AF93: 0 | AG93: 239 | AI93: https://www.google.com/maps/place/42%C2%B035'44.2%22N+90%C2%B059'45.6%22W/@42.5956377,-90.9958579,800m/data=!3m1!1e3!4m4!3m3!8m2!3d42.595608!4d-90.995998?entry=ttu&amp;g_ep=EgoyMDI1MTAyNi4wIKXMDSoASAFQAw%3D%3D">Google Maps</a> | AJ93: =HYPERLINK(AI93,"LINK") -> LINK
B94: Yes: 12k sqft + Owned | C94: HDSNOHXB | D94: WNS1063 | E94: Owned | F94: Building | G94: Central Office | I94: 41.217063 | J94: -81.442508 | K94: 1300 Terex Road | L94: Hudson | M94: OH | N94: ON080-OH-015 | O94: 2031 | P94: REIT_ILEC | Q94: Windstream Western Reserve| Inc. | R94: ABS 1 | S94: 10196.96 | T94: 22058.62 | U94: 3969.1 | V94: 5551.47 | W94: 29978 | X94: 20 | Y94: 167 | Z94: 5 | AA94: 172 | AB94: 390 | AC94: 3113 | AD94: 481 | AE94: 3503 | AF94: 0 | AG94: 3503 | AI94: https://www.sitefotos.com/vpics/guestmapdev?u1a0v7 | AJ94: =HYPERLINK(AI94,"LINK") -> LINK
B95: Yes: 12k sqft + Owned | C95: HDSNOHXA | D95: WNS2275 | E95: Owned | F95: Building | G95: Central Office | I95: 41.243414 | J95: -81.440034 | K95: 245 North Main Street | L95: Hudson | M95: OH | N95: ON080-OH-043 | O95: 3800 | P95: REIT_ILEC | Q95: Windstream Western Reserve| Inc. | R95: ABS 1 | S95: 151219.15 | T95: 292937.87 | U95: 42853.14 | V95: 87782.52 | W95: 18705 | X95: 170 | Y95: 486 | Z95: 241 | AA95: 727 | AB95: 119468.81 | AC95: 211677.8 | AD95: 26906.52 | AE95: 331146.61 | AF95: 0 | AG95: 331146.61 | AH95: 39417 | AI95: https://sitefotos.com/vpics/guestmapdev?u6l0o6 | AJ95: =HYPERLINK(AI95,"LINK") -> LINK
C96: WTWDTXXA | D96: WNS2619 | E96: Owned | F96: Building | G96: Central Office | I96: 30.811592 | J96: -95.259738 | K96: 24500 Waterwood Parkway | L96: Huntsville | M96: TX | N96: ON209-TX-004 | O96: 147 | P96: REIT_ILEC | Q96: Windstream Sugar Land| Inc. | R96: ABS 2 | S96: 13830.37 | T96: 14087.57 | U96: 3915.8 | V96: 2854.38 | W96: 5150 | X96: 9 | Y96: 105 | Z96: 0 | AA96: 105 | AB96: 1280 | AC96: 2372 | AD96: 0 | AE96: 3652 | AF96: 0 | AG96: 3652 | AJ96: =HYPERLINK(AI96,"LINK") -> LINK
C97: IRTNGAXA | D97: WNS1529 | E97: Owned | F97: Building | G97: Central Office | I97: 32.820255 | J97: -83.167826 | K97: 113 Wriley Road | L97: Irwinton | M97: GA | N97: ON044-GA-003 | O97: 130 | P97: REIT_ILEC | Q97: Windstream Accucomm Telecommunications| LLC | R97: ABS 2 | S97: 18589.07 | T97: 33935.07 | U97: 4431.32 | V97: 11287.95 | W97: 5856 | X97: 26 | Y97: 346 | Z97: 54 | AA97: 400 | AB97: 6307 | AC97: 8154.3 | AD97: 23953.19 | AE97: 14461.3 | AF97: 0 | AG97: 14461.3 | AH97: 43282 | AI97: https://sitefotos.com/vpics/guestmapdev?d0w8f0 | AJ97: =HYPERLINK(AI97,"LINK") -> LINK
C98: JSPRGAXA | D98: WNS1532 | E98: Owned | F98: Building | G98: Central Office | I98: 34.468179 | J98: -84.431445 | K98: 69 Stegall Drive | L98: Jasper | M98: GA | N98: ON042-GA-051 | O98: 215 | P98: REIT_ILEC | Q98: Windstream Georgia Communications| LLC | R98: ABS 1 | S98: 23841.25 | T98: 37315.92 | U98: 5449.75 | V98: 12081.5 | W98: 3452 | X98: 22 | Y98: 342 | Z98: 368 | AA98: 710 | AB98: 26282.12 | AC98: 57572.76 | AD98: 31373.49 | AE98: 83854.88 | AF98: 0 | AG98: 83854.88 | AI98: https://sitefotos.com/vpics/guestmapdev?j8t5r2 | AJ98: =HYPERLINK(AI98,"LINK") -> LINK
C99: JLLYIAXE | E99: Owned | F99: Building | G99: Central Office | I99: 42.478421 | J99: -94.718466 | K99: Alley East Of 129 Maston St | L99: Jolley | M99: IA | N99: ON132-IA-1204 | O99: 1688 | P99: REIT_ILEC | Q99: Windstream Iowa Communications| Inc. | R99: ABS 2 | S99: 0 | T99: 0 | U99: 0 | V99: 0 | W99: 10084 | X99: 3 | Y99: 23 | Z99: 0 | AA99: 23 | AB99: 0 | AC99: 0 | AD99: 0 | AE99: 0 | AF99: 0 | AG99: 0 | AJ99: =HYPERLINK(AI99,"LINK") -> LINK
C100: KNTNOHXA | D100: WNS2278 | E100: Owned | F100: Building | G100: Central Office | I100: 40.647896 | J100: -83.610299 | K100: 225 West Columbus Street | L100: Kenton | M100: OH | N100: ON158-OH-025 | O100: 2686 | P100: REIT_ILEC | Q100: Windstream Ohio| LLC | R100: ABS 2 | S100: 33005.9 | T100: 45165.06 | U100: 12605.5 | V100: 13894.25 | W100: 9800 | X100: 30 | Y100: 473 | Z100: 557 | AA100: 1030 | AB100: 2452.58 | AC100: 27447.49 | AD100: 2556 | AE100: 29900.07 | AF100: 0 | AG100: 29900.07 | AI100: https://www.sitefotos.com/vpics/guestmapdev?n4b2c1 | AJ100: =HYPERLINK(AI100,"LINK") -> LINK
...

Sheet Top 50
A1: Inputs
B2: W/Sqft | C2: 250
B3: White space as % of whole | C3: 0.75
A6: MBN Selected? | B6: Selected? | C6: CLLI | D6: Site_Number | E6: Land_Ownership | F6: Asset_Type | G6: Primary_Use | H6: Secondary_Use | I6: LAT | J6: LONG | K6: Address | L6: City | M6: State | N6: Lease_ID | O6: REIT_ID | P6: Ownership | Q6: Entity_Name | R6: ABS_Category | S6: KOIOS - BSM 2025 | T6: KOIOS - UTILITIES 2025 | U6: KOIOS - BSM 2026 | V6: KOIOS - UTILITIES 2026 | W6: Square Ft-Interior | X6: Rack Count | Y6: KIN COPPER_SUBS | Z6: KIN FIBER_SUBS | AA6: KIN TOTAL_SUBS | AB6: Drop MRR | AC6: Drop MRR (Non OM) | AD6: Pass Through MRR | AE6: Drop MRR Total | AF6: COLO_MRR | AG6: Overall MRR Total | AH6: Min LEASE_ID - ExecutionDate | AI6: Site Photo Link | AJ6: TA: Est. site MW capacity (sqft based) | AK6: MW>5? | AL6: Eye test site attractiveness | AM6: Eye test site attractiveness explanation | AN6: Mireye lookup code | AO6: Mireye results | AP6: Mireye recommendation
A7: Y | B7: Yes: 12k sqft + Owned | C7: ASLDKYXA | D7: WNS1701 | E7: Owned | F7: Building | G7: Central Office | I7: 38.4758 | J7: -82.64385 | K7: 619 15th Street | L7: Ashland | M7: KY | N7: B2193221111 | O7: 3469 | P7: REIT_ILEC | Q7: Windstream Kentucky East| LLC | R7: ABS 1 | S7: 80399.73 | T7: 247287.21 | U7: 15495.96 | V7: 97031.63 | W7: 34184 | X7: 232 | Y7: 223 | Z7: 1165 | AA7: 1388 | AB7: 23231.37 | AC7: 120711.48 | AD7: 101921.69 | AE7: 143942.85 | AF7: 0 | AG7: 143942.85 | AH7: 42881 | AI7: https://www.sitefotos.com/vpics/guestmapdev?c2k3m2 | AJ7: =W7*$C$3*$C$2/10^6 -> 6.4095 | AK7: Y | AL7: Low | AM7: Dense, residential neighborhood. Limited space. | AP7: =INDEX('Mireye Site Screen'!BU:BU, MATCH('Top 50'!$I7, 'Mireye Site Screen'!$C:$C, 0)) -> REVIEW (5-15 MW band)
B8: Yes: 12k sqft + Owned | C8: MEDSKYXA | D8: WNS1703 | E8: Owned | F8: Building | G8: Central Office | I8: 38.40965 | J8: -82.713032 | K8: 9216 Highway 60 | L8: Ashland | M8: KY | N8: ON216-KY-002 | P8: WIN_ILEC | Q8: Windstream Kentucky East| LLC | R8: ABS 1 | S8: 56902.92 | T8: 87147.61 | U8: 18735.57 | V8: 34174.83 | W8: 12209 | X8: 76 | Y8: 281 | Z8: 1025 | AA8: 1306 | AB8: 16039.46 | AC8: 39822.17 | AD8: 92545.24 | AE8: 55861.63 | AF8: 0 | AG8: 55861.63 | AI8: https://www.sitefotos.com/vpics/guestmapdev?r3f5f4 | AJ8: =W8*$C$3*$C$2/10^6 -> 2.2891875 | AM8: significant additional wooded space; commercial area; residential on single side of parcel, set back from edge
B9: Yes: 12k sqft + Owned | C9: BNBGOHXA | D9: WNS1052 | E9: Owned | F9: Building | G9: Central Office | I9: 41.385699 | J9: -81.340629 | K9: 8425 Baindridge Road | L9: Bainbridge | M9: OH | N9: ON080-OH-003 | O9: 2020 | P9: REIT_ILEC | Q9: Windstream Western Reserve| Inc. | R9: ABS 1 | S9: 31055.14 | T9: 57971.48 | U9: 12785.38 | V9: 19898.04 | W9: 14355 | X9: 64 | Y9: 285 | Z9: 474 | AA9: 759 | AB9: 1021 | AC9: 7569.59 | AD9: 18040.8 | AE9: 8590.59 | AF9: 0 | AG9: 8590.59 | AI9: https://www.google.com/maps/place/8425+Bainbridge+Rd,+Chagrin+Falls,+OH+44023/@41.385724,-81.3409919,102m/data=!3m1!1e3!4m12!1m5!3m4!2zNDHCsDIzJzA4LjYiTiA4McKwMjAnMjYuNCJX!8m2!3d41.38572!4d-81.34067!3m5!1s0x88311a7811e73ce9:0x8ae504c98819a4a0!8m2!3d41.3857038!4d-81.3406819!16s%2Fg%2F11b8v5dgqb?entry=ttu&amp;g_ep=EgoyMDI1MTAwNy4wIKXMDSoASAFQAw%3D%3D">Google Maps</a> | AJ9: =W9*$C$3*$C$2/10^6 -> 2.6915625 | AM9: some parking lot, commercial space, but highly residential around site
A10: Y | B10: Yes: 12k sqft + Owned | C10: CRNLGA01 | D10: WNS0048 | E10: Owned | F10: Building | G10: Central Office | I10: 34.497208 | J10: -83.549978 | K10: 2000 Communications Boulevard | L10: Baldwin | M10: GA | N10: B040009 | O10: 3405 | P10: REIT_ILEC | Q10: Windstream Standard| LLC | R10: ABS 2 | S10: 0 | T10: 131239.21 | U10: 0 | V10: 35861.89 | W10: 55823 | X10: 11 | Y10: 541 | Z10: 0 | AA10: 541 | AB10: 0 | AC10: 0 | AD10: 1299 | AE10: 0 | AF10: 0 | AG10: 0 | AH10: 31383 | AI10: https://sitefotos.com/vpics/guestmapdev?g4t5f6 | AJ10: =W10*$C$3*$C$2/10^6 -> 10.466812 | AK10: Y | AL10: Strong | AM10: Middle of a field basically. Nothing but room. | AN10: 1 | AO10: =INDEX('Mireye Site Screen'!BU:BU, MATCH('Top 50'!$AN10, 'Mireye Site Screen'!$A:$A, 0)) -> GO | AP10: =INDEX('Mireye Site Screen'!BV:BV, MATCH('Top 50'!$AN10, 'Mireye Site Screen'!$A:$A, 0)) -> Pursue first - open Georgia Power capacity inquiry now
B11: Yes - High Rack count | C11: BEREKYXA | D11: WNS1709 | E11: Owned | F11: Building | G11: Central Office | H11: Switch | I11: 37.573344 | J11: -84.285739 | K11: 310 Center Street | L11: Berea | M11: KY | N11: ON219-KY-003 | O11: 227 | P11: REIT_ILEC | Q11: Windstream Kentucky East| LLC | R11: ABS 1 | S11: 17800.04 | T11: 51712.55 | U11: 4044.87 | V11: 16119.02 | W11: 3242 | X11: 90 | Y11: 166 | Z11: 846 | AA11: 1012 | AB11: 15989.08 | AC11: 57335.17 | AD11: 59842.41 | AE11: 73324.25 | AF11: 0 | AG11: 73324.25 | AH11: 42881 | AI11: https://www.sitefotos.com/vpics/guestmapdev?q6e1d4 | AJ11: =W11*$C$3*$C$2/10^6 -> 0.607875 | AM11: corner of what looks like agricultural land.
B12: Yes: 12k sqft + Owned | C12: BRAROKXA | D12: WNS2324 | E12: Owned | F12: Building | G12: Central Office | H12: Switch | I12: 36.052614 | J12: -95.791826 | K12: 114 West Broadway | L12: Broken Arrow | M12: OK | N12: ON200-OK-005 | O12: 34 | P12: REIT_ILEC | Q12: Valor Telecommunications of Texas| LLC | R12: ABS 2 | S12: 42692.94 | T12: 104993.98 | U12: 18556.6 | V12: 34474.51 | W12: 17085 | X12: 150 | Y12: 526 | Z12: 1508 | AA12: 2034 | AB12: 14122.6 | AC12: 13377.91 | AD12: 45891.26 | AE12: 27500.51 | AF12: 1011.97 | AG12: 28512.48 | AI12: https://www.sitefotos.com/vpics/guestmapdev?p2x4k3 | AJ12: =W12*$C$3*$C$2/10^6 -> 3.2034375
B13: Yes: 12k sqft + Owned | C13: BRAROKXC | D13: WNS2325 | E13: Owned | F13: Building | G13: Central Office | H13: Switch | I13: 35.998678 | J13: -95.796852 | K13: 5301 South Elm Place W | L13: Broken Arrow | M13: OK | N13: ON200-OK-007 | O13: 41 | P13: REIT_ILEC | Q13: Valor Telecommunications of Texas| LLC | R13: ABS 2 | S13: 91043.67 | T13: 89430.4 | U13: 26395.93 | V13: 28858.43 | W13: 14330 | X13: 109 | Y13: 532 | Z13: 362 | AA13: 894 | AB13: 12002.37 | AC13: 3547.06 | AD13: 39317.23 | AE13: 15549.43 | AF13: 0 | AG13: 15549.43 | AI13: https://www.sitefotos.com/vpics/guestmapdev?w7d2n3 | AJ13: =W13*$C$3*$C$2/10^6 -> 2.686875
B14: Yes - High Rack count | C14: BRAROKXD | D14: WNS2327 | E14: Owned | F14: Building | G14: Central Office | H14: Switch | I14: 36.089602 | J14: -95.790558 | K14: 201 East Omaha Street | L14: Broken Arrow | M14: OK | N14: ON200-OK-009 | O14: 178 | P14: REIT_ILEC | Q14: Valor Telecommunications of Texas| LLC | R14: ABS 2 | S14: 38650.16 | T14: 47222.1 | U14: 2055.36 | V14: 21691.28 | W14: 4300 | X14: 106 | Y14: 396 | Z14: 404 | AA14: 800 | AB14: 13778.5 | AC14: 35254.89 | AD14: 35210.86 | AE14: 49033.39 | AF14: 0 | AG14: 49033.39 | AI14: https://www.sitefotos.com/vpics/guestmapdev?r2t1s4 | AJ14: =W14*$C$3*$C$2/10^6 -> 0.80625
B15: Yes: 12k sqft + Owned | C15: BWFDTXXA | E15: Owned | F15: Building | G15: Central Office | H15: Tower | I15: 33.17722 | J15: -102.27442 | K15: 101 East Tate | L15: Brownfield | M15: TX | N15: ON400-TX-1001 | O15: 2835 | P15: REIT_ILEC | R15: ABS 2 | S15: 0 | T15: 0 | U15: 0 | V15: 0 | W15: 12000 | X15: 93 | Y15: 291 | Z15: 714 | AA15: 1005 | AB15: 11734.8 | AC15: 39179.17 | AD15: 114449.47 | AE15: 50913.97 | AF15: 0 | AG15: 50913.97 | AH15: 42339 | AI15: https://www.sitefotos.com/vpics/guestmapdev?v4r7w8 | AJ15: =W15*$C$3*$C$2/10^6 -> 2.25
B16: Yes - High Rack count | C16: CMVLKYXA | D16: WNS1718 | E16: Owned | F16: Building | G16: Central Office | I16: 37.342599 | J16: -85.343916 | K16: 303 E Broadway | L16: Campbellsville | M16: KY | N16: ON219-KY-008 | P16: WIN_ILEC | Q16: Windstream Kentucky East| LLC | R16: ABS 2 | S16: 22230.25 | T16: 58783.53 | U16: 8095.15 | V16: 21965.42 | W16: 8877 | X16: 85 | Y16: 471 | Z16: 2243 | AA16: 2714 | AB16: 12345.65 | AC16: 70247.22 | AD16: 23338.55 | AE16: 82592.87 | AF16: 0 | AG16: 82592.87 | AH16: 42881 | AI16: https://www.google.com/maps/place/37%C2%B020'33.3%22N+85%C2%B020'38.1%22W/@37.3425844,-85.3445604,216m/data=!3m1!1e3!4m4!3m3!8m2!3d37.3425833!4d-85.3439167?entry=ttu&amp;g_ep=EgoyMDI1MTExNy4wIKXMDSoASAFQAw%3D%3D">Google Maps</a> | AJ16: =W16*$C$3*$C$2/10^6 -> 1.6644375
B17: Yes - High Rack count | C17: CNTNGAXA | D17: WNS1482 | E17: Owned | F17: Building | G17: Central Office | I17: 34.23611 | J17: -84.490655 | K17: 190 South Church Street | L17: Canton | M17: GA | N17: ON042-GA-105 | O17: 106 | P17: REIT_ILEC | Q17: Windstream Georgia Communications| LLC | R17: ABS 1 | S17: 30559.41 | T17: 126734.91 | U17: 11829.91 | V17: 41202.68 | W17: 7075 | X17: 81 | Y17: 602 | Z17: 368 | AA17: 970 | AB17: 30521.33 | AC17: 44090.74 | AD17: 38562.74 | AE17: 74612.07 | AF17: 0 | AG17: 74612.07 | AH17: 43137 | AI17: https://www.google.com/maps/place/Kinetic+Fiber+Internet+-+Canton+GA/@34.2301179,-84.4892039,112m/data=!3m1!1e3!4m15!1m8!3m7!1s0x88f565bbe68ef9af:0xbf14ffe07e1ed3ad!2s206+Longview+St,+Canton,+GA+30114!3b1!8m2!3d34.2301135!4d-84.488882!16s%2Fg%2F11l0nhqjn7!3m5!1s0x88f6c7e1263eea59:0x4040cd808668f9ea!8m2!3d34.2300248!4d-84.4881739!16s%2Fg%2F1vc6f7d_?entry=ttu&amp;g_ep=EgoyMDI1MTExNy4wIKXMDSoASAFQAw%3D%3D">Google Maps</a> | AJ17: =W17*$C$3*$C$2/10^6 -> 1.3265625
B18: Yes: 12k sqft + Owned | C18: CHRDOHXA | D18: WNS2244 | E18: Owned | F18: Building | G18: Central Office | I18: 41.581285 | J18: -81.202133 | K18: 205 South Hambden Street | L18: Chardon | M18: OH | N18: ON080-OH-044 | O18: 2659 | P18: REIT_ILEC | Q18: Windstream Western Reserve| Inc. | R18: ABS 1 | S18: 82937.03 | T18: 102360.37 | U18: 30699.82 | V18: 32185.13 | W18: 12446 | X18: 100 | Y18: 647 | Z18: 575 | AA18: 1222 | AB18: 4888.4 | AC18: 90111.32 | AD18: 14874.4 | AE18: 94999.72 | AF18: 0 | AG18: 94999.72 | AI18: https://www.sitefotos.com/vpics/guestmapdev?k0u2x5 | AJ18: =W18*$C$3*$C$2/10^6 -> 2.333625
B19: Yes: 12k sqft + Owned | C19: CHTHOKXD | E19: Owned | F19: Building | G19: Central Office | I19: 35.470961 | J19: -95.523631 | K19: 115 Northwest 1st Street | L19: Checotah | M19: OK | N19: ON200-OK-010 | O19: 302 | P19: REIT_ILEC | Q19: Valor Telecommunications of Texas| LLC | R19: ABS 2 | S19: 0 | T19: 0 | U19: 0 | V19: 0 | W19: 20000 | X19: 21 | Y19: 290 | Z19: 499 | AA19: 789 | AB19: 3684 | AC19: 3256.33 | AD19: 1292 | AE19: 6940.33 | AF19: 0 | AG19: 6940.33 | AH19: 42339 | AI19: https://www.google.com/maps/place/130+Howell+Dr,+Elizabethtown,+KY+42701/@37.7137354,-85.8271202,860m/data=!3m2!1e3!4b1!4m6!3m5!1s0x8868ef14cb372ebf:0xa1909efe4828c1f5!8m2!3d37.7137312!4d-85.8245453!16s%2Fg%2F11bw4nx7h4?entry=ttu&amp;g_ep=EgoyMDI2MDIwNC4wIKXMDSoASAFQAw%3D%3D">Google Maps</a> | AJ19: =W19*$C$3*$C$2/10^6 -> 3.75
B20: Yes: 12k sqft + Owned | C20: CHGVNCXA | D20: WNS1906 | E20: Owned | F20: Building | G20: Central Office | I20: 35.556922 | J20: -80.595882 | K20: 1525 South Main Street | L20: China Grove | M20: NC | N20: B018190 | O20: 2511 | P20: REIT_ILEC | Q20: Windstream Concord Telephone| LLC | R20: ABS 2 | S20: 16498.61 | T20: 24010.91 | U20: 17096.62 | V20: 7610.97 | W20: 12000 | X20: 38 | Y20: 184 | Z20: 1898 | AA20: 2082 | AB20: 6142 | AC20: 3830.7 | AD20: 85095.52 | AE20: 9972.7 | AF20: 0 | AG20: 9972.7 | AH20: 41883 | AI20: https://www.sitefotos.com/vpics/guestmapdev?n7j7q5 | AJ20: =W20*$C$3*$C$2/10^6 -> 2.25
B21: Yes - High Rack count | C21: CLEVGAXA | D21: WNS1491 | E21: Owned | F21: Building | G21: Central Office | I21: 34.597027 | J21: -83.766127 | K21: 158 West Kytle Street | L21: Cleveland | M21: GA | N21: ON040-GA-120 | O21: 200 | P21: REIT_ILEC | Q21: Windstream Standard| LLC | R21: ABS 1 | S21: 11195.13 | T21: 113494.35 | U21: 5552.62 | V21: 37854.63 | W21: 3688 | X21: 124 | Y21: 1025 | Z21: 257 | AA21: 1282 | AB21: 10847.39 | AC21: 71876.55 | AD21: 64725.86 | AE21: 82723.94 | AF21: 0 | AG21: 82723.94 | AH21: 42881 | AI21: https://sitefotos.com/vpics/guestmapdev?e5b4u1 | AJ21: =W21*$C$3*$C$2/10^6 -> 0.6915
A22: Y | B22: Yes - High Rack count | C22: CMRCGAXA | D22: WNS1495 | E22: Owned | F22: Building | G22: Central Office | I22: 34.203976 | J22: -83.459471 | K22: 45 Georgia Avenue | L22: Commerce | M22: GA | N22: ON041-GA-001 | O22: 76 | P22: REIT_ILEC | Q22: Windstream Georgia| LLC | R22: ABS 1 | S22: 52795.68 | T22: 300789.85 | U22: 21756.39 | V22: 113603.09 | W22: 9417 | X22: 128 | Y22: 815 | Z22: 465 | AA22: 1280 | AB22: 192014.29 | AC22: 208054.34 | AD22: 263492.71 | AE22: 400068.63 | AF22: 0 | AG22: 400068.63 | AH22: 42881 | AI22: https://sitefotos.com/vpics/guestmapdev?o0d4c1 | AJ22: =W22*$C$3*$C$2/10^6 -> 1.7656875
A23: Y | B23: Yes: 12k sqft + Owned | C23: ELYROHXA | D23: WNS2262 | E23: Owned | F23: Building | G23: Central Office | I23: 41.365741 | J23: -82.109993 | K23: 363 3rd Street | L23: Elyria | M23: OH | N23: B158010 | O23: 2674 | P23: REIT_ILEC | Q23: Windstream Ohio| LLC | R23: ABS 1 | S23: 94411.73 | T23: 341674.15 | U23: 37852.57 | V23: 100578.63 | W23: 73218 | X23: 159 | Y23: 1304 | Z23: 1087 | AA23: 2391 | AB23: 2448.53 | AC23: 61314.71 | AD23: 48268.88 | AE23: 63763.24 | AF23: 0 | AG23: 63763.24 | AH23: 42881 | AI23: https://www.sitefotos.com/vpics/guestmapdev?i3h7y0 | AJ23: =W23*$C$3*$C$2/10^6 -> 13.728375 | AK23: Y | AL23: Medium | AM23: Some parking lot, commercial space, but highly residential around site | AP23: =INDEX('Mireye Site Screen'!BU:BU, MATCH('Top 50'!$I23, 'Mireye Site Screen'!$C:$C, 0)) -> #N/A
A24: Y | B24: Yes: 12k sqft + Owned | C24: FTZGGAXA | D24: WNS1514 | E24: Owned | F24: Building | G24: Central Office | I24: 31.715144 | J24: -83.253794 | K24: 110 East Central | L24: Fitzgerald | M24: GA | N24: ON042-GA-132 | O24: 35 | P24: REIT_ILEC | Q24: Windstream Georgia Communications| LLC | R24: ABS 2 | S24: 46961.1 | T24: 316512.79 | U24: 15698.45 | V24: 74237.68 | W24: 16821 | X24: 92 | Y24: 442 | Z24: 1527 | AA24: 1969 | AB24: 242075.11 | AC24: 312077.57 | AD24: 173549.1 | AE24: 554152.68 | AF24: 0 | AG24: 554152.68 | AH24: 42767 | AI24: https://sitefotos.com/vpics/guestmapdev?g7s2j2 | AJ24: =W24*$C$3*$C$2/10^6 -> 3.1539375
B25: Yes: 12k sqft + Owned | C25: GENVOHXA | D25: WNS2267 | E25: Owned | F25: Building | G25: Central Office | I25: 41.805317 | J25: -80.945672 | K25: 37 South Forest Street | L25: Geneva | M25: OH | N25: ON080-OH-040 | O25: 51 | P25: REIT_ILEC | Q25: Windstream Western Reserve| Inc. | R25: ABS 1 | S25: 43683.77 | T25: 37088.83 | U25: 14547.93 | V25: 13944.09 | W25: 12477 | X25: 25 | Y25: 326 | Z25: 797 | AA25: 1123 | AB25: 3910 | AC25: 4547.86 | AD25: 9739.4 | AE25: 8457.86 | AF25: 0 | AG25: 8457.86 | AI25: https://www.sitefotos.com/vpics/guestmapdev?a0g2a6 | AJ25: =W25*$C$3*$C$2/10^6 -> 2.3394375
B26: Yes: 12k sqft + Owned | C26: GNBRARXA | D26: WNS1370 | E26: Owned | F26: Building | G26: Central Office | I26: 35.232663 | J26: -92.388351 | K26: 9 South Broadview Street | L26: Greenbrier | M26: AR | N26: ON202-AR-013 | O26: 2298 | P26: REIT_ILEC | Q26: Windstream Arkansas| LLC | R26: ABS 1 | S26: 57457.22 | T26: 86295.67 | U26: 23436.5 | V26: 19649.56 | W26: 20000 | X26: 64 | Y26: 331 | Z26: 324 | AA26: 655 | AB26: 8811.8 | AC26: 20476.55 | AD26: 63414.33 | AE26: 29288.35 | AF26: 0 | AG26: 29288.35 | AH26: 42881 | AI26: https://www.sitefotos.com/vpics/guestmapdev?e4o1u0 | AJ26: =W26*$C$3*$C$2/10^6 -> 3.75
A27: Y | B27: Yes: 12k sqft + Owned | C27: GRNLIAXC | D27: WNS1631 | E27: Owned | F27: Building | G27: Central Office | I27: 41.74517 | J27: -92.725415 | K27: 1010 Main Street | L27: Grinnell | M27: IA | N27: ON132-IA-1181 | O27: 37 | P27: REIT_ILEC | Q27: Windstream Iowa Communications| Inc. | R27: ABS 2 | S27: 37252.22 | T27: 109942.31 | U27: 21509.57 | V27: 40362.96 | W27: 15723 | X27: 84 | Y27: 648 | Z27: 595 | AA27: 1243 | AB27: 86783.49 | AC27: 175897.93 | AD27: 71294.07 | AE27: 262681.42 | AF27: 21 | AG27: 262702.42 | AI27: https://www.sitefotos.com/vpics/guestmapdev?s1u7o1 | AJ27: =W27*$C$3*$C$2/10^6 -> 2.9480625
B28: Yes: 12k sqft + Owned | C28: HRSNARXA | E28: Owned | F28: Building | G28: Central Office | I28: 36.214283 | J28: -93.079052 | K28: 202 Graham Street | L28: Harrison | M28: AR | N28: B202322 | O28: 1392 | P28: REIT_ILEC | Q28: Windstream Arkansas| LLC | R28: ABS 1 | S28: 149943.27 | T28: 97350.18 | U28: 58606.83 | V28: 23685.58 | W28: 21579 | X28: 81 | Y28: 472 | Z28: 144 | AA28: 616 | AB28: 12764 | AC28: 53237.64 | AD28: 52403.81 | AE28: 66001.64 | AF28: 0 | AG28: 66001.64 | AH28: 41831 | AI28: https://www.sitefotos.com/vpics/guestmapdev?o8a8x4 | AJ28: =W28*$C$3*$C$2/10^6 -> 4.0460625 | AK28: Y | AL28: Strong | AM28: Middle of a field basically. Room for days. | AN28: 2 | AO28: =INDEX('Mireye Site Screen'!BU:BU, MATCH('Top 50'!$AN28, 'Mireye Site Screen'!$A:$A, 0)) -> GO (leaning) | AP28: =INDEX('Mireye Site Screen'!BV:BV, MATCH('Top 50'!$AN28, 'Mireye Site Screen'!$A:$A, 0)) -> Pursue #2 - geotech karst study for expansion footprint + Entergy capacity inquiry in parallel
A29: Y | B29: Yes: 12k sqft + Owned | C29: HZRDKYXA | D29: WNS1739 | E29: Owned | F29: Building | G29: Central Office | I29: 37.249865 | J29: -83.19392 | K29: 101 Winterberry Drive | L29: Hazard | M29: KY | N29: ON219-KY-021 | O29: 42 | P29: REIT_ILEC | Q29: Windstream Kentucky East| LLC | R29: ABS 1 | S29: 46258.55 | T29: 118939.09 | U29: 9698.41 | V29: 42853.88 | W29: 14149 | X29: 133 | Y29: 624 | Z29: 1401 | AA29: 2025 | AB29: 48976.38 | AC29: 165196.62 | AD29: 31654.32 | AE29: 214173 | AF29: 0 | AG29: 214173 | AH29: 42614 | AI29: https://www.sitefotos.com/vpics/guestmapdev?i6e5b4 | AJ29: =W29*$C$3*$C$2/10^6 -> 2.6529375
A30: Y | B30: Yes: 12k sqft + Owned | C30: HDSNOHXB | D30: WNS1063 | E30: Owned | F30: Building | G30: Central Office | I30: 41.217063 | J30: -81.442508 | K30: 1300 Terex Road | L30: Hudson | M30: OH | N30: ON080-OH-015 | O30: 2031 | P30: REIT_ILEC | Q30: Windstream Western Reserve| Inc. | R30: ABS 1 | S30: 10196.96 | T30: 22058.62 | U30: 3969.1 | V30: 5551.47 | W30: 29978 | X30: 20 | Y30: 167 | Z30: 5 | AA30: 172 | AB30: 390 | AC30: 3113 | AD30: 481 | AE30: 3503 | AF30: 0 | AG30: 3503 | AI30: https://www.sitefotos.com/vpics/guestmapdev?u1a0v7 | AJ30: =W30*$C$3*$C$2/10^6 -> 5.620875 | AK30: Y | AL30: Strong | AM30: Corner of what looks like agricultural land. | AN30: 3 | AO30: =INDEX('Mireye Site Screen'!BU:BU, MATCH('Top 50'!$AN30, 'Mireye Site Screen'!$A:$A, 0)) -> REVIEW | AP30: =INDEX('Mireye Site Screen'!BV:BV, MATCH('Top 50'!$AN30, 'Mireye Site Screen'!$A:$A, 0)) -> Advance - gauge Hudson Public Power capacity appetite for the increment; spec Tier 4 gensets
A31: Y | B31: Yes: 12k sqft + Owned | C31: HDSNOHXA | D31: WNS2275 | E31: Owned | F31: Building | G31: Central Office | I31: 41.243414 | J31: -81.440034 | K31: 245 North Main Street | L31: Hudson | M31: OH | N31: ON080-OH-043 | O31: 3800 | P31: REIT_ILEC | Q31: Windstream Western Reserve| Inc. | R31: ABS 1 | S31: 151219.15 | T31: 292937.87 | U31: 42853.14 | V31: 87782.52 | W31: 18705 | X31: 170 | Y31: 486 | Z31: 241 | AA31: 727 | AB31: 119468.81 | AC31: 211677.8 | AD31: 26906.52 | AE31: 331146.61 | AF31: 0 | AG31: 331146.61 | AH31: 39417 | AI31: https://sitefotos.com/vpics/guestmapdev?u6l0o6 | AJ31: =W31*$C$3*$C$2/10^6 -> 3.5071875
B32: Yes: 12k sqft + Owned | C32: KRVLTXXA | D32: WNS2631 | E32: Owned | F32: Building | G32: Central Office | I32: 30.045348 | J32: -99.139977 | K32: 812 Water Street | L32: Kerrville | M32: TX | N32: ON810-TX-009 | O32: 2899 | P32: REIT_ILEC | Q32: Windstream Communications Kerrville| LLC | R32: ABS 1 | S32: 44982.18 | T32: 68041.94 | U32: 10368.24 | V32: 23709.36 | W32: 24782 | X32: 144 | Y32: 720 | Z32: 787 | AA32: 1507 | AB32: 13942.9 | AC32: 48060.79 | AD32: 4423 | AE32: 62003.69 | AF32: 0 | AG32: 62003.69 | AH32: 39507 | AI32: https://www.sitefotos.com/vpics/guestmapdev?g2e5m3 | AJ32: =W32*$C$3*$C$2/10^6 -> 4.646625 | AK32: Y | AL32: Medium/Low | AM32: Dense industrial area. Parking lot behind but expect it may be too dense. | AP32: =INDEX('Mireye Site Screen'!BU:BU, MATCH('Top 50'!$I32, 'Mireye Site Screen'!$C:$C, 0)) -> #N/A
B33: Yes: 12k sqft + Owned | C33: LVLDTXXA | D33: WNS2638 | E33: Owned | F33: Building | G33: Central Office | H33: Tower | I33: 33.588056 | J33: -102.37954 | K33: 506 Avenue I | L33: Levelland | M33: TX | N33: ON400-01-054 | O33: 2215 | P33: REIT_ILEC | Q33: Valor Telecommunications of Texas| LLC | R33: ABS 2 | S33: 62293.72 | T33: 37529.42 | U33: 20677.18 | V33: 15123.29 | W33: 12108 | X33: 75 | Y33: 280 | Z33: 684 | AA33: 964 | AB33: 8290 | AC33: 24438.57 | AD33: 3619 | AE33: 32728.57 | AF33: 0 | AG33: 32728.57 | AH33: 42583 | AI33: https://www.sitefotos.com/vpics/guestmapdev?p2h0f6 | AJ33: =W33*$C$3*$C$2/10^6 -> 2.27025
B34: Yes: 12k sqft + Owned | C34: LVOKFLXA | D34: WNS1448 | E34: Owned | F34: Building | G34: Central Office | I34: 30.293973 | J34: -82.982079 | K34: 206 White Avenue SE | L34: Live Oak | M34: FL | N34: ON047-FL-1012 | O34: 2347 | P34: REIT_ILEC | Q34: Windstream Florida| Inc. | R34: ABS 2 | S34: 177616.39 | T34: 165791.72 | U34: 20604.42 | V34: 59604.05 | W34: 21370 | X34: 123 | Y34: 774 | Z34: 856 | AA34: 1630 | AB34: 67011.38 | AC34: 100782.94 | AD34: 50269.76 | AE34: 167794.32 | AF34: 1027.52 | AG34: 168821.84 | AH34: 39173 | AI34: https://www.google.com/maps/place/30%C2%B017'38.3%22N+82%C2%B058'56.0%22W/@30.2939734,-82.9828659,179m/data=!3m2!1e3!4b1!4m4!3m3!8m2!3d30.2939722!4d-82.9822222?entry=ttu&amp;g_ep=EgoyMDI2MDIyNC4wIKXMDSoASAFQAw%3D%3D">Google Maps</a> | AJ34: =W34*$C$3*$C$2/10^6 -> 4.006875 | AK34: Y | AL34: Medium | AM34: Relatively dense commercial + residential | AP34: =INDEX('Mireye Site Screen'!BU:BU, MATCH('Top 50'!$I34, 'Mireye Site Screen'!$C:$C, 0)) -> #N/A
B35: Yes: 12k sqft + Owned | C35: MDVLGAXA | D35: WNS1550 | E35: Owned | F35: Building | G35: Central Office | I35: 33.090815 | J35: -83.228473 | K35: 750 North Jefferson Street | L35: Milledgeville | M35: GA | N35: ON042-GA-103 | O35: 19 | P35: REIT_ILEC | Q35: Windstream Georgia Communications| LLC | R35: ABS 2 | S35: 86249.72 | T35: 156249.37 | U35: 45893.97 | V35: 50239.29 | W35: 25764 | X35: 93 | Y35: 1016 | Z35: 346 | AA35: 1362 | AB35: 40278.47 | AC35: 76847.68 | AD35: 212148.55 | AE35: 117126.15 | AF35: 0 | AG35: 117126.15 | AH35: 42881 | AI35: https://sitefotos.com/vpics/guestmapdev?t5n6n8 | AJ35: =W35*$C$3*$C$2/10^6 -> 4.83075 | AK35: Y | AL35: Medium | AM35: Space on the block but looks like it's residential; expect limited availability; exception is relatively large parking space which seems to serve only this building. | AP35: =INDEX('Mireye Site Screen'!BU:BU, MATCH('Top 50'!$I35, 'Mireye Site Screen'!$C:$C, 0)) -> #N/A
A36: Y | B36: Yes: 12k sqft + Owned | C36: MRHDKYXA | D36: WNS1776 | E36: Owned | F36: Building | G36: Central Office | H36: Switch | I36: 38.183664 | J36: -83.434779 | K36: 154 East 2nd Street | L36: Morehead | M36: KY | N36: ON219-KY-033 | O36: 23 | P36: REIT_ILEC | Q36: Windstream Kentucky East| LLC | R36: ABS 1 | S36: 37578.36 | T36: 109271.36 | U36: 6631.25 | V36: 39402.98 | W36: 23104 | X36: 160 | Y36: 263 | Z36: 407 | AA36: 670 | AB36: 17854.9 | AC36: 107767.71 | AD36: 81907.1 | AE36: 125622.61 | AF36: 0 | AG36: 125622.61 | AI36: https://www.sitefotos.com/vpics/guestmapdev?q5b1t3 | AJ36: =W36*$C$3*$C$2/10^6 -> 4.332 | AK36: Y | AL36: Medium | AM36: Relatively dense commercial | AP36: =INDEX('Mireye Site Screen'!BU:BU, MATCH('Top 50'!$I36, 'Mireye Site Screen'!$C:$C, 0)) -> #N/A
B37: Yes: 12k sqft + Owned | C37: MLTRGAXA | D37: WNS1556 | E37: Owned | F37: Building | G37: Central Office | I37: 31.177483 | J37: -83.783714 | K37: 216 4th Street SE | L37: Moultrie | M37: GA | N37: ON042-GA-131 | O37: 20 | P37: REIT_ILEC | Q37: Windstream Georgia Communications| LLC | R37: ABS 1 | S37: 44518.26 | T37: 130268.76 | U37: 32316.68 | V37: 39313.9 | W37: 25380 | X37: 89 | Y37: 460 | Z37: 2509 | AA37: 2969 | AB37: 13721 | AC37: 107934.84 | AD37: 34945.33 | AE37: 121655.84 | AF37: 0 | AG37: 121655.84 | AH37: 42881 | AI37: https://sitefotos.com/vpics/guestmapdev?u2o1q0 | AJ37: =W37*$C$3*$C$2/10^6 -> 4.75875 | AK37: Y | AL37: Medium/Strong | AM37: Space on the lot but relatively dense around it | AN37: 4 | AO37: =INDEX('Mireye Site Screen'!BU:BU, MATCH('Top 50'!$AN37, 'Mireye Site Screen'!$A:$A, 0)) -> REVIEW | AP37: =INDEX('Mireye Site Screen'!BV:BV, MATCH('Top 50'!$AN37, 'Mireye Site Screen'!$A:$A, 0)) -> Hold as OZ-advantaged backup; Phase I environmental if advanced
B38: Yes: 12k sqft + Owned | C38: MLTRGA05 | D38: WNS0398 | E38: Owned | F38: Building | G38: Central Office | H38: Warehouse | I38: 31.17919 | J38: -83.748761 | K38: 282 Industrial Drive | L38: Moultrie | M38: GA | N38: B042274 | O38: 3432 | P38: REIT_ILEC | Q38: Windstream Georgia Communications| LLC | R38: ABS 1 | S38: 63723.57 | T38: 35179.59 | U38: 23980.62 | V38: 9833.75 | W38: 15016 | X38: 4 | Y38: 0 | Z38: 0 | AA38: 0 | AB38: 0 | AC38: 0 | AD38: 0 | AE38: 0 | AF38: 0 | AG38: 0 | AI38: https://www.sitefotos.com/vpics/guestmapdev?g0p7o8 | AJ38: =W38*$C$3*$C$2/10^6 -> 2.8155
A39: Y | B39: Yes: 12k sqft + Owned | C39: NWRKOHXA | D39: WNS2289 | E39: Owned | F39: Building | G39: Central Office | I39: 40.059449 | J39: -82.404873 | K39: 66 North 4th Street | L39: Newark | M39: OH | N39: ON158-OH-024 | O39: 2693 | P39: REIT_ILEC | Q39: Windstream Ohio| LLC | R39: ABS 2 | S39: 49396.64 | T39: 121164.43 | U39: 30226.23 | V39: 45375.08 | W39: 35563 | X39: 145 | Y39: 717 | Z39: 1236 | AA39: 1953 | AB39: 6099.45 | AC39: 28989.82 | AD39: 57489.56 | AE39: 35089.27 | AF39: 0 | AG39: 35089.27 | AI39: https://www.sitefotos.com/vpics/guestmapdev?d8r3s3 | AJ39: =W39*$C$3*$C$2/10^6 -> 6.6680625 | AK39: Y | AL39: Medium/Strong | AM39: Little to no room for expansion, but enough interior sq ft for significant MW IT if power available | AN39: 5 | AO39: =INDEX('Mireye Site Screen'!BU:BU, MATCH('Top 50'!$AN39, 'Mireye Site Screen'!$A:$A, 0)) -> REVIEW (5-15 MW band) | AP39: =INDEX('Mireye Site Screen'!BV:BV, MATCH('Top 50'!$AN39, 'Mireye Site Screen'!$A:$A, 0)) -> Keep as low-band expansion candidate - AEP capacity inquiry decides it
A40: Y | B40: Yes: 12k sqft + Owned | C40: NWTNIAXC | D40: WNS1656 | E40: Owned | F40: Building | G40: Central Office | I40: 41.698332 | J40: -93.054486 | K40: 115 S Second Ave W | L40: Newton | M40: IA | N40: ON132-IA-01178 | O40: 2411 | P40: REIT_ILEC | Q40: Windstream Iowa Communications| Inc. | R40: ABS 2 | S40: 143343.34 | T40: 91808.72 | U40: 31658.36 | V40: 22200.06 | W40: 43934 | X40: 60 | Y40: 862 | Z40: 1789 | AA40: 2651 | AB40: 7531.78 | AC40: 39884.18 | AD40: 90116.1 | AE40: 47415.96 | AF40: 0 | AG40: 47415.96 | AI40: https://www.sitefotos.com/vpics/guestmapdev?v2o0r3 | AJ40: =W40*$C$3*$C$2/10^6 -> 8.237625 | AK40: Y | AL40: Medium/Strong | AM40: Lot is ~4x building footprint currently incl. parking; commercial + residential surrounding | AN40: 6 | AO40: =INDEX('Mireye Site Screen'!BU:BU, MATCH('Top 50'!$AN40, 'Mireye Site Screen'!$A:$A, 0)) -> REVIEW | AP40: =INDEX('Mireye Site Screen'!BV:BV, MATCH('Top 50'!$AN40, 'Mireye Site Screen'!$A:$A, 0)) -> Hold - verify Alliant service, assemblage, and Uniti lease terms; mid-tier
B41: Yes - High Rack count | C41: NCVLKYXA | D41: WNS1784 | E41: Owned | F41: Building | G41: Central Office | I41: 37.880671 | J41: -84.572366 | K41: 105 North York Street | L41: Nicholasville | M41: KY | N41: ON219-KY-035 | O41: 123 | P41: REIT_ILEC | Q41: Windstream Kentucky East| LLC | R41: ABS 1 | S41: 22704.46 | T41: 83234.99 | U41: 9764.05 | V41: 22830.17 | W41: 6190 | X41: 121 | Y41: 335 | Z41: 1385 | AA41: 1720 | AB41: 19185.03 | AC41: 26962.61 | AD41: 49596.69 | AE41: 46147.64 | AF41: 0 | AG41: 46147.64 | AI41: https://www.sitefotos.com/vpics/guestmapdev?e7q8w5 | AJ41: =W41*$C$3*$C$2/10^6 -> 1.160625
A42: Y | B42: Yes: 12k sqft + Owned | C42: NRFDOHXA | D42: WNS2297 | E42: Owned | F42: Building | G42: Central Office | I42: 41.314744 | J42: -81.537039 | K42: 54 Leonard Avenue | L42: Northfield | M42: OH | N42: B080033 | O42: 2701 | P42: REIT_ILEC | Q42: Windstream Western Reserve| Inc. | R42: ABS 1 | S42: 53064.32 | T42: 123417.05 | U42: 33189.06 | V42: 36876.69 | W42: 66721 | X42: 93 | Y42: 371 | Z42: 960 | AA42: 1331 | AB42: 4919.5 | AC42: 34006.75 | AD42: 24440.44 | AE42: 38926.25 | AF42: 0 | AG42: 38926.25 | AI42: https://www.sitefotos.com/vpics/guestmapdev?q4k0k6 | AJ42: =W42*$C$3*$C$2/10^6 -> 12.510188 | AK42: Y | AL42: Strong | AM42: Significant existing interior sq ft; significant lot space for expansion | AN42: 7 | AO42: =INDEX('Mireye Site Screen'!BU:BU, MATCH('Top 50'!$AN42, 'Mireye Site Screen'!$A:$A, 0)) -> REVIEW | AP42: =INDEX('Mireye Site Screen'!BV:BV, MATCH('Top 50'!$AN42, 'Mireye Site Screen'!$A:$A, 0)) -> Rises under operating-facility lens - verify serving utility (FirstEnergy?) + assemblage, then utility capacity inquiry on the 345 kV path
B43: Yes - High Rack count | C43: PRRYGAXA | D43: WNS1566 | E43: Owned | F43: Building | G43: Central Office | I43: 32.457382 | J43: -83.732627 | K43: 910 Main Street | L43: Perry | M43: GA | N43: ON042-GA-073 | O43: 133 | P43: REIT_ILEC | Q43: Windstream Georgia Communications| LLC | R43: ABS 1 | S43: 18113.29 | T43: 90112.32 | U43: 3981.92 | V43: 29397.49 | W43: 5775 | X43: 95 | Y43: 648 | Z43: 1054 | AA43: 1702 | AB43: 18123.95 | AC43: 34747.53 | AD43: 124837.6 | AE43: 52871.48 | AF43: 1402.12 | AG43: 54273.6 | AH43: 43282 | AI43: https://sitefotos.com/vpics/guestmapdev?g3t5o5 | AJ43: =W43*$C$3*$C$2/10^6 -> 1.0828125
B44: Yes: 12k sqft + Owned | C44: RCFDOHXA | E44: Owned | F44: Building | G44: Central Office | I44: 41.239257 | J44: -81.655758 | K44: 4676 West Streetsboro Road | L44: Richfield | M44: OH | N44: ON080-OH-1004 | O44: 2707 | P44: REIT_ILEC | Q44: Windstream Western Reserve| Inc. | R44: ABS 1 | S44: 0 | T44: 0 | U44: 0 | V44: 0 | W44: 20000 | X44: 27 | Y44: 212 | Z44: 423 | AA44: 635 | AB44: 5793.04 | AC44: 84385.62 | AD44: 7660.89 | AE44: 90178.66 | AF44: 0 | AG44: 90178.66 | AI44: https://www.google.com/maps/place/130+Howell+Dr,+Elizabethtown,+KY+42701/@37.7137354,-85.8271202,860m/data=!3m2!1e3!4b1!4m6!3m5!1s0x8868ef14cb372ebf:0xa1909efe4828c1f5!8m2!3d37.7137312!4d-85.8245453!16s%2Fg%2F11bw4nx7h4?entry=ttu&amp;g_ep=EgoyMDI2MDIwNC4wIKXMDSoASAFQAw%3D%3D">Google Maps</a> | AJ44: =W44*$C$3*$C$2/10^6 -> 3.75
A45: Y | B45: Yes: 12k sqft + Owned | C45: TRNYTXXH | D45: WNS1293 | E45: Owned | F45: Building | G45: Central Office | I45: 30.85154 | J45: -95.40012 | K45: 75 FRONT ST @ F.M. 980 Riverside TX 77367 US | L45: Riverside | M45: TX | N45: O400-TX-053672 | P45: WIN_ILEC | Q45: Valor | R45: ABS 2 | S45: 4543.06 | T45: 17203.77 | U45: 1549.4 | V45: 6700.45 | W45: 42400 | X45: 10 | Y45: 231 | Z45: 5 | AA45: 236 | AB45: 0 | AC45: 924 | AD45: 0 | AE45: 924 | AF45: 0 | AG45: 924 | AI45: https://www.sitefotos.com/vpics/guestmapdev?e8d1r3 | AJ45: =W45*$C$3*$C$2/10^6 -> 7.95 | AK45: Y | AL45: Strong | AM45: Significant additional space on lot; minimal density surrounding | AN45: 8 | AO45: =INDEX('Mireye Site Screen'!BU:BU, MATCH('Top 50'!$AN45, 'Mireye Site Screen'!$A:$A, 0)) -> NO-GO (flood) | AP45: =INDEX('Mireye Site Screen'!BV:BV, MATCH('Top 50'!$AN45, 'Mireye Site Screen'!$A:$A, 0)) -> Park - spend ~$2k on elevation certificate; revive only if LOMA path viable
B46: Yes: 12k sqft + Owned | C46: SYMRTXXA | D46: WNS2709 | E46: Owned | F46: Building | G46: Central Office | H46: Tower | I46: 33.591359 | J46: -99.260073 | K46: 400 North Main Street | L46: Seymour | M46: TX | N46: ON400-TX-197 | O46: 36 | P46: REIT_ILEC | Q46: Valor Telecommunications of Texas| LLC | R46: ABS 1 | S46: 111480.26 | T46: 164773.62 | U46: 32901.23 | V46: 43914.86 | W46: 16690 | X46: 54 | Y46: 283 | Z46: 667 | AA46: 950 | AB46: 7595 | AC46: 25151.77 | AD46: 9368.14 | AE46: 32746.77 | AF46: 45.58 | AG46: 32792.35 | AH46: 39855 | AI46: https://www.sitefotos.com/vpics/guestmapdev?x7r0j2 | AJ46: =W46*$C$3*$C$2/10^6 -> 3.129375
A47: Y | B47: Yes: 12k sqft + Owned | C47: SGLDTXXE | D47: WNS2726 | E47: Owned | F47: Building | G47: Central Office | I47: 29.636252 | J47: -95.598181 | K47: 12626 Dairy Ashford Road | L47: Sugar Land | M47: TX | N47: ON209-TX-014 | O47: 26 | P47: REIT_ILEC | Q47: Windstream Sugar Land| Inc. | R47: ABS 2 | S47: 26919.01 | T47: 110332.84 | U47: 10148.72 | V47: 33553.73 | W47: 20815 | X47: 159 | Y47: 393 | Z47: 228 | AA47: 621 | AB47: 60980.73 | AC47: 142333.73 | AD47: 30063.88 | AE47: 203314.46 | AF47: 3824.02 | AG47: 207138.48 | AI47: https://www.sitefotos.com/vpics/guestmapdev?i7m7q2 | AJ47: =W47*$C$3*$C$2/10^6 -> 3.9028125 | AK47: Y | AL47: Medium/Strong | AM47: Limited additional space on lot; BUT looks like multiple empty lots adjoining | AO47: 2
B48: Yes: 12k sqft + Owned | C48: SGLDTXXD | D48: WNS2722 | E48: Owned | F48: Building | G48: Central Office | I48: 29.586082 | J48: -95.620715 | K48: 1850 Austin Parkway | L48: Sugar Land | M48: TX | N48: ON209-TX-013 | O48: 2946 | P48: REIT_ILEC | Q48: Windstream Sugar Land| Inc. | R48: ABS 2 | S48: 27441.88 | T48: 52597.95 | U48: 6637.73 | V48: 13311.14 | W48: 20000 | X48: 64 | Y48: 718 | Z48: 368 | AA48: 1086 | AB48: 10990.23 | AC48: 14205.04 | AD48: 21875.66 | AE48: 25195.27 | AF48: 0 | AG48: 25195.27 | AI48: https://www.google.com/maps/place/29%C2%B035'09.9%22N+95%C2%B037'14.6%22W/@29.5860919,-95.6213714,236m/data=!3m2!1e3!4b1!4m4!3m3!8m2!3d29.5860907!4d-95.6207277?entry=ttu&amp;g_ep=EgoyMDI2MDIyNC4wIKXMDSoASAFQAw%3D%3D">Google Maps</a> | AJ48: =W48*$C$3*$C$2/10^6 -> 3.75
B49: Yes: 12k sqft + Owned | C49: SWNYTXXA | D49: WNS2733 | E49: Owned | F49: Building | G49: Central Office | I49: 29.038604 | J49: -95.699574 | K49: 202 Pecan Street | L49: Sweeny | M49: TX | N49: ON209-TX-019 | O49: 3225 | P49: REIT_ILEC | Q49: Windstream Sugar Land| Inc. | R49: ABS 2 | S49: 26297.8 | T49: 24504.66 | U49: 24898.86 | V49: 11673.25 | W49: 12000 | X49: 29 | Y49: 371 | Z49: 528 | AA49: 899 | AB49: 4759 | AC49: 4056.82 | AD49: 0 | AE49: 8815.82 | AF49: 0 | AG49: 8815.82 | AH49: 42881 | AI49: https://www.sitefotos.com/vpics/guestmapdev?k6p1p5 | AJ49: =W49*$C$3*$C$2/10^6 -> 2.25
B50: Yes: 12k sqft + Owned | C50: TOLDIAXO | D50: WNS1669 | E50: Owned | F50: Building | G50: Central Office | I50: 41.981527 | J50: -92.581266 | K50: 1201 South County Road | L50: Toledo | M50: IA | N50: ON132-IA-1082 | O50: 43 | P50: REIT_ILEC | Q50: Windstream Iowa Communications| Inc. | R50: ABS 2 | S50: 48301.87 | T50: 40500.03 | U50: 7029.58 | V50: 13546.64 | W50: 13998 | X50: 23 | Y50: 211 | Z50: 434 | AA50: 645 | AB50: 1471.7 | AC50: 11634.8 | AD50: 20688.4 | AE50: 13106.5 | AF50: 21 | AG50: 13127.5 | AI50: https://www.sitefotos.com/vpics/guestmapdev?s3a4q4 | AJ50: =W50*$C$3*$C$2/10^6 -> 2.624625
A51: Y | B51: Yes: 12k sqft + Owned | C51: BRAROKXB | D51: WNS2371 | E51: Owned | F51: Building | G51: Central Office | I51: 36.057572 | J51: -95.869011 | K51: 7200 S Mingo Rd | L51: Tulsa | M51: OK | N51: ON200-OK-006 | O51: 2730 | P51: REIT_ILEC | Q51: Valor Telecommunications of Texas| LLC | R51: ABS 2 | S51: 62023.19 | T51: 183555.22 | U51: 26118.34 | V51: 57091.68 | W51: 13599 | X51: 226 | Y51: 708 | Z51: 415 | AA51: 1123 | AB51: 83353.69 | AC51: 95058.36 | AD51: 68553.96 | AE51: 178412.05 | AF51: 0 | AG51: 178412.05 | AI51: https://www.sitefotos.com/vpics/guestmapdev?i8w0l5 | AJ51: =W51*$C$3*$C$2/10^6 -> 2.5498125
B52: Yes: 12k sqft + Owned | C52: TWBGOHIR | E52: Owned | F52: Building | G52: Central Office | I52: 41.311249 | J52: -81.442344 | K52: 2684 East Aurora Road | L52: Twinsburg | M52: OH | N52: ON080-OH-1006 | O52: 2712 | P52: REIT_ILEC | Q52: Windstream Western Reserve| Inc. | R52: ABS 1 | S52: 0 | T52: 0 | U52: 0 | V52: 0 | W52: 20000 | AI52: https://www.google.com/maps/place/130+Howell+Dr,+Elizabethtown,+KY+42701/@37.7137354,-85.8271202,860m/data=!3m2!1e3!4b1!4m6!3m5!1s0x8868ef14cb372ebf:0xa1909efe4828c1f5!8m2!3d37.7137312!4d-85.8245453!16s%2Fg%2F11bw4nx7h4?entry=ttu&amp;g_ep=EgoyMDI2MDIwNC4wIKXMDSoASAFQAw%3D%3D">Google Maps</a> | AJ52: =W52*$C$3*$C$2/10^6 -> 3.75
B53: Yes: 12k sqft + Owned | C53: VIANOK05 | E53: Owned | F53: Building | G53: Central Office | I53: 35.498468 | J53: -94.971459 | K53: 109 Blackstone St | L53: Vian | M53: OK | N53: ON208-OK-008 | P53: WIN_ILEC | Q53: Oklahoma Windstream| LLC | R53: ABS 2 | S53: 0 | T53: 0 | U53: 0 | V53: 0 | W53: 12000 | X53: 13 | Y53: 0 | Z53: 0 | AA53: 0 | AB53: 0 | AC53: 0 | AD53: 0 | AE53: 0 | AF53: 760 | AG53: 760 | AH53: 36503 | AI53: https://www.sitefotos.com/vpics/guestmapdev?v4r7w8 | AJ53: =W53*$C$3*$C$2/10^6 -> 2.25
B54: Yes - High Rack count | C54: WNDRGAXA | D54: WNS1594 | E54: Owned | F54: Building | G54: Central Office | I54: 33.994648 | J54: -83.721188 | K54: 74 Woodlawn Avenue | L54: Winder | M54: GA | N54: ON042-GA-092 | O54: 92 | P54: REIT_ILEC | Q54: Windstream Georgia Communications| LLC | R54: ABS 2 | S54: 39493.07 | T54: 149148.35 | U54: 3438.86 | V54: 45265.02 | W54: 7771 | X54: 119 | Y54: 509 | Z54: 2027 | AA54: 2536 | AB54: 107959.85 | AC54: 57589.49 | AD54: 150609.52 | AE54: 165549.34 | AF54: 0 | AG54: 165549.34 | AI54: https://sitefotos.com/vpics/guestmapdev?s0q8i7 | AJ54: =W54*$C$3*$C$2/10^6 -> 1.4570625
A55: Y | B55: Yes: 12k sqft + Owned | C55: ASHTOHXA | D55: WNS2238 | E55: Owned | F55: Building | G55: Central Office | I55: 41.865549 | J55: -80.783442 | K55: 4616 Park Avenue | L55: WYMAN | M55: OH | N55: B080053 | O55: 3549 | P55: REIT_ILEC | Q55: Windstream Western Reserve| Inc. | R55: ABS 2 | S55: 51649.4 | T55: 96181.38 | U55: 19265.16 | V55: 36680.53 | W55: 30000 | X55: 125 | Y55: 722 | Z55: 633 | AA55: 1355 | AB55: 3866 | AC55: 30884.12 | AD55: 10543.4 | AE55: 34750.12 | AF55: 0 | AG55: 34750.12 | AH55: 42984 | AI55: https://www.sitefotos.com/vpics/guestmapdev?q1f1l4 | AJ55: =W55*$C$3*$C$2/10^6 -> 5.625 | AK55: Y | AL55: Medium/Low | AM55: Limited additional space on lot; relatively high commercial + residential density | AP55: =INDEX('Mireye Site Screen'!BU:BU, MATCH('Top 50'!$I55, 'Mireye Site Screen'!$C:$C, 0)) -> #N/A

Sheet Mireye Site Screen
B1: Site | F1: Parcel (Regrid via Mireye) | M1: Power | Z1: Gas / BTM | AF1: Flood & Hazard | AQ1: Climate / Cooling | AU1: Air & Environment | BD1: Water / Sewer | BK1: Connectivity | BM1: Neighbors | BR1: Summary
A2: ID | B2: Site | C2: Lat | D2: Lng | E2: Screen depth | F2: Situs address | G2: Owner of record | H2: APN | I2: Zoning | J2: Parcel area (m2) | K2: Parcel area (acres) | L2: Parcel caveat | M2: ISO/RTO | N2: Serving utility (retail) | O2: Ind. elec price ($/kWh) | P2: Est. annual cost ($/MW-yr) | Q2: Substation dist (m) | R2: Substation max kV | S2: Trans line dist (m) | T2: Trans line kV | U2: Trans line owner | V2: Max kV within 10 km | W2: Substations in 10 km | X2: Redundancy flag | Y2: County queue (MW, generator-side) | Z2: Gas pipeline dist (m) | AA2: Interstate pipeline (m) | AB2: Ind. gas ($/MCF) | AC2: Grid ($/MWh) | AD2: Modeled gas gen ($/MWh, fuel-only) | AE2: BTM gas flag | AF2: FEMA zone | AG2: In SFHA | AH2: Seismic design cat. | AI2: PGA 2%/50yr (g) | AJ2: Design wind (mph) | AK2: Karst | AL2: Nearest dam (m) | AM2: Dam hazard class | AN2: High-hazard dams 10 km | AO2: Shrink-swell | AP2: Slope (deg) | AQ2: Design wet bulb (degC) | AR2: Days >=32C /yr | AS2: Free cooling h/yr @15C | AT2: Free cooling h/yr @10C | AU2: Ozone nonattainment | AV2: Worst class | AW2: Maintenance area | AX2: Superfund in 8 km | AY2: Brownfields in 8 km | AZ2: USTs in 1 km | BA2: Open LUST in 1 km | BB2: Opportunity Zone | BC2: Incentive stack | BD2: In water service area | BE2: Water system | BF2: System pop served | BG2: In sewer service area | BH2: Sewer provider | BI2: WWTP dist (m) | BJ2: WWTP pop served | BK2: FTTP providers | BL2: 5G class | BM2: Housing units 1 km | BN2: Density (units/km2) | BO2: Residential context | BP2: School dist (m) | BQ2: School name | BR2: Rank | BS2: Key strengths | BT2: Key risks | BU2: Verdict | BV2: Recommendation
B3: Ashland, Boyd Co KY | C3: 38.4758 | D3: -82.64385 | E3: Full (greenfield recipe - predates conversion recipe; no building/conversion fields) | F3: not pulled | G3: not pulled | H3: not pulled | I3: R-5 | J3: 4388.49 | K3: =J3/4046.856 -> 1.0844196 | L3: Single-point Regrid match - FRAGMENT RISK: R-5/1.08-ac may be adjacent lot if site is a multi-parcel assemblage (Northfield pattern); county check needed | M3: not pulled | N3: Kentucky Power Co | O3: 0.073 | P3: 639480 | Q3: 1446.8 | R3: 69 | S3: 695.8 | T3: 69 | U3: Kentucky Power Co | V3: 69 | W3: 15 | X3: TRUE | Y3: absent | Z3: 6713.6 | AA3: 6713.6 | AB3: 4.51 | AC3: 73 | AD3: 41.32 | AE3: TRUE | AF3: X | AG3: No | AH3: B | AI3: 0.135 | AJ3: 112 | AK3: No | AL3: 9078.4 | AM3: High | AN3: 2 | AO3: Low | AP3: 1.21 | AQ3: 25 | AR3: 28 | AS3: 4531 | AT3: 3434 | AU3: No | AV3: absent | AW3: No | AX3: 10 | AY3: 21 | AZ3: 34 | BA3: 0 | BB3: No | BC3: (none) | BD3: Yes | BE3: Ashland Water Works | BF3: 44402 | BG3: Yes | BH3: Ashland | BI3: 1771 | BJ3: 21481 | BK3: 2 | BL3: 5g_high_speed | BM3: 1735 | BN3: 381.1 | BO3: dense | BP3: 221 | BQ3: Ashland Child Development Center | BR3: 9 | BS3: Operating facility (established use); Zone X; flat; water+sewer in-area; best OH-valley gas economics ($41 vs $73 grid); 345 kV substation 6.6 km | BT3: 69 kV ceiling in radius caps ~5-15 MW; expansion friction from dense residential + childcare 221 m; parcel zoning/size unverified (fragment risk); greenfield-recipe screen only | BU3: REVIEW (5-15 MW band) | BV3: Keep as low-band expansion candidate; re-screen with conversion recipe + county assemblage check after Sept 1
A4: 1 | B4: Baldwin GA - 2000 Communications Blvd | C4: 34.497208 | D4: -83.549978 | E4: Full (conversion screen) | F4: 2000 COMMUNICATIONS BLVD | G4: absent | H4: 090 016 | I4: HI | J4: 106647.29 | K4: =J4/4046.856 -> 26.353122 | L4: Validated: coord + address pulls returned same parcel; address exact match | M4: absent | N4: Georgia Power Co | O4: 0.0684 | P4: 599184 | Q4: 1300.6 | R4: 115 | S4: 169.5 | T4: 115 | U4: Georgia Power Co | V4: 115 | W4: 10 | X4: TRUE | Y4: absent | Z4: absent | AA4: 51825.7 | AB4: 5.56 | AC4: 68.4 | AD4: 50.94 | AE4: absent | AF4: X | AG4: No | AH4: C | AI4: 0.195 | AJ4: 112 | AK4: No | AL4: 3629.9 | AM4: Low | AN4: 3 | AO4: Low | AP4: 0.35 | AQ4: 24.5 | AR4: 24 | AS4: 4154 | AT4: 2717 | AU4: No | AV4: absent | AW4: No | AX4: 0 | AY4: 2 | AZ4: 1 | BA4: 0 | BB4: No | BC4: (none) | BD4: No (54 m to boundary) | BE4: absent | BF4: absent | BG4: Yes | BH4: Baldwin WPCP | BI4: 2067 | BJ4: 5231 | BK4: 1 | BL4: 5g_high_speed | BM4: 778 | BN4: 136.4 | BO4: dense | BP4: 1249 | BQ4: Baldwin Elementary School | BR4: 1 | BS4: Operating facility + 26.35-ac HI parcel for expansion; 115 kV line 170 m; attainment air; clean environmental radius; full 5-50 MW band | BT4: No gas fallback (interstate 52 km); outside water area (54 m extension); small WWTP (5,231); no queue visibility (non-RTO) | BU4: GO | BV4: Pursue first - open Georgia Power capacity inquiry now
A5: 7 | B5: Northfield OH - 54 Leonard Ave | C5: 41.314744 | D5: -81.537039 | E5: Full (conversion screen) | F5: LEONARD AVE | G5: Kinetic ABS OH LLC | H5: 4002466 | I5: T-C | J5: 463.24 | K5: =J5/4046.856 -> 0.11446911 | L5: FRAGMENT - wrong parcel for address; county shows 7-parcel assemblage (APNs 4002461-4002467); building on 4002461 | M5: PJM | N5: City of Cleveland (OH) - SUSPECT | O5: 0.0995 | P5: 871620 | Q5: 1090.9 | R5: absent | S5: 893.1 | T5: 345 | U5: absent | V5: 345 | W5: 23 | X5: TRUE | Y5: absent | Z5: 534.6 | AA5: 24864.2 | AB5: 11.23 | AC5: 99.5 | AD5: 102.88 | AE5: TRUE | AF5: X | AG5: No | AH5: B | AI5: 0.095 | AJ5: 112 | AK5: No | AL5: 1699.4 | AM5: High | AN5: 3 | AO5: Low | AP5: 3.77 | AQ5: 24.1 | AR5: 8 | AS5: 5538 | AT5: 4258 | AU5: Yes - ozone (2015 std) | AV5: Serious | AW5: Yes (2008 ozone) | AX5: 7 | AY5: 2 | AZ5: 4 | BA5: 2 | BB5: No | BC5: (none) | BD5: Yes | BE5: Cleveland Public Water System | BF5: 1308955 | BG5: Yes | BH5: NEORSD Southerly WWTP | BI5: 7099 | BJ5: 21809 | BK5: 4 | BL5: 5g_high_speed | BM5: 1137 | BN5: 196.8 | BO5: dense | BP5: 87 | BQ5: Nordonia Middle School | BR5: 3 | BS5: Operating facility (established use beside school); best wires in portfolio - 345 kV line 893 m, 23 substations/10 km; 1.3M-person water system; 4 fiber providers; strong cooling | BT5: Serious ozone (incremental genset permitting, netting possible vs existing permits); $872k/MW-yr power; parcel data unreliable (7-parcel assemblage); utility attribution suspect; nearest UST 30 m likely own fuel tank | BU5: REVIEW | BV5: Rises under operating-facility lens - verify serving utility (FirstEnergy?) + assemblage, then utility capacity inquiry on the 345 kV path
A6: 3 | B6: Hudson OH - 1300 Terex Rd | C6: 41.217063 | D6: -81.442508 | E6: Full (conversion screen) | F6: 1300 TEREX RD | G6: Kinetic ABS OH LLC | H6: 3003811 | I6: DISTRICT-8 | J6: 3254.56 | K6: =J6/4046.856 -> 0.80421937 | L6: Single matched parcel; owner holds 16 Summit Co parcels - may be part of assemblage | M6: PJM | N6: City of Hudson (OH) - verified real muni | O6: 0.0995 | P6: 871620 | Q6: 1054.1 | R6: 138 | S6: 814.1 | T6: absent | U6: absent | V6: 138 | W6: 21 | X6: TRUE | Y6: absent | Z6: 724 | AA6: 30645.3 | AB6: 11.23 | AC6: 99.5 | AD6: 102.88 | AE6: TRUE | AF6: X | AG6: No | AH6: B | AI6: 0.085 | AJ6: 112 | AK6: No | AL6: 2007.5 | AM6: Significant | AN6: 5 | AO6: Low | AP6: 1.29 | AQ6: 24 | AR6: 8 | AS6: 5448 | AT6: 4240 | AU6: Yes - ozone (2015 std) | AV6: Serious | AW6: Yes (2008 ozone) | AX6: 1 | AY6: 3 | AZ6: 3 | BA6: 0 | BB6: No | BC6: (none) | BD6: Yes | BE6: Hudson City PWS | BF6: 8385 | BG6: No (546 m to boundary) | BH6: absent | BI6: 6095 | BJ6: 16758 | BK6: 4 | BL6: 5g_high_speed | BM6: 944 | BN6: 86.3 | BO6: dense | BP6: 256 | BQ6: The Goddard School | BR6: 4 | BS6: Operating facility; 138 kV substation 1.1 km; 21 substations/10 km; clean environmental; strong cooling; 4 fiber providers | BT6: Municipal utility counterparty at 50 MW; Serious ozone (incremental gensets need Tier 4); outside sewer area; small water system | BU6: REVIEW | BV6: Advance - gauge Hudson Public Power capacity appetite for the increment; spec Tier 4 gensets
A7: 5 | B7: Newark OH - 66 N 4th St | C7: 40.059449 | D7: -82.404873 | E7: Full (conversion screen) | F7: 66 N 4 ST | G7: Kinetic ABS OH LLC | H7: 02121190402004058000 | I7: DC | J7: 1113.45 | K7: =J7/4046.856 -> 0.27513952 | L7: Single matched parcel; downtown CBD - possible assemblage | M7: PJM | N7: Ohio Power Co (AEP) | O7: 0.0995 | P7: 871620 | Q7: 928.1 | R7: absent | S7: 605.7 | T7: 69 | U7: Ohio Power Co | V7: 69 | W7: 21 | X7: TRUE | Y7: 710.04 | Z7: 2707.6 | AA7: 2707.6 | AB7: 11.23 | AC7: 99.5 | AD7: 102.88 | AE7: TRUE | AF7: X | AG7: No | AH7: B | AI7: 0.085 | AJ7: 112 | AK7: No | AL7: 3160.8 | AM7: Significant | AN7: 0 | AO7: Low | AP7: 0.84 | AQ7: 24.6 | AR7: 11 | AS7: 5045 | AT7: 3940 | AU7: No | AV7: absent | AW7: Yes (2008+2015 ozone) | AX7: 5 | AY7: 16 | AZ7: 16 | BA7: 1 | BB7: No | BC7: brownfield_repowering_screened | BD7: Yes | BE7: Newark City PWS | BF7: 49934 | BG7: Yes | BH7: Newark WWTP & Sewer System | BI7: 2889 | BJ7: 10538 | BK7: 3 | BL7: 5g_high_speed | BM7: 3135 | BN7: 541.4 | BO7: dense | BP7: 182 | BQ7: Child Of God Preschool | BR7: 8 | BS7: Operating facility (established downtown use); solid AEP counterparty; maintenance-only air (best air status in the OH group); water+sewer in-area; 710 MW county queue | BT7: 69 kV ceiling in entire radius caps ~5-15 MW; nearest UST 33 m likely own tank but 16 USTs/16 brownfields in downtown radius (diligence); expansion friction from preschool 182 m + density | BU7: REVIEW (5-15 MW band) | BV7: Keep as low-band expansion candidate - AEP capacity inquiry decides it
A8: 8 | B8: Riverside TX - FM 980 (Walker Co) | C8: 30.85154 | D8: -95.40012 | E8: Full (conversion screen) | F8: FM 980 | G8: Valor Telecommunications of Texas LP | H8: 14123 | I8: absent | J8: 2327.99 | K8: =J8/4046.856 -> 0.57525892 | L8: Single matched parcel; rural - assemblage unknown | M8: ERCOT (field) - SUSPECT, wires are Entergy TX (likely MISO) | N8: Mid-South Electric Coop Assn | O8: 0.0633 | P8: 554508 | Q8: 1467.8 | R8: 138 | S8: 802.7 | T8: 69 | U8: Entergy Texas, Inc. | V8: 138 | W8: 2 | X8: FALSE | Y8: 150 | Z8: 544.7 | AA8: 544.7 | AB8: 3.12 | AC8: 63.3 | AD8: 28.58 | AE8: TRUE | AF8: A | AG8: YES - SFHA, no BFE published | AH8: B | AI8: 0.045 | AJ8: 112 | AK8: No | AL8: 1640 | AM8: Low | AN8: 2 | AO8: Low | AP8: 0.85 | AQ8: 26.2 | AR8: 104 | AS8: 2693 | AT8: 1460 | AU8: No | AV8: absent | AW8: No | AX8: 0 | AY8: 0 | AZ8: 2 | BA8: 0 | BB8: No | BC8: (none) | BD8: Yes | BE8: Riverside SUD | BF8: 6492 | BG8: No (7,460 m to boundary) | BH8: absent | BI8: 10865 | BJ8: 3010 | BK8: 1 | BL8: 5g_high_speed | BM8: 315 | BN8: 32.2 | BO8: moderate | BP8: 9750 | BQ8: (unreliable Overture record) | BR8: 10 | BS8: Operating facility already living with the flood zone; cheapest grid ($555k/MW-yr); best usable gas hedge ($29 vs $63, pipeline 545 m, attainment air); 138 kV | BT8: FEMA Zone A (no BFE) - substantial-improvement rule bites densification capex >50% of building value regardless of existing ops; worst-tier cooling; 2 substations/10 km, redundancy FALSE; sewer 7.5 km | BU8: NO-GO (flood) | BV8: Park - spend ~$2k on elevation certificate; revive only if LOMA path viable
A9: 2 | B9: Harrison AR - 202 Graham St | C9: 36.214283 | D9: -93.079052 | E9: Full (conversion screen) | F9: 202 GRAHAM STRE | G9: absent | H9: 825-14426-200 | I9: C3 | J9: 40473.46 | K9: =J9/4046.856 -> 10.001211 | L9: Single matched parcel - 10.0 ac; only multi-acre parcel besides Baldwin | M9: MISO | N9: Entergy Arkansas LLC | O9: 0.062 | P9: 543120 | Q9: 960.6 | R9: 161 | S9: 960.6 | T9: 161 | U9: Entergy Arkansas Inc | V9: 161 | W9: 3 | X9: TRUE | Y9: absent | Z9: 5124.3 | AA9: 62989.5 | AB9: 9.28 | AC9: 62 | AD9: 85.01 | AE9: TRUE (flag only - see risks) | AF9: X | AG9: No | AH9: D | AI9: 0.225 | AJ9: 112 | AK9: YES - carbonate, EXPOSED (Boone Fm) | AL9: absent | AM9: absent | AN9: 0 | AO9: absent | AP9: 2.58 | AQ9: 25.6 | AR9: 38 | AS9: 4294 | AT9: 2981 | AU9: No | AV9: absent | AW9: No | AX9: 0 | AY9: 0 | AZ9: 3 | BA9: 0 | BB9: No | BC9: (none) | BD9: Yes | BE9: Harrison Waterworks | BF9: 17455 | BG9: Yes | BH9: Harrison WWTP | BI9: 2947 | BJ9: 13468 | BK9: 3 | BL9: 5g_high_speed | BM9: 388 | BN9: 38.4 | BO9: moderate | BP9: 1158 | BQ9: Educational Opportunity Center | BR9: 2 | BS9: Operating facility + 10.0-ac C3 parcel for expansion; 161 kV substation+line ~960 m; cheapest power in portfolio ($543k/MW-yr); attainment; spotless environmental | BT9: Exposed carbonate karst + seismic design cat. D - governs NEW expansion structures (existing building's decades of service partly de-risk); only 3 substations/10 km; gas gen uneconomic | BU9: GO (leaning) | BV9: Pursue #2 - geotech karst study for expansion footprint + Entergy capacity inquiry in parallel
A10: 4 | B10: Moultrie GA - 216 4th St SE | C10: 31.177483 | D10: -83.783714 | E10: Full (conversion screen) | F10: 216 4TH ST SE | G10: absent | H10: M035 001 | I10: C-3 | J10: 5286.65 | K10: =J10/4046.856 -> 1.3063598 | L10: Single matched parcel - 1.31 ac | M10: absent | N10: City of Moultrie (GA) - muni | O10: 0.0684 | P10: 599184 | Q10: 565.6 | R10: 115 | S10: 302.9 | T10: 115 | U10: Georgia Power Co | V10: 115 | W10: 15 | X10: TRUE | Y10: 130 | Z10: 4850.7 | AA10: 4850.7 | AB10: 5.56 | AC10: 68.4 | AD10: 50.94 | AE10: TRUE | AF10: X | AG10: No | AH10: B | AI10: 0.065 | AJ10: 112 | AK10: Buried carbonate (low confidence) | AL10: 2624.8 | AM10: Low | AN10: 1 | AO10: Low | AP10: 0.94 | AQ10: 26.4 | AR10: 69 | AS10: 2658 | AT10: 1372 | AU10: No | AV10: absent | AW10: No | AX10: 0 | AY10: 2 | AZ10: 32 | BA10: 2 | BB10: YES - tract 13071970702 | BC10: opportunity_zone | BD10: Yes | BE10: Moultrie | BF10: 17067 | BG10: Yes | BH10: Moultrie WPCP | BI10: 2852 | BJ10: 13760 | BK10: 1 | BL10: 5g_high_speed | BM10: 1285 | BN10: 188.2 | BO10: dense | BP10: 775 | BQ10: Stringfellow Elementary School | BR10: 5 | BS10: Operating facility; only Opportunity Zone site (capital-stack sweetener); 115 kV line 303 m (GA Power wires); attainment; 15 substations/10 km | BT10: Muni retail counterparty; nearest UST 31 m likely own tank but 32 USTs + 2 open LUST in 1 km (Phase I); hot climate (69 days >=32C); 1.31-ac parcel | BU10: REVIEW | BV10: Hold as OZ-advantaged backup; Phase I environmental if advanced
A11: 6 | B11: Newton IA - 115 S 2nd Ave W | C11: 41.698332 | D11: -93.054486 | E11: Full (conversion screen) | F11: 115 S 2ND AVE W | G11: CSL Iowa System LLC (Uniti leaseback) | H11: 0834158001 | I11: C-CBD | J11: 1731 | K11: =J11/4046.856 -> 0.42773946 | L11: Single matched parcel; downtown CBD - possible assemblage | M11: MISO | N11: Consumers Energy - SUSPECT (likely Alliant/IPL; a Consumers Energy Coop exists in IA) | O11: 0.0626 | P11: 548376 | Q11: 784.2 | R11: 161 | S11: 751.7 | T11: absent | U11: MidAmerican Energy Co | V11: 161 | W11: 4 | X11: TRUE | Y11: absent | Z11: 4438.6 | AA11: 4438.6 | AB11: 6.69 | AC11: 62.6 | AD11: 61.29 | AE11: TRUE | AF11: X | AG11: No | AH11: B | AI11: 0.045 | AJ11: 112 | AK11: No | AL11: 2844.3 | AM11: Low | AN11: 0 | AO11: Moderate | AP11: 2.88 | AQ11: 26.7 | AR11: 16 | AS11: 5312 | AT11: 4331 | AU11: No | AV11: absent | AW11: No | AX11: 1 | AY11: 0 | AZ11: 23 | BA11: 2 | BB11: No | BC11: brownfield_repowering_screened | BD11: Yes | BE11: Newton Water Supply | BF11: 16518 | BG11: Yes | BH11: Newton WWTP | BI11: 274 | BJ11: 16283 | BK11: 3 | BL11: 5g_high_speed | BM11: 2685 | BN11: 494.5 | BO11: dense | BP11: 426 | BQ11: Central Junior High School | BR11: 6 | BS11: Operating facility; 161 kV substation 784 m; cheap power ($548k/MW-yr); attainment; excellent cooling (5,312 h) | BT11: 0.43-ac CBD fragment (assemblage unknown); Uniti (CSL) leaseback ownership - counterparty differs; utility attribution suspect; superfund 827 m + 2 open LUST (diligence); expansion friction from junior high 426 m | BU11: REVIEW | BV11: Hold - verify Alliant service, assemblage, and Uniti lease terms; mid-tier
B12: Sugar Land TX - Fort Bend Co | C12: 29.636252 | D12: -95.598181 | E12: TRIAGE ONLY (credits) - no parcel/building/school | F12: not pulled | G12: not pulled | H12: not pulled | I12: not pulled | J12: not pulled | K12: not pulled | L12: Parcel fields not pulled - credit exhaustion; complete after Sept 1 reset | M12: ERCOT (eGRID ERCT) | N12: CenterPoint Energy (wires; retail via competitive REP) | O12: 0.0633 | P12: 554508 | Q12: 913.6 | R12: 138 | S12: not pulled | T12: not pulled | U12: not pulled | V12: not pulled | W12: 18 | X12: TRUE | Y12: 3320.46 | Z12: 615.1 | AA12: 726.7 | AB12: 3.12 | AC12: 63.3 | AD12: 28.58 | AE12: TRUE | AF12: X | AG12: No | AH12: A | AI12: 0.045 | AJ12: 136 | AK12: No | AL12: 3892.1 | AM12: High | AN12: 1 | AO12: VERY HIGH | AP12: 1.37 | AQ12: 27.1 | AR12: 106 | AS12: 1994 | AT12: 1032 | AU12: Yes - ozone (2008+2015 stds) | AV12: SEVERE | AW12: No | AX12: 1 | AY12: 2 | AZ12: 5 | BA12: 0 | BB12: No | BC12: brownfield_repowering_screened | BD12: Yes | BE12: City of Sugar Land | BF12: 90909 | BG12: Yes | BH12: Sugar Land North WWTP | BI12: 2299 | BJ12: 1239 | BK12: 4 | BL12: 5g_high_speed | BM12: 1677 | BN12: 296.4 | BO12: dense | BP12: not pulled | BQ12: not pulled | BR12: 7 | BS12: Operating facility; Zone X despite Houston metro; 18 substations/10 km; 3.3 GW county queue (hot market); best gas economics on paper; nearest UST 29 m likely own tank | BT12: SEVERE ozone (25 tpy NOx major threshold - neutralizes gas play, forces Tier 4 on incremental gensets); 136 mph design wind; very-high shrink-swell clays; worst cooling (1,994 h); screen incomplete | BU12: REVIEW (incomplete) | BV12: Complete parcel screen after Sept 1 credit reset before judging

Sheet COs_Asset_List
A1: CLLI - A | B1: Asset Name | C1: Asset Model | D1: SIZE (BTUs) | E1: KW | F1: DATE INSTALLED | G1: Age | H1: Useful Life | I1: Within Useful Life? | J1: FIXED/PORTABLE | K1: FUEL SYSTEM | L1: Generator Run Time (Hours)
A2: ABRDNCXA | B2: GEN01-ALICECHALMERS-67OT-7014315 | C2: GENERATOR PM | E2: 100 | F2: 29526 | G2: 43 | H2: 25 | I2: no | J2: FIXED | K2: DIESEL | L2: 1493.3
A3: ABRDNCXA | B3: CND01-TRANE-TTA090A300FA-9283SBJAD | C3: HVAC - CONDENSER UNIT | D3: 90000 | F3: 39814 | G3: 15 | H3: 15 | I3: no
A4: ABRDNCXA | B4: CND02-YORK-E1FDO98525B-ELEM417454 | C4: HVAC - CONDENSER UNIT | D4: 48000 | F4: 35339 | G4: 28 | H4: 15 | I4: no
A5: ABRDNCXA | B5: AHU01-TRANE-TWE090A300EL-9271L14BD | C5: HVAC - AIR HANDLING UNIT | D5: 90000 | F5: 39965 | G5: 15 | H5: 15 | I5: no
A6: ABRDNCXA | B6: AHU02-YORK-FFP048H067-EMS345622 | C6: HVAC - AIR HANDLING UNIT | D6: 36000 | F6: 35339 | G6: 28 | H6: 15 | I6: no
A7: ABRDNCXA | B7: AHU03-TRANE-TSC090H3R0A02-192710171L | C7: HVAC - AIR HANDLING UNIT | I7: no
A8: ABRDNCXA | B8: AHU02- TRANE-5TEM6D06AV41SAA-25293YU23V | C8: HVAC - AIR HANDLING UNIT | I8: no
A9: ABRDNCXA | B9: CND02-TRANE-5TWA40483000AA-252430AFKF | C9: HVAC - CONDENSER UNIT | I9: no
A10: ADBNIAXO | B10: GEN01-ONAN-75ODUB15R27996A-F850766924 | C10: GENERATOR PM | E10: 75 | F10: 31199 | G10: 39 | H10: 25 | I10: no | J10: FIXED | K10: DIESEL | L10: 39.7
A11: ADBNIAXO | B11: AHU01-LENNOX-HS19653V3Y-UnkSerial | C11: HVAC - AIR HANDLING UNIT | D11: 60000 | I11: no
A12: ADBNIAXO | B12: AHU02-LENNOX-HS290605P-UnkSerial | C12: HVAC - AIR HANDLING UNIT | D12: 60000 | I12: no
A13: ADELGAXA | B13: GEN01-Olympian-D60P1-D4751A001 | C13: GENERATOR PM | E13: 60 | I13: no | J13: FIXED | K13: Diesel | L13: 977.4
A14: ADELGAXA | B14: AHU01-CARRIER-FB4CNF042-4714A84662 | C14: HVAC - AIR HANDLING UNIT | D14: 42000 | F14: 41944 | G14: 9 | H14: 15 | I14: yes
A15: ADELGAXA | B15: CND01-CARRIER-25HCD342A310-411E18487 | C15: HVAC - CONDENSER UNIT | D15: 42000 | I15: no
A16: ADELGAXA | B16: WAC01-MARVAIR-AVPA60ACA100NU-EJF16769201 | C16: HVAC - AC WALL UNIT | D16: 60000 | F16: 43617 | G16: 5 | H16: 15 | I16: yes
A17: ADELGAXA | B17: WAC02-BARD-W60ACA00-289C20374564802 | C17: HVAC - AC WALL UNIT | I17: no
A18: ADELGAXA | B18: WAC03-BARD-W60A2A00-324C17341658002 | C18: HVAC - AC WALL UNIT | F18: 42736 | I18: no
A19: ALBIIAXO | B19: GEN01-ONAN-125DVD15R26986B-K870947167 | C19: GENERATOR PM | E19: 125 | F19: 32157 | G19: 36 | H19: 25 | I19: no | J19: FIXED | K19: DIESEL | L19: 168.8
A20: ALBIIAXO | B20: CND01-LENNOX-UnkModel-UnkSerial | C20: HVAC - CONDENSER UNIT | D20: 24000 | I20: no
A21: ALBIIAXO | B21: CND02-CARRIER-38AR2008501-2202G20047 | C21: HVAC - CONDENSER UNIT | D21: 90000 | F21: 37408 | G21: 22 | H21: 15 | I21: no
A22: ALBIIAXO | B22: CND03-LENNOX-HS19513V4Y-5192G03682 | C22: HVAC - CONDENSER UNIT | D22: 48000 | F22: 33786 | G22: 32 | H22: 15 | I22: no
A23: ALBIIAXO | B23: AHU01-LENNOX-G51MP60C09008-5908B17971 | C23: HVAC - AIR HANDLING UNIT | D23: 90000 | F23: 39479 | G23: 16 | H23: 15 | I23: no
A24: ALBIIAXO | B24: AHU02-LENNOX-G51MP60C09008-5908B17942 | C24: HVAC - AIR HANDLING UNIT | D24: 90000 | F24: 39479 | G24: 16 | H24: 15 | I24: no
A25: ALBIIAXO | B25: AHU03-LENNOX-CB19512P-5193A77863 | C25: HVAC - AIR HANDLING UNIT | D25: 48000 | F25: 33970 | G25: 31 | H25: 15 | I25: no
A26: ALBIIAXO | B26: AHU04-LENNOX-ML196UH070XE36B-52-1722C21879 | C26: HVAC - AIR HANDLING UNIT | D26: 36000 | F26: 44698 | G26: 2 | H26: 15 | I26: yes
A27: ALBIIAXO | B27: CND04-LENNOX-TSA36S4N44Y-5820C17368 | C27: HVAC - CONDENSER UNIT | D27: 36000 | F27: 44698 | G27: 2 | H27: 15 | I27: yes
A28: ALBMNCXA | B28: GEN01-CUMMINS-350DFCC5564642-G020395528 | C28: GENERATOR PM | E28: 350 | F28: 37438 | G28: 22 | H28: 25 | I28: yes | J28: FIXED | K28: Diesel | L28: 757.9
A29: ALBMNCXA | B29: CND01-CARRIER-38QKW024521-1505G50007 | C29: HVAC - CONDENSER UNIT | D29: 24000 | F29: 38443 | G29: 19 | H29: 15 | I29: no
A30: ALBMNCXA | B30: AHU02-MARLO-CMZ133X-M58196 | C30: HVAC - AIR HANDLING UNIT | I30: no
A31: ALBMNCXA | B31: AHU01-CARRIER-40RM024B511GC-4504X02161 | C31: HVAC - AIR HANDLING UNIT | D31: 24000 | F31: 38292 | G31: 19 | H31: 15 | I31: no
A32: ALBMNCXA | B32: AHU01-Carrier-FX4DNF061-0416A88576 | C32: HVAC - AIR HANDLING UNIT | D32: 60000 | F32: 42370 | G32: 8 | H32: 15 | I32: yes
A33: ALBMNCXA | B33: CND01-Carrier-24ABB360A520-02165E00305 | C33: HVAC - CONDENSER UNIT | D33: 60000 | F33: 42370 | G33: 8 | H33: 15 | I33: yes
A34: ALBMNCXA | B34: AHU03-TRANE-NTXWST36A112AA-9000162T20U80W | C34: HVAC - AIR HANDLING UNIT | D34: 36000 | I34: no
A35: ALBMNCXA | B35: CND03-TRANE-NTXSST36A112AA-9000247T20U8C5 | C35: HVAC - CONDENSER UNIT | D35: 36000 | I35: no
A36: ALBMNCXA | B36: CND02-TRANE-TTA24043CAB01AE-21313769TA | C36: HVAC - CONDENSER UNIT | I36: no
A37: ALBMNCXA | B37: RTU01-TRANE-TCD300F3DOAH-114810090D | C37: HVAC - ROOF TOP UNIT | I37: no
A38: ALBYKYXA | B38: UH01-ELECTROMODE-WA40-UnkSerial | C38: HVAC - UNIT HEATER | I38: no
A39: ALBYKYXA | B39: GEN02-CONDEC-31700812-BA23821ED | C39: GENERATOR PM | E39: 115 | I39: no | J39: FIXED | K39: Diesel | L39: 406.4
A40: ALBYKYXA | B40: AHU01-CARRIER-40RUAA16A2A6-3616U28425 | C40: HVAC - AIR HANDLING UNIT | F40: 42656 | G40: 7 | H40: 15 | I40: yes
A41: ALBYKYXA | B41: CND01-CARRIER-38AUDA16A0A5-3316P52467 | C41: HVAC - CONDENSER UNIT | F41: 42656 | G41: 7 | H41: 15 | I41: yes
A42: ALBYKYXA | B42: UH02-MARKEL-31TR48-03264502 | C42: HVAC - UNIT HEATER | F42: 44607 | G42: 2 | H42: 15 | I42: yes
A43: ALBYKYXA | B43: AHU02-CARRIER-40RUAA16T2A5AOAOAO-0522U29370 | C43: HVAC - AIR HANDLING UNIT | D43: 180000 | F43: 44753 | G43: 2 | H43: 15 | I43: yes
A44: ALBYKYXA | B44: CND02-CARRIER-38AUZA16-OAOAOA0A5-0822P34705 | C44: HVAC - CONDENSER UNIT | D44: 180000 | F44: 44753 | G44: 2 | H44: 15 | I44: yes
A45: ALCHFLXA | B45: GEN01-Cummins-80DGDA4956988-C010220821 | C45: GENERATOR PM | E45: 80 | F45: 36984 | G45: 23 | H45: 25 | I45: yes | J45: FIXED | K45: Diesel | L45: 657.1
A46: ALCHFLXA | B46: AHU02-CARRIER-40RM008B611HC-3706U24223 | C46: HVAC - AIR HANDLING UNIT | D46: 90000 | F46: 38961 | G46: 18 | H46: 15 | I46: no
A47: ALCHFLXA | B47: CND02-CARRIER-38AU2A08A0B5A090A0-2511G40138 | C47: HVAC - CONDENSER UNIT | D47: 90000 | F47: 40695 | G47: 13 | H47: 15 | I47: yes
A48: ALCHFLXA | B48: AHU03-CARRIER-40RUAA08T2A50A0A0-1220U09517 | C48: HVAC - AIR HANDLING UNIT | D48: 90000 | F48: 43983 | G48: 4 | H48: 15 | I48: yes
A49: ALCHFLXA | B49: CND03-CARRIER-38AUZA08A0B50A0A0-0620C92349 | C49: HVAC - CONDENSER UNIT | D49: 90000 | F49: 43983 | G49: 4 | H49: 15 | I49: yes
A50: ALCHFLXA | B50: AHU01-DAIKEN-DX14XA1203-2301261294 | C50: HVAC - AIR HANDLING UNIT | D50: 120000 | I50: no
A51: ALCHFLXA | B51: CND01-DAIKEN-DAX12043-2301217199 | C51: HVAC - CONDENSER UNIT | D51: 120000 | F51: 45444 | I51: no
A52: ANDRTXXA | B52: GEN01-Cummins ONAN-155DFE15R-D760123588 | C52: GENERATOR PM | E52: 155 | F52: 27851 | G52: 48 | H52: 25 | I52: no | J52: FIXED | K52: Diesel | L52: 1288
A53: ANDRTXXA | B53: AHU03-TRANE-TWE120B300DA-2271PAC5H | C53: HVAC - AIR HANDLING UNIT | D53: 120000 | F53: 44562 | G53: 2 | H53: 15 | I53: yes
A54: ANDRTXXA | B54: CND03-TRANE-TTA120E400AA-2375Y60AD | C54: HVAC - CONDENSER UNIT | D54: 120000 | F54: 44927 | G54: 1 | H54: 15 | I54: yes
A55: ANDRTXXA | B55: AHU01-TRANE-TWE120E300AB-14344YKDBA | C55: HVAC - AIR HANDLING UNIT | D55: 120000 | F55: 41852 | G55: 10 | H55: 15 | I55: yes
A56: ANDRTXXA | B56: AHU02-TRANE-TWE120E300AB-143440FPBA | C56: HVAC - AIR HANDLING UNIT | D56: 120000 | F56: 41852 | G56: 10 | H56: 15 | I56: yes
A57: ANDRTXXA | B57: CND01-TRANE-TTA120E400AA-14252B4LYA | C57: HVAC - CONDENSER UNIT | D57: 120000 | F57: 41791 | G57: 10 | H57: 15 | I57: yes
A58: ANDRTXXA | B58: CND02-TRANE-TTA120E400AA-14254W14YA | C58: HVAC - CONDENSER UNIT | D58: 120000 | F58: 41791 | G58: 10 | H58: 15 | I58: yes
A59: ANDRTXXA | B59: AHU04-TRANE-TWE09043-19061537BA | C59: HVAC - AIR HANDLING UNIT | D59: 90000 | F59: 43466 | G59: 5 | H59: 15 | I59: yes
A60: ANDRTXXA | B60: CND04-TRANE-TTA09043-18451783YA | C60: HVAC - CONDENSER UNIT | D60: 90000 | F60: 43101 | G60: 6 | H60: 15 | I60: yes
A61: ANDRTXXA | B61: AHU05-TRANE-TWE09043AAA00A0000-1252665BA | C61: HVAC - AIR HANDLING UNIT | D61: 90000 | F61: 40909 | G61: 12 | H61: 15 | I61: yes
A62: ANDRTXXA | B62: CND05-TRANE-TTA09043-18262073YA | C62: HVAC - CONDENSER UNIT | D62: 90000 | F62: 43101 | G62: 6 | H62: 15 | I62: yes
A63: ANDRTXXA | B63: AHU06-TRANE-AUHV60D3XH21CC-W1D6532687 | C63: HVAC - AIR HANDLING UNIT | I63: no
A64: ANDRTXXA | B64: CND06-TRANE-TCJD605435A-W1L6057178 | C64: HVAC - CONDENSER UNIT | D64: 60000 | F64: 42370 | G64: 8 | H64: 15 | I64: yes
A65: ANDRTXXA | B65: AHU07-TRANE-AUHV60D3XH21CC-W1D6532690 | C65: HVAC - AIR HANDLING UNIT | D65: 60000 | F65: 42370 | G65: 8 | H65: 15 | I65: yes
A66: ANDRTXXA | B66: CND07-TRANE-TCJD6054354A-W1K607453 | C66: HVAC - CONDENSER UNIT | D66: 60000 | F66: 42370 | G66: 8 | H66: 15 | I66: yes
A67: ANDRTXXA | B67: AHU05-CARRIER-50CD-005-510-0484G91587 | C67: HVAC - AIR HANDLING UNIT | D67: 60000 | F67: 30682 | G67: 40 | H67: 15 | I67: no
A68: ANDRTXXA | B68: WAC01-BARD-W70A2809-404F1331745102 | C68: HVAC - AC WALL UNIT | D68: 72000 | F68: 41275 | G68: 11 | H68: 15 | I68: yes
A69: ANDRTXXA | B69: WAC02-BARD-W70A2809-404F1331745202 | C69: HVAC - AC WALL UNIT | D69: 72000 | F69: 41275 | G69: 11 | H69: 15 | I69: yes
A70: ANDRTXXA | B70: WAC03-BARD-W7012809-40F1331745002 | C70: HVAC - AC WALL UNIT | D70: 72000 | F70: 41275 | G70: 11 | H70: 15 | I70: yes
A71: ANDRTXXA | B71: PAC01-LENNOX-KCB036S4DN1P-5616G08733 | C71: HVAC - PACKAGE UNIT | I71: no
A72: ANWOIAXO | B72: GEN01-ONAN-30DDA15R28076D-C820615391 | C72: GENERATOR PM | E72: 30 | G72: 42 | H72: 25 | I72: no | J72: FIXED | K72: DIESEL
A73: ANWOIAXO | B73: GEN01-ONAN-30DDA15R28076D-C820615391 | C73: GENERATOR PM | E73: 30 | F73: 30011 | I73: no | J73: FIXED | K73: DIESEL | L73: 1146.6
A74: ASHTOHXA | B74: AHU02-LIEBERT-VS070ADC0E19775-14K8E0023 | C74: HVAC - AIR HANDLING UNIT | D74: 240000 | F74: 41640 | G74: 10 | H74: 15 | I74: yes
A75: ASHTOHXA | B75: AHU01-LIEBERT-VS070ADC0E19775-14X8E0024 | C75: HVAC - AIR HANDLING UNIT | D75: 240000 | F75: 41640 | G75: 10 | H75: 15 | I75: yes
A76: ASHTOHXA | B76: WAC04-LENNOX-CB17275V1-5600J04369 | C76: HVAC - AC WALL UNIT | D76: 240000 | F76: 36526 | G76: 24 | H76: 15 | I76: no
A77: ASHTOHXA | B77: WAC03-LENNOX-HS292402Y-5600M04765 | C77: HVAC - AC WALL UNIT | F77: 36526 | G77: 24 | H77: 15 | I77: no
A78: ASHTOHXA | B78: GEN02-CUMMINS-DQDAC-H160988986 | C78: GENERATOR PM | E78: 300 | F78: 42614 | G78: 8 | H78: 25 | I78: yes | J78: FIXED | K78: Diesel | L78: 225.8
A79: ASHTOHXA | B79: AHU01-TRANE-A4AH4E60A1C30BA-21254NDY3V | C79: HVAC - AIR HANDLING UNIT | D79: 60000 | F79: 44698 | G79: 2 | H79: 15 | I79: yes
A80: ASHTOHXA | B80: CND01-TRANE-4TTTA3060D3000DA-22083EGJ5F | C80: HVAC - CONDENSER UNIT | D80: 60000 | F80: 44698 | G80: 2 | H80: 15 | I80: yes
A81: ASLDKYXA | B81: GEN01-CATERPILLAR-SR4B-9FG02372 | C81: GENERATOR PM | E81: 600 | I81: no | J81: FIXED | K81: Diesel | L81: 571
A82: ASLDKYXA | B82: AHU01-YORK-M30H-66765168HI | C82: HVAC - AIR HANDLING UNIT | F82: 32874 | I82: no
A83: ASLDKYXA | B83: AHU02-YORK-M30H-UnkSerial | C83: HVAC - AIR HANDLING UNIT | I83: no
A84: ASLDKYXA | B84: AHU03-YORK-UnkModel-66765168H2 | C84: HVAC - AIR HANDLING UNIT | I84: no
A85: ASLDKYXA | B85: AHU05-LIEBERT-11C-155591 | C85: HVAC - AIR HANDLING UNIT | F85: 31048 | G85: 39 | H85: 15 | I85: no
A86: ASLDKYXA | B86: AHU06-CARRIER-FB4CNP060-2614A87982 | C86: HVAC - AIR HANDLING UNIT | D86: 60000 | F86: 41791 | G86: 10 | H86: 15 | I86: yes
A87: ASLDKYXA | B87: AHU07-LIEBERT-D125AVAECI-435359001 | C87: HVAC - AIR HANDLING UNIT | D87: 240000 | F87: 37987 | G87: 20 | H87: 15 | I87: no
A88: ASLDKYXA | B88: AHU08-LIEBERT-FH376CC01-85161A | C88: HVAC - AIR HANDLING UNIT | D88: 240000 | F88: 32509 | G88: 35 | H88: 15 | I88: no
A89: ASLDKYXA | B89: AHU09-LIEBERT-FH376CC01-85161C | C89: HVAC - AIR HANDLING UNIT | D89: 240000 | F89: 32509 | G89: 35 | H89: 15 | I89: no
A90: ASLDKYXA | B90: AHU10-LIEBERT-FH376CC01-85161B | C90: HVAC - AIR HANDLING UNIT | D90: 240000 | F90: 32509 | G90: 35 | H90: 15 | I90: no
A91: ASLDKYXA | B91: AHU11-LIEBERT-UnkModel-UnkSerial | C91: HVAC - AIR HANDLING UNIT | I91: no
A92: ASLDKYXA | B92: CND05-CARRIER-PA13NA060E-2514X68504 | C92: HVAC - CONDENSER UNIT | I92: no
A93: ASLDKYXA | B93: AHU12-CARRIER-40RUAA16T2A5A-2521U21730 | C93: HVAC - AIR HANDLING UNIT | I93: no
A94: ASLDKYXA | B94: CND06-CARRIER-38AUZA16AOA5AOAOAO-2421P41825 | C94: HVAC - CONDENSER UNIT | D94: 180000 | F94: 44509 | G94: 2 | H94: 15 | I94: yes
A95: ASLDKYXA | B95: CND07-LIEBERT-CDF165LY-132650924 | C95: HVAC - CONDENSER UNIT | I95: no
A96: ASLDKYXA | B96: AHU13-CARRIER-UnkModel-UnkSerial | C96: HVAC - AIR HANDLING UNIT | I96: no
A97: ASLDKYXA | B97: CND08-JCI-FPH-6HEM001617 | C97: HVAC - CONDENSER UNIT | I97: no
A98: AURROHXA | B98: GEN01-MARATHON-440FDR7112JJW-PM3176103 | C98: GENERATOR PM | E98: 150 | F98: 30682 | G98: 40 | H98: 25 | I98: no | J98: FIXED | K98: Diesel | L98: 1859
A99: AURROHXA | B99: CND03-LIEBERT-CDF205LY-91010038 | C99: HVAC - CONDENSER UNIT | I99: no
A100: AURROHXA | B100: AHU04-BRYANT-524JE12A000A20AAA-2415U13950 | C100: HVAC - AIR HANDLING UNIT | D100: 12000 | F100: 42156 | G100: 9 | H100: 15 | I100: yes
...

Sheet WS_Top200_Existing_Power
A1: CLLI | B1: Total Generator KW | C1: # racks | D1: Estimated Power kW (racks x 1.74) | E1: Which estimate is greater?
A2: ABRDNCXA | B2: 100 | C2: 27 | D2: 47 | E2: =IF(B2>D2, "Generator", "Racks") -> Generator | F2: =COUNTIF(E2:E201, "Generator") -> 162
A3: ADBNIAXO | B3: 75 | C3: 30 | D3: 52.2 | E3: =IF(B3>D3, "Generator", "Racks") -> Generator | F3: =COUNTIF(E2:E201, "Racks") -> 38
A4: ADELGAXA | B4: 60 | C4: 27 | D4: 47 | E4: =IF(B4>D4, "Generator", "Racks") -> Generator
A5: ALBIIAXO | B5: 125 | C5: 13 | D5: 22.6 | E5: =IF(B5>D5, "Generator", "Racks") -> Generator
A6: ALBMNCXA | B6: 350 | C6: 55 | D6: 95.7 | E6: =IF(B6>D6, "Generator", "Racks") -> Generator
A7: ALBYKYXA | B7: 115 | C7: 38 | D7: 66.1 | E7: =IF(B7>D7, "Generator", "Racks") -> Generator
A8: ALCHFL01 | C8: 4 | D8: 7 | E8: =IF(B8>D8, "Generator", "Racks") -> Racks
A9: ALCHFLAJ | E9: =IF(B9>D9, "Generator", "Racks") -> Racks
A10: ALCHFLXA | B10: 80 | C10: 32 | D10: 55.7 | E10: =IF(B10>D10, "Generator", "Racks") -> Generator
A11: ANDRTXXA | B11: 155 | C11: 46 | D11: 80 | E11: =IF(B11>D11, "Generator", "Racks") -> Generator
A12: ANWOIAXO | B12: 60 | C12: 8 | D12: 13.9 | E12: =IF(B12>D12, "Generator", "Racks") -> Generator
A13: ASHTOHXA | B13: 300 | C13: 125 | D13: 217.5 | E13: =IF(B13>D13, "Generator", "Racks") -> Generator
A14: ASLDKYXA | B14: 600 | C14: 232 | D14: 403.7 | E14: =IF(B14>D14, "Generator", "Racks") -> Generator
A15: AURROHXA | B15: 150 | C15: 70 | D15: 121.8 | E15: =IF(B15>D15, "Generator", "Racks") -> Generator
A16: BBVLKYXA | B16: 90 | C16: 28 | D16: 48.7 | E16: =IF(B16>D16, "Generator", "Racks") -> Generator
A17: BEREKYXA | B17: 150 | C17: 90 | D17: 156.6 | E17: =IF(B17>D17, "Generator", "Racks") -> Racks
A18: BKVLKYXA | B18: 80 | C18: 16 | D18: 27.8 | E18: =IF(B18>D18, "Generator", "Racks") -> Generator
A19: BLKLGAXA | B19: 100 | C19: 35 | D19: 60.9 | E19: =IF(B19>D19, "Generator", "Racks") -> Generator
A20: BLVIGABW | C20: 2 | D20: 3.5 | E20: =IF(B20>D20, "Generator", "Racks") -> Racks
A21: BNBGOHXA | B21: 100 | C21: 64 | D21: 111.4 | E21: =IF(B21>D21, "Generator", "Racks") -> Racks
A22: BRAROKXA | B22: 470 | C22: 150 | D22: 261 | E22: =IF(B22>D22, "Generator", "Racks") -> Generator
A23: BRAROKXB | B23: 510 | C23: 226 | D23: 393.2 | E23: =IF(B23>D23, "Generator", "Racks") -> Generator
A24: BRAROKXC | B24: 410 | C24: 109 | D24: 189.7 | E24: =IF(B24>D24, "Generator", "Racks") -> Generator
A25: BRAROKXD | B25: 350 | C25: 106 | D25: 184.4 | E25: =IF(B25>D25, "Generator", "Racks") -> Generator
A26: BRAROKXE | B26: 300 | C26: 38 | D26: 66.1 | E26: =IF(B26>D26, "Generator", "Racks") -> Generator
A27: BRFRFLXA | B27: 100 | C27: 20 | D27: 34.8 | E27: =IF(B27>D27, "Generator", "Racks") -> Generator
A28: BRHDKYXA | B28: 50 | C28: 14 | D28: 24.4 | E28: =IF(B28>D28, "Generator", "Racks") -> Generator
A29: BRSDKYXA | B29: 125 | C29: 41 | D29: 71.3 | E29: =IF(B29>D29, "Generator", "Racks") -> Generator
A30: BWFDTXXA | B30: 685 | C30: 93 | D30: 161.8 | E30: =IF(B30>D30, "Generator", "Racks") -> Generator
A31: CAIRGAXA | B31: 125 | C31: 37 | D31: 64.4 | E31: =IF(B31>D31, "Generator", "Racks") -> Generator
A32: CECLOHXA | C32: 5 | D32: 8.7 | E32: =IF(B32>D32, "Generator", "Racks") -> Racks
A33: CETNIAXC | B33: 100 | C33: 24 | D33: 41.8 | E33: =IF(B33>D33, "Generator", "Racks") -> Generator
A34: CHGVNCXA | B34: 350 | C34: 38 | D34: 66.1 | E34: =IF(B34>D34, "Generator", "Racks") -> Generator
A35: CHRDOHXA | B35: 150 | C35: 100 | D35: 174 | E35: =IF(B35>D35, "Generator", "Racks") -> Racks
A36: CHRTIAXC | B36: 137 | C36: 32 | D36: 55.7 | E36: =IF(B36>D36, "Generator", "Racks") -> Generator
A37: CHTHOKXD | B37: 300 | C37: 21 | D37: 36.5 | E37: =IF(B37>D37, "Generator", "Racks") -> Generator
A38: CHWOGAXA | B38: 200 | C38: 40 | D38: 69.6 | E38: =IF(B38>D38, "Generator", "Racks") -> Generator
A39: CLDGTXXA | B39: 40 | C39: 23 | D39: 40 | E39: =IF(B39>D39, "Generator", "Racks") -> Racks
A40: CLEVGAXA | B40: 250 | C40: 124 | D40: 215.8 | E40: =IF(B40>D40, "Generator", "Racks") -> Generator
A41: CLHNFLXA | B41: 60 | C41: 44 | D41: 76.6 | E41: =IF(B41>D41, "Generator", "Racks") -> Racks
A42: CLJTIAWH | B42: 90 | C42: 2 | D42: 3.5 | E42: =IF(B42>D42, "Generator", "Racks") -> Generator
A43: CLRDIAXT | B43: 160 | C43: 24 | D43: 41.8 | E43: =IF(B43>D43, "Generator", "Racks") -> Generator
A44: CLSTOHXA | B44: 150 | C44: 24 | D44: 41.8 | E44: =IF(B44>D44, "Generator", "Racks") -> Generator
... A58: DHLNGAXA | B58: 150 | C58: 50 | D58: 87 | E58: =IF(B58>D58, "Generator", "Racks") -> Generator
A59: DLHRTXXA | C59: 20 | D59: 34.8 | E59: =IF(B59>D59, "Generator", "Racks") -> Racks
A60: DLRKARXA | B60: 6 | C60: 6 | D60: 10.4 | E60: =IF(B60>D60, "Generator", "Racks") -> Racks
A61: DLTNGAXD | B61: 250 | C61: 18 | D61: 31.3 | E61: =IF(B61>D61, "Generator", "Racks") -> Generator
A62: DMMTTXXA | B62: 150 | C62: 28 | D62: 48.7 | E62: =IF(B62>D62, "Generator", "Racks") -> Generator
A63: DNSNIAXO | B63: 205 | C63: 21 | D63: 36.5 | E63: =IF(B63>D63, "Generator", "Racks") -> Generator
A64: DNVLGAXA | B64: 100 | C64: 30 | D64: 52.2 | E64: =IF(B64>D64, "Generator", "Racks") -> Generator
A65: DUMSTXXA | B65: 150 | C65: 74 | D65: 128.8 | E65: =IF(B65>D65, "Generator", "Racks") -> Generator
A66: DWSNGAXA | B66: 60 | C66: 35 | D66: 60.9 | E66: =IF(B66>D66, "Generator", "Racks") -> Racks
A67: DYVLIAXO | B67: 60 | C67: 26 | D67: 45.2 | E67: =IF(B67>D67, "Generator", "Racks") -> Generator
A68: EDWDIAXO | C68: 4 | D68: 7 | E68: =IF(B68>D68, "Generator", "Racks") -> Racks
A69: ELYROHXA | B69: 380 | C69: 159 | D69: 276.7 | E69: =IF(B69>D69, "Generator", "Racks") -> Generator
A70: ELYROHXB | B70: 135 | C70: 52 | D70: 90.5 | E70: =IF(B70>D70, "Generator", "Racks") -> Generator
A71: ELYROHXD | B71: 150 | C71: 16 | D71: 27.8 | E71: =IF(B71>D71, "Generator", "Racks") -> Generator
A72: ELYROHXE | B72: 125 | C72: 33 | D72: 57.4 | E72: =IF(B72>D72, "Generator", "Racks") -> Generator
A73: EMBGIAXP | B73: 150 | C73: 23 | D73: 40 | E73: =IF(B73>D73, "Generator", "Racks") -> Generator
A74: EVRSKYXA | B74: 50 | C74: 42 | D74: 73.1 | E74: =IF(B74>D74, "Generator", "Racks") -> Racks
A75: FLTNGAXA | B75: 125 | C75: 25 | D75: 43.5 | E75: =IF(B75>D75, "Generator", "Racks") -> Generator
A76: FMBGKYXA | B76: 150 | C76: 69 | D76: 120.1 | E76: =IF(B76>D76, "Generator", "Racks") -> Generator
A77: FRCYIAXO | B77: 100 | C77: 15 | D77: 26.1 | E77: =IF(B77>D77, "Generator", "Racks") -> Generator
A78: FRDYARXA | B78: 80 | C78: 36 | D78: 62.6 | E78: =IF(B78>D78, "Generator", "Racks") -> Generator
A79: FRFDIAXC | B79: 135 | C79: 40 | D79: 69.6 | E79: =IF(B79>D79, "Generator", "Racks") -> Generator
A80: FRVWOHXA | B80: 100 | C80: 28 | D80: 48.7 | E80: =IF(B80>D80, "Generator", "Racks") -> Generator
... A83: GNBRARXA | B83: 150 | C83: 64 | D83: 111.4 | E83: =IF(B83>D83, "Generator", "Racks") -> Generator
A84: GNFDIAAJ | C84: 0 | E84: =IF(B84>D84, "Generator", "Racks") -> Racks
A85: GNUPKYXA | B85: 100 | C85: 52 | D85: 90.5 | E85: =IF(B85>D85, "Generator", "Racks") -> Generator
A86: GRNLIAXC | B86: 100 | C86: 84 | D86: 146.2 | E86: =IF(B86>D86, "Generator", "Racks") -> Racks
A87: GRQYNCXA | B87: 150 | C87: 30 | D87: 52.2 | E87: =IF(B87>D87, "Generator", "Racks") -> Generator
A88: GRVIOHXA | B88: 100 | C88: 24 | D88: 41.8 | E88: =IF(B88>D88, "Generator", "Racks") -> Generator
A89: HDSNOHXA | B89: 660 | C89: 170 | D89: 295.8 | E89: =IF(B89>D89, "Generator", "Racks") -> Generator
A90: HDSNOHXB | C90: 20 | D90: 34.8 | E90: =IF(B90>D90, "Generator", "Racks") -> Racks
A91: HETHOHXA | B91: 100 | C91: 27 | D91: 47 | E91: =IF(B91>D91, "Generator", "Racks") -> Generator
A92: HIRMOHXA | C92: 14 | D92: 24.4 | E92: =IF(B92>D92, "Generator", "Racks") -> Racks
A93: HLCRIAXP | C93: 6 | D93: 10.4 | E93: =IF(B93>D93, "Generator", "Racks") -> Racks
A94: HLRDFLXA | B94: 60 | C94: 30 | D94: 52.2 | E94: =IF(B94>D94, "Generator", "Racks") -> Generator
A95: HRSNARXA | B95: 700 | C95: 81 | D95: 140.9 | E95: =IF(B95>D95, "Generator", "Racks") -> Generator
A96: HWSSGAXA | B96: 150 | C96: 19 | D96: 33.1 | E96: =IF(B96>D96, "Generator", "Racks") -> Generator
A97: HZRDKYXA | B97: 250 | C97: 133 | D97: 231.4 | E97: =IF(B97>D97, "Generator", "Racks") -> Generator
A98: IRTNGAXA | B98: 100 | C98: 26 | D98: 45.2 | E98: =IF(B98>D98, "Generator", "Racks") -> Generator
A99: JLLYIAXE | C99: 3 | D99: 5.2 | E99: =IF(B99>D99, "Generator", "Racks") -> Racks
A100: JSPRGAXA | B100: 125 | C100: 22 | D100: 38.3 | E100: =IF(B100>D100, "Generator", "Racks") -> Generator
A101: KGVLOHXA | B101: 85 | C101: 23 | D101: 40 | E101: =IF(B101>D101, "Generator", "Racks") -> Generator
A102: KNTNOHXA | B102: 125 | C102: 30 | D102: 52.2 | E102: =IF(B102>D102, "Generator", "Racks") -> Generator
A103: KNVLIAWH | B103: 65 | C103: 5 | D103: 8.7 | E103: =IF(B103>D103, "Generator", "Racks") -> Generator
A104: KNVLIAXC | B104: 600 | C104: 79 | D104: 137.5 | E104: =IF(B104>D104, "Generator", "Racks") -> Generator
A105: KNVLIAXD | C105: 5 | D105: 8.7 | E105: =IF(B105>D105, "Generator", "Racks") -> Racks
A106: KRVLTXXA | B106: 300 | C106: 144 | D106: 250.6 | E106: =IF(B106>D106, "Generator", "Racks") -> Generator
A107: LAMSTXXA | B107: 60 | C107: 20 | D107: 34.8 | E107: =IF(B107>D107, "Generator", "Racks") -> Generator
A108: LAVNGAXA | B108: 150 | C108: 42 | D108: 73.1 | E108: =IF(B108>D108, "Generator", "Racks") -> Generator
A109: LEDSALXA | B109: 125 | C109: 27 | D109: 47 | E109: =IF(B109>D109, "Generator", "Racks") -> Generator
A110: LEDSALXB | B110: 200 | C110: 52 | D110: 90.5 | E110: =IF(B110>D110, "Generator", "Racks") -> Generator
A111: LFYTGAXA | B111: 125 | C111: 37 | D111: 64.4 | E111: =IF(B111>D111, "Generator", "Racks") -> Generator
A112: LKCYIAXO | C112: 9 | D112: 15.7 | E112: =IF(B112>D112, "Generator", "Racks") -> Racks
A113: LTFDKYXA | B113: 100 | C113: 35 | D113: 60.9 | E113: =IF(B113>D113, "Generator", "Racks") -> Generator
A114: LTFDTXXA | B114: 250 | C114: 39 | D114: 67.9 | E114: =IF(B114>D114, "Generator", "Racks") -> Generator
A115: LVLDTXXA | B115: 600 | C115: 75 | D115: 130.5 | E115: =IF(B115>D115, "Generator", "Racks") -> Generator
...

Sheet Site detail lookup
B2: # | C2: CLLI | D2: City | E2: State | F2: County | G2: Street Address | H2: Latitude | I2: Longitude | J2: Parcel Size (acres) | K2: Racks - Legacy Tenant (SG4 portfolio range) | L2: Site Capacity (SG4 portfolio range) | M2: Facility Size (sq ft) | N2: [Davis notes?] | O2: Distance: Nearest transmission (mi) | P2: Nearest transmission capacity (kv) | Q2: line_from_sub | R2: line_to_sub
B3: 1 | C3: ABRDNCXA | D3: Aberdeen | E3: NC | F3: Moore | G3: 211 North Poplar Street | H3: 35.1347 | I3: -79.4268 | J3: =INDEX(WS_Sites_Parcel_Sizes_FINAL!$I:$I, MATCH('Site detail lookup'!$C3, WS_Sites_Parcel_Sizes_FINAL!$A:$A, 0)) -> 1.3423 | K3: =INDEX('Top 200 COs'!X:X, MATCH('Site detail lookup'!$C3, 'Top 200 COs'!$C:$C, 0)) -> 27 | L3: =INDEX(WS_Top200_Existing_Power!B:B, MATCH('Site detail lookup'!C3, WS_Top200_Existing_Power!A:A, 0)) -> 100 | M3: =INDEX('Top 200 COs'!W:W, MATCH('Site detail lookup'!$C3, 'Top 200 COs'!$C:$C, 0)) -> 3604 | O3: =INDEX(WS_Top200_Transm_Dist_2!G:G, MATCH('Site detail lookup'!$C3, WS_Top200_Transm_Dist_2!$B:$B, 0))/5280 -> 0.94715909 | P3: =INDEX(WS_Top200_Transm_Dist_2!O:O, MATCH('Site detail lookup'!$C3, WS_Top200_Transm_Dist_2!$B:$B, 0)) -> -999999 | Q3: =INDEX(WS_Top200_Transm_Dist_2!I:I, MATCH('Site detail lookup'!$C3, WS_Top200_Transm_Dist_2!$B:$B, 0)) -> TAP147638 | R3: =INDEX(WS_Top200_Transm_Dist_2!J:J, MATCH('Site detail lookup'!$C3, WS_Top200_Transm_Dist_2!$B:$B, 0)) -> TAP147639 | S3: Were you making notes in the Windstream 200 file? If so, possible to move those to the main Targeted_Sites_Overview file?
B4: 2 | C4: ALBMNCXA | D4: Albemarle | E4: NC | F4: Stanly | G4: 250 North 1st Street | H4: 35.354 | I4: -80.1991 | J4: =INDEX(WS_Sites_Parcel_Sizes_FINAL!$I:$I, MATCH('Site detail lookup'!$C4, WS_Sites_Parcel_Sizes_FINAL!$A:$A, 0)) -> 0.8423 | K4: =INDEX('Top 200 COs'!X:X, MATCH('Site detail lookup'!$C4, 'Top 200 COs'!$C:$C, 0)) -> 55 | L4: =INDEX(WS_Top200_Existing_Power!B:B, MATCH('Site detail lookup'!C4, WS_Top200_Existing_Power!A:A, 0)) -> 350 | M4: =INDEX('Top 200 COs'!W:W, MATCH('Site detail lookup'!$C4, 'Top 200 COs'!$C:$C, 0)) -> 8000 | O4: =INDEX(WS_Top200_Transm_Dist_2!G:G, MATCH('Site detail lookup'!$C4, WS_Top200_Transm_Dist_2!$B:$B, 0))/5280 -> 0.28276515 | P4: =INDEX(WS_Top200_Transm_Dist_2!O:O, MATCH('Site detail lookup'!$C4, WS_Top200_Transm_Dist_2!$B:$B, 0)) -> 100 | Q4: =INDEX(WS_Top200_Transm_Dist_2!I:I, MATCH('Site detail lookup'!$C4, WS_Top200_Transm_Dist_2!$B:$B, 0)) -> UNKNOWN114426 | R4: =INDEX(WS_Top200_Transm_Dist_2!J:J, MATCH('Site detail lookup'!$C4, WS_Top200_Transm_Dist_2!$B:$B, 0)) -> TAP150528
B5: 3 | C5: CHGVNCXA | D5: China Grove | E5: NC | F5: Rowan | G5: 1525 South Main Street | H5: 35.5569 | I5: -80.5959 | J5: =INDEX(WS_Sites_Parcel_Sizes_FINAL!$I:$I, MATCH('Site detail lookup'!$C5, WS_Sites_Parcel_Sizes_FINAL!$A:$A, 0)) -> 0.4238 | K5: =INDEX('Top 200 COs'!X:X, MATCH('Site detail lookup'!$C5, 'Top 200 COs'!$C:$C, 0)) -> 38 | L5: =INDEX(WS_Top200_Existing_Power!B:B, MATCH('Site detail lookup'!C5, WS_Top200_Existing_Power!A:A, 0)) -> 350 | M5: =INDEX('Top 200 COs'!W:W, MATCH('Site detail lookup'!$C5, 'Top 200 COs'!$C:$C, 0)) -> 12000 | O5: =INDEX(WS_Top200_Transm_Dist_2!G:G, MATCH('Site detail lookup'!$C5, WS_Top200_Transm_Dist_2!$B:$B, 0))/5280 -> 0.13977273 | P5: =INDEX(WS_Top200_Transm_Dist_2!O:O, MATCH('Site detail lookup'!$C5, WS_Top200_Transm_Dist_2!$B:$B, 0)) -> 100 | Q5: =INDEX(WS_Top200_Transm_Dist_2!I:I, MATCH('Site detail lookup'!$C5, WS_Top200_Transm_Dist_2!$B:$B, 0)) -> UNKNOWN114688 | R5: =INDEX(WS_Top200_Transm_Dist_2!J:J, MATCH('Site detail lookup'!$C5, WS_Top200_Transm_Dist_2!$B:$B, 0)) -> UNKNOWN114689
B6: 4 | C6: FRVWOHXA | D6: Fairview (Barnesville?) | E6: OH | F6: Guernsey (Belmont?) | G6: 32699 Old National Road | H6: 40.0595 | I6: -81.2204 | J6: =INDEX(WS_Sites_Parcel_Sizes_FINAL!$I:$I, MATCH('Site detail lookup'!$C6, WS_Sites_Parcel_Sizes_FINAL!$A:$A, 0)) -> 0.9684 | K6: =INDEX('Top 200 COs'!X:X, MATCH('Site detail lookup'!$C6, 'Top 200 COs'!$C:$C, 0)) -> 28 | L6: =INDEX(WS_Top200_Existing_Power!B:B, MATCH('Site detail lookup'!C6, WS_Top200_Existing_Power!A:A, 0)) -> 100 | M6: =INDEX('Top 200 COs'!W:W, MATCH('Site detail lookup'!$C6, 'Top 200 COs'!$C:$C, 0)) -> 3022 | O6: =INDEX(WS_Top200_Transm_Dist_2!G:G, MATCH('Site detail lookup'!$C6, WS_Top200_Transm_Dist_2!$B:$B, 0))/5280 -> 5.5757576 | P6: =INDEX(WS_Top200_Transm_Dist_2!O:O, MATCH('Site detail lookup'!$C6, WS_Top200_Transm_Dist_2!$B:$B, 0)) -> 138 | Q6: =INDEX(WS_Top200_Transm_Dist_2!I:I, MATCH('Site detail lookup'!$C6, WS_Top200_Transm_Dist_2!$B:$B, 0)) -> SPEIDEL | R6: =INDEX(WS_Top200_Transm_Dist_2!J:J, MATCH('Site detail lookup'!$C6, WS_Top200_Transm_Dist_2!$B:$B, 0)) -> BARNESVILLE
B7: 5 | C7: ASHTOHXA | D7: Ashtabula | E7: OH | F7: Ashtabula | G7: 4616 Park Avenue | H7: 41.8655 | I7: -80.7834 | J7: =INDEX(WS_Sites_Parcel_Sizes_FINAL!$I:$I, MATCH('Site detail lookup'!$C7, WS_Sites_Parcel_Sizes_FINAL!$A:$A, 0)) -> 0.3376 | K7: =INDEX('Top 200 COs'!X:X, MATCH('Site detail lookup'!$C7, 'Top 200 COs'!$C:$C, 0)) -> 125 | L7: =INDEX(WS_Top200_Existing_Power!B:B, MATCH('Site detail lookup'!C7, WS_Top200_Existing_Power!A:A, 0)) -> 300 | M7: =INDEX('Top 200 COs'!W:W, MATCH('Site detail lookup'!$C7, 'Top 200 COs'!$C:$C, 0)) -> 30000 | O7: =INDEX(WS_Top200_Transm_Dist_2!G:G, MATCH('Site detail lookup'!$C7, WS_Top200_Transm_Dist_2!$B:$B, 0))/5280 -> 1.0676136 | P7: =INDEX(WS_Top200_Transm_Dist_2!O:O, MATCH('Site detail lookup'!$C7, WS_Top200_Transm_Dist_2!$B:$B, 0)) -> 345 | Q7: =INDEX(WS_Top200_Transm_Dist_2!I:I, MATCH('Site detail lookup'!$C7, WS_Top200_Transm_Dist_2!$B:$B, 0)) -> TAP136893 | R7: =INDEX(WS_Top200_Transm_Dist_2!J:J, MATCH('Site detail lookup'!$C7, WS_Top200_Transm_Dist_2!$B:$B, 0)) -> PERRY
B8: 6 | C8: BNBGOHXA | D8: Bainbridge Twp | E8: OH | F8: Geauga | G8: 8425 Baindridge Road | H8: 41.3857 | I8: -81.3406 | J8: =INDEX(WS_Sites_Parcel_Sizes_FINAL!$I:$I, MATCH('Site detail lookup'!$C8, WS_Sites_Parcel_Sizes_FINAL!$A:$A, 0)) -> 0.3535 | K8: =INDEX('Top 200 COs'!X:X, MATCH('Site detail lookup'!$C8, 'Top 200 COs'!$C:$C, 0)) -> 64 | L8: =INDEX(WS_Top200_Existing_Power!B:B, MATCH('Site detail lookup'!C8, WS_Top200_Existing_Power!A:A, 0)) -> 100 | M8: =INDEX('Top 200 COs'!W:W, MATCH('Site detail lookup'!$C8, 'Top 200 COs'!$C:$C, 0)) -> 14355 | N8: seeing parcel size as 0.25 | O8: =INDEX(WS_Top200_Transm_Dist_2!G:G, MATCH('Site detail lookup'!$C8, WS_Top200_Transm_Dist_2!$B:$B, 0))/5280 -> 2.400947 | P8: =INDEX(WS_Top200_Transm_Dist_2!O:O, MATCH('Site detail lookup'!$C8, WS_Top200_Transm_Dist_2!$B:$B, 0)) -> 345 | Q8: =INDEX(WS_Top200_Transm_Dist_2!I:I, MATCH('Site detail lookup'!$C8, WS_Top200_Transm_Dist_2!$B:$B, 0)) -> UNKNOWN137113 | R8: =INDEX(WS_Top200_Transm_Dist_2!J:J, MATCH('Site detail lookup'!$C8, WS_Top200_Transm_Dist_2!$B:$B, 0)) -> LEROY CENTER
B9: 7 | C9: CHRDOHXA | D9: Chardon | E9: OH | F9: Geauga | G9: 205 South Hambden Street | H9: 41.5813 | I9: -81.2021 | J9: =INDEX(WS_Sites_Parcel_Sizes_FINAL!$I:$I, MATCH('Site detail lookup'!$C9, WS_Sites_Parcel_Sizes_FINAL!$A:$A, 0)) -> 0.1915 | K9: =INDEX('Top 200 COs'!X:X, MATCH('Site detail lookup'!$C9, 'Top 200 COs'!$C:$C, 0)) -> 100 | L9: =INDEX(WS_Top200_Existing_Power!B:B, MATCH('Site detail lookup'!C9, WS_Top200_Existing_Power!A:A, 0)) -> 150 | M9: =INDEX('Top 200 COs'!W:W, MATCH('Site detail lookup'!$C9, 'Top 200 COs'!$C:$C, 0)) -> 12446 | O9: =INDEX(WS_Top200_Transm_Dist_2!G:G, MATCH('Site detail lookup'!$C9, WS_Top200_Transm_Dist_2!$B:$B, 0))/5280 -> 0.67102273 | P9: =INDEX(WS_Top200_Transm_Dist_2!O:O, MATCH('Site detail lookup'!$C9, WS_Top200_Transm_Dist_2!$B:$B, 0)) -> 138 | Q9: =INDEX(WS_Top200_Transm_Dist_2!I:I, MATCH('Site detail lookup'!$C9, WS_Top200_Transm_Dist_2!$B:$B, 0)) -> UNKNOWN112912 | R9: =INDEX(WS_Top200_Transm_Dist_2!J:J, MATCH('Site detail lookup'!$C9, WS_Top200_Transm_Dist_2!$B:$B, 0)) -> TAP148482
B10: 8 | C10: ELYROHXA | D10: Elyria | E10: OH | F10: Lorain | G10: 363 3rd Street | H10: 41.3657 | I10: -82.11 | J10: =INDEX(WS_Sites_Parcel_Sizes_FINAL!$I:$I, MATCH('Site detail lookup'!$C10, WS_Sites_Parcel_Sizes_FINAL!$A:$A, 0)) -> 0.5012 | K10: =INDEX('Top 200 COs'!X:X, MATCH('Site detail lookup'!$C10, 'Top 200 COs'!$C:$C, 0)) -> 159 | L10: =INDEX(WS_Top200_Existing_Power!B:B, MATCH('Site detail lookup'!C10, WS_Top200_Existing_Power!A:A, 0)) -> 380 | M10: =INDEX('Top 200 COs'!W:W, MATCH('Site detail lookup'!$C10, 'Top 200 COs'!$C:$C, 0)) -> 73218 | O10: =INDEX(WS_Top200_Transm_Dist_2!G:G, MATCH('Site detail lookup'!$C10, WS_Top200_Transm_Dist_2!$B:$B, 0))/5280 -> 0.93787879 | P10: =INDEX(WS_Top200_Transm_Dist_2!O:O, MATCH('Site detail lookup'!$C10, WS_Top200_Transm_Dist_2!$B:$B, 0)) -> 138 | Q10: =INDEX(WS_Top200_Transm_Dist_2!I:I, MATCH('Site detail lookup'!$C10, WS_Top200_Transm_Dist_2!$B:$B, 0)) -> UNKNOWN113152 | R10: =INDEX(WS_Top200_Transm_Dist_2!J:J, MATCH('Site detail lookup'!$C10, WS_Top200_Transm_Dist_2!$B:$B, 0)) -> UNKNOWN113217
B11: 9 | C11: GENVOHXA | D11: Geneva | E11: OH | F11: Ashtabula | G11: 37 South Forest Street | H11: 41.8053 | I11: -80.9457 | J11: =INDEX(WS_Sites_Parcel_Sizes_FINAL!$I:$I, MATCH('Site detail lookup'!$C11, WS_Sites_Parcel_Sizes_FINAL!$A:$A, 0)) -> 0.8339 | K11: =INDEX('Top 200 COs'!X:X, MATCH('Site detail lookup'!$C11, 'Top 200 COs'!$C:$C, 0)) -> 25 | L11: =INDEX(WS_Top200_Existing_Power!B:B, MATCH('Site detail lookup'!C11, WS_Top200_Existing_Power!A:A, 0)) -> 190 | M11: =INDEX('Top 200 COs'!W:W, MATCH('Site detail lookup'!$C11, 'Top 200 COs'!$C:$C, 0)) -> 12477 | O11: =INDEX(WS_Top200_Transm_Dist_2!G:G, MATCH('Site detail lookup'!$C11, WS_Top200_Transm_Dist_2!$B:$B, 0))/5280 -> 2.5704545 | P11: =INDEX(WS_Top200_Transm_Dist_2!O:O, MATCH('Site detail lookup'!$C11, WS_Top200_Transm_Dist_2!$B:$B, 0)) -> 345 | Q11: =INDEX(WS_Top200_Transm_Dist_2!I:I, MATCH('Site detail lookup'!$C11, WS_Top200_Transm_Dist_2!$B:$B, 0)) -> TAP136893 | R11: =INDEX(WS_Top200_Transm_Dist_2!J:J, MATCH('Site detail lookup'!$C11, WS_Top200_Transm_Dist_2!$B:$B, 0)) -> PERRY
B12: 10 | C12: MDSNOHXA | D12: Madison | E12: OH | F12: Lake | G12: 2740 Hubbard Road | H12: 41.8003 | I12: -81.049 | J12: =INDEX(WS_Sites_Parcel_Sizes_FINAL!$I:$I, MATCH('Site detail lookup'!$C12, WS_Sites_Parcel_Sizes_FINAL!$A:$A, 0)) -> 0.6524 | K12: =INDEX('Top 200 COs'!X:X, MATCH('Site detail lookup'!$C12, 'Top 200 COs'!$C:$C, 0)) -> 28 | L12: =INDEX(WS_Top200_Existing_Power!B:B, MATCH('Site detail lookup'!C12, WS_Top200_Existing_Power!A:A, 0)) -> 125 | M12: =INDEX('Top 200 COs'!W:W, MATCH('Site detail lookup'!$C12, 'Top 200 COs'!$C:$C, 0)) -> 3222 | O12: =INDEX(WS_Top200_Transm_Dist_2!G:G, MATCH('Site detail lookup'!$C12, WS_Top200_Transm_Dist_2!$B:$B, 0))/5280 -> 0.68579545 | P12: =INDEX(WS_Top200_Transm_Dist_2!O:O, MATCH('Site detail lookup'!$C12, WS_Top200_Transm_Dist_2!$B:$B, 0)) -> 345 | Q12: =INDEX(WS_Top200_Transm_Dist_2!I:I, MATCH('Site detail lookup'!$C12, WS_Top200_Transm_Dist_2!$B:$B, 0)) -> TAP136893 | R12: =INDEX(WS_Top200_Transm_Dist_2!J:J, MATCH('Site detail lookup'!$C12, WS_Top200_Transm_Dist_2!$B:$B, 0)) -> PERRY
B13: 11 | C13: NRFDOHXA | D13: Northfield | E13: OH | F13: Summit | G13: 54 Leonard Avenue | H13: 41.3147 | I13: -81.537 | J13: =INDEX(WS_Sites_Parcel_Sizes_FINAL!$I:$I, MATCH('Site detail lookup'!$C13, WS_Sites_Parcel_Sizes_FINAL!$A:$A, 0)) -> 0.1685 | K13: =INDEX('Top 200 COs'!X:X, MATCH('Site detail lookup'!$C13, 'Top 200 COs'!$C:$C, 0)) -> 93 | L13: =INDEX(WS_Top200_Existing_Power!B:B, MATCH('Site detail lookup'!C13, WS_Top200_Existing_Power!A:A, 0)) -> 200 | M13: =INDEX('Top 200 COs'!W:W, MATCH('Site detail lookup'!$C13, 'Top 200 COs'!$C:$C, 0)) -> 66721 | O13: =INDEX(WS_Top200_Transm_Dist_2!G:G, MATCH('Site detail lookup'!$C13, WS_Top200_Transm_Dist_2!$B:$B, 0))/5280 -> 0.55246212 | P13: =INDEX(WS_Top200_Transm_Dist_2!O:O, MATCH('Site detail lookup'!$C13, WS_Top200_Transm_Dist_2!$B:$B, 0)) -> 345 | Q13: =INDEX(WS_Top200_Transm_Dist_2!I:I, MATCH('Site detail lookup'!$C13, WS_Top200_Transm_Dist_2!$B:$B, 0)) -> UNKNOWN137113 | R13: =INDEX(WS_Top200_Transm_Dist_2!J:J, MATCH('Site detail lookup'!$C13, WS_Top200_Transm_Dist_2!$B:$B, 0)) -> HANNA
B14: 12 | C14: RCFDOHXA | D14: Richfield | E14: OH | F14: Summit | G14: 4676 West Streetsboro Road | H14: 41.2393 | I14: -81.6558 | J14: =INDEX(WS_Sites_Parcel_Sizes_FINAL!$I:$I, MATCH('Site detail lookup'!$C14, WS_Sites_Parcel_Sizes_FINAL!$A:$A, 0)) -> 0.1615 | K14: =INDEX('Top 200 COs'!X:X, MATCH('Site detail lookup'!$C14, 'Top 200 COs'!$C:$C, 0)) -> 27 | L14: =INDEX(WS_Top200_Existing_Power!B:B, MATCH('Site detail lookup'!C14, WS_Top200_Existing_Power!A:A, 0)) -> 100 | M14: =INDEX('Top 200 COs'!W:W, MATCH('Site detail lookup'!$C14, 'Top 200 COs'!$C:$C, 0)) -> 20000 | N14: seeing parcel size as 0.3 | O14: =INDEX(WS_Top200_Transm_Dist_2!G:G, MATCH('Site detail lookup'!$C14, WS_Top200_Transm_Dist_2!$B:$B, 0))/5280 -> 1.3772727 | P14: =INDEX(WS_Top200_Transm_Dist_2!O:O, MATCH('Site detail lookup'!$C14, WS_Top200_Transm_Dist_2!$B:$B, 0)) -> 138 | Q14: =INDEX(WS_Top200_Transm_Dist_2!I:I, MATCH('Site detail lookup'!$C14, WS_Top200_Transm_Dist_2!$B:$B, 0)) -> TAP137138 | R14: =INDEX(WS_Top200_Transm_Dist_2!J:J, MATCH('Site detail lookup'!$C14, WS_Top200_Transm_Dist_2!$B:$B, 0)) -> WEST AKRON
B15: 13 | C15: TWBGOHXA | D15: Twinsburg | E15: OH | F15: Summit | G15: 2684 Route 82 (2678 E Aurora Rd?) | H15: 41.3111 | I15: -81.4423 | J15: =INDEX(WS_Sites_Parcel_Sizes_FINAL!$I:$I, MATCH('Site detail lookup'!$C15, WS_Sites_Parcel_Sizes_FINAL!$A:$A, 0)) -> 0.4985 | K15: =INDEX('Top 200 COs'!X:X, MATCH('Site detail lookup'!$C15, 'Top 200 COs'!$C:$C, 0)) -> 99 | L15: =INDEX(WS_Top200_Existing_Power!B:B, MATCH('Site detail lookup'!C15, WS_Top200_Existing_Power!A:A, 0)) -> 115 | M15: =INDEX('Top 200 COs'!W:W, MATCH('Site detail lookup'!$C15, 'Top 200 COs'!$C:$C, 0)) -> 20000 | N15: potential duplicate | O15: =INDEX(WS_Top200_Transm_Dist_2!G:G, MATCH('Site detail lookup'!$C15, WS_Top200_Transm_Dist_2!$B:$B, 0))/5280 -> 0.25530303 | P15: =INDEX(WS_Top200_Transm_Dist_2!O:O, MATCH('Site detail lookup'!$C15, WS_Top200_Transm_Dist_2!$B:$B, 0)) -> -999999 | Q15: =INDEX(WS_Top200_Transm_Dist_2!I:I, MATCH('Site detail lookup'!$C15, WS_Top200_Transm_Dist_2!$B:$B, 0)) -> CASE | R15: =INDEX(WS_Top200_Transm_Dist_2!J:J, MATCH('Site detail lookup'!$C15, WS_Top200_Transm_Dist_2!$B:$B, 0)) -> TWINSBURG
B16: 14 | C16: TWBGOHIR | D16: Twinsburg | E16: OH | F16: Summit | G16: 2684 East Aurora Road | H16: 41.3112 | I16: -81.4423 | J16: =INDEX(WS_Sites_Parcel_Sizes_FINAL!$I:$I, MATCH('Site detail lookup'!$C16, WS_Sites_Parcel_Sizes_FINAL!$A:$A, 0)) -> 0.4985 | K16: =INDEX('Top 200 COs'!X:X, MATCH('Site detail lookup'!$C16, 'Top 200 COs'!$C:$C, 0)) -> 0 | L16: =INDEX(WS_Top200_Existing_Power!B:B, MATCH('Site detail lookup'!C16, WS_Top200_Existing_Power!A:A, 0)) -> 0 | M16: =INDEX('Top 200 COs'!W:W, MATCH('Site detail lookup'!$C16, 'Top 200 COs'!$C:$C, 0)) -> 20000 | N16: potential duplicate | O16: =INDEX(WS_Top200_Transm_Dist_2!G:G, MATCH('Site detail lookup'!$C16, WS_Top200_Transm_Dist_2!$B:$B, 0))/5280 -> 0.26287879 | P16: =INDEX(WS_Top200_Transm_Dist_2!O:O, MATCH('Site detail lookup'!$C16, WS_Top200_Transm_Dist_2!$B:$B, 0)) -> -999999 | Q16: =INDEX(WS_Top200_Transm_Dist_2!I:I, MATCH('Site detail lookup'!$C16, WS_Top200_Transm_Dist_2!$B:$B, 0)) -> CASE | R16: =INDEX(WS_Top200_Transm_Dist_2!J:J, MATCH('Site detail lookup'!$C16, WS_Top200_Transm_Dist_2!$B:$B, 0)) -> TWINSBURG
B17: 15 | C17: NWRKOHXD | D17: Newark | E17: OH | F17: Licking | G17: 7322 Dorsey Mill Road Southeast (343 Dorsey Mills Rd?) | H17: 40.0136 | I17: -82.4046 | J17: =INDEX(WS_Sites_Parcel_Sizes_FINAL!$I:$I, MATCH('Site detail lookup'!$C17, WS_Sites_Parcel_Sizes_FINAL!$A:$A, 0)) -> 0.386 | K17: =INDEX('Top 200 COs'!X:X, MATCH('Site detail lookup'!$C17, 'Top 200 COs'!$C:$C, 0)) -> 24 | L17: =INDEX(WS_Top200_Existing_Power!B:B, MATCH('Site detail lookup'!C17, WS_Top200_Existing_Power!A:A, 0)) -> 75 | M17: =INDEX('Top 200 COs'!W:W, MATCH('Site detail lookup'!$C17, 'Top 200 COs'!$C:$C, 0)) -> 3890 | N17: seeing parcel size as 0.52 | O17: =INDEX(WS_Top200_Transm_Dist_2!G:G, MATCH('Site detail lookup'!$C17, WS_Top200_Transm_Dist_2!$B:$B, 0))/5280 -> 1.0511364 | P17: =INDEX(WS_Top200_Transm_Dist_2!O:O, MATCH('Site detail lookup'!$C17, WS_Top200_Transm_Dist_2!$B:$B, 0)) -> 69 | Q17: =INDEX(WS_Top200_Transm_Dist_2!I:I, MATCH('Site detail lookup'!$C17, WS_Top200_Transm_Dist_2!$B:$B, 0)) -> TAP158957 | R17: =INDEX(WS_Top200_Transm_Dist_2!J:J, MATCH('Site detail lookup'!$C17, WS_Top200_Transm_Dist_2!$B:$B, 0)) -> UNKNOWN163359
B18: 16 | C18: NWRKOHXA | D18: Newark | E18: OH | F18: Licking | G18: 66 North 4th Street | H18: 40.0594 | I18: -82.4049 | J18: =INDEX(WS_Sites_Parcel_Sizes_FINAL!$I:$I, MATCH('Site detail lookup'!$C18, WS_Sites_Parcel_Sizes_FINAL!$A:$A, 0)) -> 0.2758 | K18: =INDEX('Top 200 COs'!X:X, MATCH('Site detail lookup'!$C18, 'Top 200 COs'!$C:$C, 0)) -> 145 | L18: =INDEX(WS_Top200_Existing_Power!B:B, MATCH('Site detail lookup'!C18, WS_Top200_Existing_Power!A:A, 0)) -> 200 | M18: =INDEX('Top 200 COs'!W:W, MATCH('Site detail lookup'!$C18, 'Top 200 COs'!$C:$C, 0)) -> 35563 | O18: =INDEX(WS_Top200_Transm_Dist_2!G:G, MATCH('Site detail lookup'!$C18, WS_Top200_Transm_Dist_2!$B:$B, 0))/5280 -> 0.37575758 | P18: =INDEX(WS_Top200_Transm_Dist_2!O:O, MATCH('Site detail lookup'!$C18, WS_Top200_Transm_Dist_2!$B:$B, 0)) -> 69 | Q18: =INDEX(WS_Top200_Transm_Dist_2!I:I, MATCH('Site detail lookup'!$C18, WS_Top200_Transm_Dist_2!$B:$B, 0)) -> UNKNOWN112976 | R18: =INDEX(WS_Top200_Transm_Dist_2!J:J, MATCH('Site detail lookup'!$C18, WS_Top200_Transm_Dist_2!$B:$B, 0)) -> UNKNOWN112977
B19: 17 | C19: MEDSKYXA | D19: Meads | E19: KY | F19: Boyd | G19: 9200 US Route 60 | H19: 38.4096 | I19: =I24-82.713 -> -166.2412 | J19: [Missing] | K19: =INDEX('Top 200 COs'!X:X, MATCH('Site detail lookup'!$C19, 'Top 200 COs'!$C:$C, 0)) -> 76 | L19: =INDEX(WS_Top200_Existing_Power!B:B, MATCH('Site detail lookup'!C19, WS_Top200_Existing_Power!A:A, 0)) -> 200 | M19: =INDEX('Top 200 COs'!W:W, MATCH('Site detail lookup'!$C19, 'Top 200 COs'!$C:$C, 0)) -> 12209 | N19: -82.7129 | O19: =INDEX(WS_Top200_Transm_Dist_2!G:G, MATCH('Site detail lookup'!$C19, WS_Top200_Transm_Dist_2!$B:$B, 0))/5280 -> 0.5625 | P19: =INDEX(WS_Top200_Transm_Dist_2!O:O, MATCH('Site detail lookup'!$C19, WS_Top200_Transm_Dist_2!$B:$B, 0)) -> 69 | Q19: =INDEX(WS_Top200_Transm_Dist_2!I:I, MATCH('Site detail lookup'!$C19, WS_Top200_Transm_Dist_2!$B:$B, 0)) -> BELLEFONTE | R19: =INDEX(WS_Top200_Transm_Dist_2!J:J, MATCH('Site detail lookup'!$C19, WS_Top200_Transm_Dist_2!$B:$B, 0)) -> PRINCESS
B20: 18 | C20: BLVIGABW | D20: Blairsville | E20: GA | F20: Union | G20: 40 River Road Connector | H20: 34.864 | I20: -83.9848 | J20: =INDEX(WS_Sites_Parcel_Sizes_FINAL!$I:$I, MATCH('Site detail lookup'!$C20, WS_Sites_Parcel_Sizes_FINAL!$A:$A, 0)) -> 4.2884 | K20: =INDEX('Top 200 COs'!X:X, MATCH('Site detail lookup'!$C20, 'Top 200 COs'!$C:$C, 0)) -> 2 | L20: =INDEX(WS_Top200_Existing_Power!B:B, MATCH('Site detail lookup'!C20, WS_Top200_Existing_Power!A:A, 0)) -> 0 | M20: =INDEX('Top 200 COs'!W:W, MATCH('Site detail lookup'!$C20, 'Top 200 COs'!$C:$C, 0)) -> 5000 | N20: parcel id: 071A-004 (071A 004) | O20: =INDEX(WS_Top200_Transm_Dist_2!G:G, MATCH('Site detail lookup'!$C20, WS_Top200_Transm_Dist_2!$B:$B, 0))/5280 -> 1.1931818 | P20: =INDEX(WS_Top200_Transm_Dist_2!O:O, MATCH('Site detail lookup'!$C20, WS_Top200_Transm_Dist_2!$B:$B, 0)) -> 161 | Q20: =INDEX(WS_Top200_Transm_Dist_2!I:I, MATCH('Site detail lookup'!$C20, WS_Top200_Transm_Dist_2!$B:$B, 0)) -> YOUNGCANE | R20: =INDEX(WS_Top200_Transm_Dist_2!J:J, MATCH('Site detail lookup'!$C20, WS_Top200_Transm_Dist_2!$B:$B, 0)) -> BLAIRSVILLE
B21: 19 | C21: CNTNGAXA | D21: Canton | E21: GA | F21: Cherokee | G21: 190 South Church Street | H21: 34.2361 | I21: -84.4907 | J21: =INDEX(WS_Sites_Parcel_Sizes_FINAL!$I:$I, MATCH('Site detail lookup'!$C21, WS_Sites_Parcel_Sizes_FINAL!$A:$A, 0)) -> 0.1743 | K21: =INDEX('Top 200 COs'!X:X, MATCH('Site detail lookup'!$C21, 'Top 200 COs'!$C:$C, 0)) -> 81 | L21: =INDEX(WS_Top200_Existing_Power!B:B, MATCH('Site detail lookup'!C21, WS_Top200_Existing_Power!A:A, 0)) -> 750 | M21: =INDEX('Top 200 COs'!W:W, MATCH('Site detail lookup'!$C21, 'Top 200 COs'!$C:$C, 0)) -> 7075 | N21: seeing parcel size as 1 | O21: =INDEX(WS_Top200_Transm_Dist_2!G:G, MATCH('Site detail lookup'!$C21, WS_Top200_Transm_Dist_2!$B:$B, 0))/5280 -> 0.31893939 | P21: =INDEX(WS_Top200_Transm_Dist_2!O:O, MATCH('Site detail lookup'!$C21, WS_Top200_Transm_Dist_2!$B:$B, 0)) -> 115 | Q21: =INDEX(WS_Top200_Transm_Dist_2!I:I, MATCH('Site detail lookup'!$C21, WS_Top200_Transm_Dist_2!$B:$B, 0)) -> UNKNOWN111132 | R21: =INDEX(WS_Top200_Transm_Dist_2!J:J, MATCH('Site detail lookup'!$C21, WS_Top200_Transm_Dist_2!$B:$B, 0)) -> UNKNOWN172553
B22: 20 | C22: CHWOGAXA | D22: Chatsworth | E22: GA | F22: Murray | G22: 220 North 2nd Avenue | H22: 34.7683 | I22: -84.7682 | J22: [Missing] | K22: =INDEX('Top 200 COs'!X:X, MATCH('Site detail lookup'!$C22, 'Top 200 COs'!$C:$C, 0)) -> 40 | L22: =INDEX(WS_Top200_Existing_Power!B:B, MATCH('Site detail lookup'!C22, WS_Top200_Existing_Power!A:A, 0)) -> 200 | M22: =INDEX('Top 200 COs'!W:W, MATCH('Site detail lookup'!$C22, 'Top 200 COs'!$C:$C, 0)) -> 6372 | N22: parcel id: 0067A-073 (0067A 073) | O22: =INDEX(WS_Top200_Transm_Dist_2!G:G, MATCH('Site detail lookup'!$C22, WS_Top200_Transm_Dist_2!$B:$B, 0))/5280 -> 0.78409091 | P22: =INDEX(WS_Top200_Transm_Dist_2!O:O, MATCH('Site detail lookup'!$C22, WS_Top200_Transm_Dist_2!$B:$B, 0)) -> 115 | Q22: =INDEX(WS_Top200_Transm_Dist_2!I:I, MATCH('Site detail lookup'!$C22, WS_Top200_Transm_Dist_2!$B:$B, 0)) -> UNKNOWN109911 | R22: =INDEX(WS_Top200_Transm_Dist_2!J:J, MATCH('Site detail lookup'!$C22, WS_Top200_Transm_Dist_2!$B:$B, 0)) -> TAP176873
B23: 21 | C23: CLEVGAXA | D23: Cleveland | E23: GA | F23: White | G23: 158 West Kytle Street | H23: 34.597 | I23: -83.7661 | J23: [Missing] | K23: =INDEX('Top 200 COs'!X:X, MATCH('Site detail lookup'!$C23, 'Top 200 COs'!$C:$C, 0)) -> 124 | L23: =INDEX(WS_Top200_Existing_Power!B:B, MATCH('Site detail lookup'!C23, WS_Top200_Existing_Power!A:A, 0)) -> 250 | M23: =INDEX('Top 200 COs'!W:W, MATCH('Site detail lookup'!$C23, 'Top 200 COs'!$C:$C, 0)) -> 3688 | O23: =INDEX(WS_Top200_Transm_Dist_2!G:G, MATCH('Site detail lookup'!$C23, WS_Top200_Transm_Dist_2!$B:$B, 0))/5280 -> 0.44848485 | P23: =INDEX(WS_Top200_Transm_Dist_2!O:O, MATCH('Site detail lookup'!$C23, WS_Top200_Transm_Dist_2!$B:$B, 0)) -> -999999 | Q23: =INDEX(WS_Top200_Transm_Dist_2!I:I, MATCH('Site detail lookup'!$C23, WS_Top200_Transm_Dist_2!$B:$B, 0)) -> UNKNOWN110446 | R23: =INDEX(WS_Top200_Transm_Dist_2!J:J, MATCH('Site detail lookup'!$C23, WS_Top200_Transm_Dist_2!$B:$B, 0)) -> UNKNOWN110447
B24: 22 | C24: CRNLGAXA | D24: Cornelia | E24: GA | F24: Habersham | G24: 350 North Main Street | H24: 34.5145 | I24: -83.5282 | J24: =INDEX(WS_Sites_Parcel_Sizes_FINAL!$I:$I, MATCH('Site detail lookup'!$C24, WS_Sites_Parcel_Sizes_FINAL!$A:$A, 0)) -> 1.1876 | K24: =INDEX('Top 200 COs'!X:X, MATCH('Site detail lookup'!$C24, 'Top 200 COs'!$C:$C, 0)) -> 77 | L24: =INDEX(WS_Top200_Existing_Power!B:B, MATCH('Site detail lookup'!C24, WS_Top200_Existing_Power!A:A, 0)) -> 200 | M24: =INDEX('Top 200 COs'!W:W, MATCH('Site detail lookup'!$C24, 'Top 200 COs'!$C:$C, 0)) -> 9500 | N24: parcel id: 087D120 (087D120)?? | O24: =INDEX(WS_Top200_Transm_Dist_2!G:G, MATCH('Site detail lookup'!$C24, WS_Top200_Transm_Dist_2!$B:$B, 0))/5280 -> 0.89375 | P24: =INDEX(WS_Top200_Transm_Dist_2!O:O, MATCH('Site detail lookup'!$C24, WS_Top200_Transm_Dist_2!$B:$B, 0)) -> 115 | Q24: =INDEX(WS_Top200_Transm_Dist_2!I:I, MATCH('Site detail lookup'!$C24, WS_Top200_Transm_Dist_2!$B:$B, 0)) -> UNKNOWN110332 | R24: =INDEX(WS_Top200_Transm_Dist_2!J:J, MATCH('Site detail lookup'!$C24, WS_Top200_Transm_Dist_2!$B:$B, 0)) -> TAP153139
B25: 23 | C25: CRNLGA01 | D25: Cornelia | E25: GA | F25: Habersham | G25: 2000 Communications Boulevard (1155 Communications Bv, Baldwin, GA, 30511) | H25: 34.4972 | I25: -83.55 | J25: =INDEX(WS_Sites_Parcel_Sizes_FINAL!$I:$I, MATCH('Site detail lookup'!$C25, WS_Sites_Parcel_Sizes_FINAL!$A:$A, 0)) -> 26.4027 | K25: =INDEX('Top 200 COs'!X:X, MATCH('Site detail lookup'!$C25, 'Top 200 COs'!$C:$C, 0)) -> 11 | L25: =INDEX(WS_Top200_Existing_Power!B:B, MATCH('Site detail lookup'!C25, WS_Top200_Existing_Power!A:A, 0)) -> 450 | M25: =INDEX('Top 200 COs'!W:W, MATCH('Site detail lookup'!$C25, 'Top 200 COs'!$C:$C, 0)) -> 55823 | N25: seeing parcel size as 27.25 | O25: =INDEX(WS_Top200_Transm_Dist_2!G:G, MATCH('Site detail lookup'!$C25, WS_Top200_Transm_Dist_2!$B:$B, 0))/5280 -> 0.10492424 | P25: =INDEX(WS_Top200_Transm_Dist_2!O:O, MATCH('Site detail lookup'!$C25, WS_Top200_Transm_Dist_2!$B:$B, 0)) -> 115 | Q25: =INDEX(WS_Top200_Transm_Dist_2!I:I, MATCH('Site detail lookup'!$C25, WS_Top200_Transm_Dist_2!$B:$B, 0)) -> UNKNOWN110332 | R25: =INDEX(WS_Top200_Transm_Dist_2!J:J, MATCH('Site detail lookup'!$C25, WS_Top200_Transm_Dist_2!$B:$B, 0)) -> TAP153139
B26: 24 | C26: DHLNGAXA | D26: Dahlonega | E26: GA | F26: Lumpkin | G26: 200 Boyd Circle | H26: 34.5354 | I26: -83.9825 | J26: =INDEX(WS_Sites_Parcel_Sizes_FINAL!$I:$I, MATCH('Site detail lookup'!$C26, WS_Sites_Parcel_Sizes_FINAL!$A:$A, 0)) -> 1.4647 | K26: =INDEX('Top 200 COs'!X:X, MATCH('Site detail lookup'!$C26, 'Top 200 COs'!$C:$C, 0)) -> 50 | L26: =INDEX(WS_Top200_Existing_Power!B:B, MATCH('Site detail lookup'!C26, WS_Top200_Existing_Power!A:A, 0)) -> 150 | M26: =INDEX('Top 200 COs'!W:W, MATCH('Site detail lookup'!$C26, 'Top 200 COs'!$C:$C, 0)) -> 5000 | N26: cant find this | O26: =INDEX(WS_Top200_Transm_Dist_2!G:G, MATCH('Site detail lookup'!$C26, WS_Top200_Transm_Dist_2!$B:$B, 0))/5280 -> 0.46420455 | P26: =INDEX(WS_Top200_Transm_Dist_2!O:O, MATCH('Site detail lookup'!$C26, WS_Top200_Transm_Dist_2!$B:$B, 0)) -> -999999 | Q26: =INDEX(WS_Top200_Transm_Dist_2!I:I, MATCH('Site detail lookup'!$C26, WS_Top200_Transm_Dist_2!$B:$B, 0)) -> UNKNOWN110442 | R26: =INDEX(WS_Top200_Transm_Dist_2!J:J, MATCH('Site detail lookup'!$C26, WS_Top200_Transm_Dist_2!$B:$B, 0)) -> TAP155238
B27: 25 | C27: DLTNGAXD | D27: Dalton | E27: GA | F27: Whitfield | G27: 350 Cross Plains Blvd | H27: 34.6751 | I27: -84.9664 | J27: =INDEX(WS_Sites_Parcel_Sizes_FINAL!$I:$I, MATCH('Site detail lookup'!$C27, WS_Sites_Parcel_Sizes_FINAL!$A:$A, 0)) -> 2.388 | K27: =INDEX('Top 200 COs'!X:X, MATCH('Site detail lookup'!$C27, 'Top 200 COs'!$C:$C, 0)) -> 18 | L27: =INDEX(WS_Top200_Existing_Power!B:B, MATCH('Site detail lookup'!C27, WS_Top200_Existing_Power!A:A, 0)) -> 250 | M27: =INDEX('Top 200 COs'!W:W, MATCH('Site detail lookup'!$C27, 'Top 200 COs'!$C:$C, 0)) -> 7717 | N27: seeing parcel size as 5.01 | O27: =INDEX(WS_Top200_Transm_Dist_2!G:G, MATCH('Site detail lookup'!$C27, WS_Top200_Transm_Dist_2!$B:$B, 0))/5280 -> 0.13219697 | P27: =INDEX(WS_Top200_Transm_Dist_2!O:O, MATCH('Site detail lookup'!$C27, WS_Top200_Transm_Dist_2!$B:$B, 0)) -> 115 | Q27: =INDEX(WS_Top200_Transm_Dist_2!I:I, MATCH('Site detail lookup'!$C27, WS_Top200_Transm_Dist_2!$B:$B, 0)) -> TAP145943 | R27: =INDEX(WS_Top200_Transm_Dist_2!J:J, MATCH('Site detail lookup'!$C27, WS_Top200_Transm_Dist_2!$B:$B, 0)) -> TAP173382
B28: 26 | C28: LFYTGAXA | D28: LaFayette | E28: GA | F28: Walker | G28: 105 Cherokee Street | H28: 34.7067 | I28: -85.2827 | J28: [Missing] | K28: =INDEX('Top 200 COs'!X:X, MATCH('Site detail lookup'!$C28, 'Top 200 COs'!$C:$C, 0)) -> 37 | L28: =INDEX(WS_Top200_Existing_Power!B:B, MATCH('Site detail lookup'!C28, WS_Top200_Existing_Power!A:A, 0)) -> 125 | M28: =INDEX('Top 200 COs'!W:W, MATCH('Site detail lookup'!$C28, 'Top 200 COs'!$C:$C, 0)) -> 8000 | O28: =INDEX(WS_Top200_Transm_Dist_2!G:G, MATCH('Site detail lookup'!$C28, WS_Top200_Transm_Dist_2!$B:$B, 0))/5280 -> 0.59280303 | P28: =INDEX(WS_Top200_Transm_Dist_2!O:O, MATCH('Site detail lookup'!$C28, WS_Top200_Transm_Dist_2!$B:$B, 0)) -> 115 | Q28: =INDEX(WS_Top200_Transm_Dist_2!I:I, MATCH('Site detail lookup'!$C28, WS_Top200_Transm_Dist_2!$B:$B, 0)) -> UNKNOWN109795 | R28: =INDEX(WS_Top200_Transm_Dist_2!J:J, MATCH('Site detail lookup'!$C28, WS_Top200_Transm_Dist_2!$B:$B, 0)) -> ROCK SPRING
B29: 27 | C29: MONRGAXB | D29: Monroe | E29: GA | F29: Walton | G29: 3375 GA-11 | H29: 33.8904 | I29: -83.7199 | J29: [Missing] | K29: =INDEX('Top 200 COs'!X:X, MATCH('Site detail lookup'!$C29, 'Top 200 COs'!$C:$C, 0)) -> 3 | L29: =INDEX(WS_Top200_Existing_Power!B:B, MATCH('Site detail lookup'!C29, WS_Top200_Existing_Power!A:A, 0)) -> 0 | M29: =INDEX('Top 200 COs'!W:W, MATCH('Site detail lookup'!$C29, 'Top 200 COs'!$C:$C, 0)) -> 11041 | N29: cant find this | O29: =INDEX(WS_Top200_Transm_Dist_2!G:G, MATCH('Site detail lookup'!$C29, WS_Top200_Transm_Dist_2!$B:$B, 0))/5280 -> 0.25113636 | P29: =INDEX(WS_Top200_Transm_Dist_2!O:O, MATCH('Site detail lookup'!$C29, WS_Top200_Transm_Dist_2!$B:$B, 0)) -> 230 | Q29: =INDEX(WS_Top200_Transm_Dist_2!I:I, MATCH('Site detail lookup'!$C29, WS_Top200_Transm_Dist_2!$B:$B, 0)) -> DOYLE ENERGY FACILITY | R29: =INDEX(WS_Top200_Transm_Dist_2!J:J, MATCH('Site detail lookup'!$C29, WS_Top200_Transm_Dist_2!$B:$B, 0)) -> UNKNOWN133851
B30: 28 | C30: SUVLGAXA | D30: Summerville | E30: GA | F30: Chattooga | G30: 66 West Washington Street | H30: 34.4815 | I30: -85.3487 | J30: =INDEX(WS_Sites_Parcel_Sizes_FINAL!$I:$I, MATCH('Site detail lookup'!$C30, WS_Sites_Parcel_Sizes_FINAL!$A:$A, 0)) -> 0.5211 | K30: =INDEX('Top 200 COs'!X:X, MATCH('Site detail lookup'!$C30, 'Top 200 COs'!$C:$C, 0)) -> 33 | L30: =INDEX(WS_Top200_Existing_Power!B:B, MATCH('Site detail lookup'!C30, WS_Top200_Existing_Power!A:A, 0)) -> 100 | M30: =INDEX('Top 200 COs'!W:W, MATCH('Site detail lookup'!$C30, 'Top 200 COs'!$C:$C, 0)) -> 6846 | N30: parcel id: 00S27-00000-009 | O30: =INDEX(WS_Top200_Transm_Dist_2!G:G, MATCH('Site detail lookup'!$C30, WS_Top200_Transm_Dist_2!$B:$B, 0))/5280 -> 0.79772727 | P30: =INDEX(WS_Top200_Transm_Dist_2!O:O, MATCH('Site detail lookup'!$C30, WS_Top200_Transm_Dist_2!$B:$B, 0)) -> -999999 | Q30: =INDEX(WS_Top200_Transm_Dist_2!I:I, MATCH('Site detail lookup'!$C30, WS_Top200_Transm_Dist_2!$B:$B, 0)) -> UNKNOWN110421 | R30: =INDEX(WS_Top200_Transm_Dist_2!J:J, MATCH('Site detail lookup'!$C30, WS_Top200_Transm_Dist_2!$B:$B, 0)) -> TAP149900
B31: 29 | C31: GRQYNCXA | D31: Granite Quarry (Rockwell?) | E31: NC | F31: Rowan | G31: 8145 Highway 52 | H31: 35.572 | I31: -80.4178 | J31: =INDEX(WS_Sites_Parcel_Sizes_FINAL!$I:$I, MATCH('Site detail lookup'!$C31, WS_Sites_Parcel_Sizes_FINAL!$A:$A, 0)) -> 1.2988 | K31: =INDEX('Top 200 COs'!X:X, MATCH('Site detail lookup'!$C31, 'Top 200 COs'!$C:$C, 0)) -> 30 | L31: =INDEX(WS_Top200_Existing_Power!B:B, MATCH('Site detail lookup'!C31, WS_Top200_Existing_Power!A:A, 0)) -> 150 | M31: =INDEX('Top 200 COs'!W:W, MATCH('Site detail lookup'!$C31, 'Top 200 COs'!$C:$C, 0)) -> 4860 | O31: =INDEX(WS_Top200_Transm_Dist_2!G:G, MATCH('Site detail lookup'!$C31, WS_Top200_Transm_Dist_2!$B:$B, 0))/5280 -> 0.9717803 | P31: =INDEX(WS_Top200_Transm_Dist_2!O:O, MATCH('Site detail lookup'!$C31, WS_Top200_Transm_Dist_2!$B:$B, 0)) -> 230 | Q31: =INDEX(WS_Top200_Transm_Dist_2!I:I, MATCH('Site detail lookup'!$C31, WS_Top200_Transm_Dist_2!$B:$B, 0)) -> UNKNOWN114573 | R31: =INDEX(WS_Top200_Transm_Dist_2!J:J, MATCH('Site detail lookup'!$C31, WS_Top200_Transm_Dist_2!$B:$B, 0)) -> UNKNOWN114701
B32: 30 | C32: NRWDNCXA | D32: Norwood | E32: NC | F32: Stanly | G32: 238 North Main Street | H32: 35.2267 | I32: -80.1227 | J32: =INDEX(WS_Sites_Parcel_Sizes_FINAL!$I:$I, MATCH('Site detail lookup'!$C32, WS_Sites_Parcel_Sizes_FINAL!$A:$A, 0)) -> 0.2279 | K32: =INDEX('Top 200 COs'!X:X, MATCH('Site detail lookup'!$C32, 'Top 200 COs'!$C:$C, 0)) -> 15 | L32: =INDEX(WS_Top200_Existing_Power!B:B, MATCH('Site detail lookup'!C32, WS_Top200_Existing_Power!A:A, 0)) -> 75 | M32: =INDEX('Top 200 COs'!W:W, MATCH('Site detail lookup'!$C32, 'Top 200 COs'!$C:$C, 0)) -> 3400 | O32: =INDEX(WS_Top200_Transm_Dist_2!G:G, MATCH('Site detail lookup'!$C32, WS_Top200_Transm_Dist_2!$B:$B, 0))/5280 -> 0.74488636 | P32: =INDEX(WS_Top200_Transm_Dist_2!O:O, MATCH('Site detail lookup'!$C32, WS_Top200_Transm_Dist_2!$B:$B, 0)) -> 100 | Q32: =INDEX(WS_Top200_Transm_Dist_2!I:I, MATCH('Site detail lookup'!$C32, WS_Top200_Transm_Dist_2!$B:$B, 0)) -> UNKNOWN114221 | R32: =INDEX(WS_Top200_Transm_Dist_2!J:J, MATCH('Site detail lookup'!$C32, WS_Top200_Transm_Dist_2!$B:$B, 0)) -> TAP150528
B33: 31 | C33: PWPNOHXA | D33: Powhatan Point | E33: OH | F33: Belmont | G33: 101 Ben Avenue | H33: 39.866 | I33: -80.799 | J33: =INDEX(WS_Sites_Parcel_Sizes_FINAL!$I:$I, MATCH('Site detail lookup'!$C33, WS_Sites_Parcel_Sizes_FINAL!$A:$A, 0)) -> 0.0747 | K33: =INDEX('Top 200 COs'!X:X, MATCH('Site detail lookup'!$C33, 'Top 200 COs'!$C:$C, 0)) -> 18 | L33: =INDEX(WS_Top200_Existing_Power!B:B, MATCH('Site detail lookup'!C33, WS_Top200_Existing_Power!A:A, 0)) -> 60 | M33: =INDEX('Top 200 COs'!W:W, MATCH('Site detail lookup'!$C33, 'Top 200 COs'!$C:$C, 0)) -> 3534 | N33: parcel id: 53-90011-000. seeing parcel size as 0.2 | O33: =INDEX(WS_Top200_Transm_Dist_2!G:G, MATCH('Site detail lookup'!$C33, WS_Top200_Transm_Dist_2!$B:$B, 0))/5280 -> 0.66780303 | P33: =INDEX(WS_Top200_Transm_Dist_2!O:O, MATCH('Site detail lookup'!$C33, WS_Top200_Transm_Dist_2!$B:$B, 0)) -> 69 | Q33: =INDEX(WS_Top200_Transm_Dist_2!I:I, MATCH('Site detail lookup'!$C33, WS_Top200_Transm_Dist_2!$B:$B, 0)) -> KAMMER (138KV) | R33: =INDEX(WS_Top200_Transm_Dist_2!J:J, MATCH('Site detail lookup'!$C33, WS_Top200_Transm_Dist_2!$B:$B, 0)) -> GEORGE WASHINGTON
B34: 32 | C34: GRVIOHXA | D34: Granville | E34: OH | F34: Licking | G34: 131 East Broadway | H34: 40.0676 | I34: -82.519 | J34: =INDEX(WS_Sites_Parcel_Sizes_FINAL!$I:$I, MATCH('Site detail lookup'!$C34, WS_Sites_Parcel_Sizes_FINAL!$A:$A, 0)) -> 0.1775 | K34: =INDEX('Top 200 COs'!X:X, MATCH('Site detail lookup'!$C34, 'Top 200 COs'!$C:$C, 0)) -> 24 | L34: =INDEX(WS_Top200_Existing_Power!B:B, MATCH('Site detail lookup'!C34, WS_Top200_Existing_Power!A:A, 0)) -> 100 | M34: =INDEX('Top 200 COs'!W:W, MATCH('Site detail lookup'!$C34, 'Top 200 COs'!$C:$C, 0)) -> 6307 | O34: =INDEX(WS_Top200_Transm_Dist_2!G:G, MATCH('Site detail lookup'!$C34, WS_Top200_Transm_Dist_2!$B:$B, 0))/5280 -> 0.52897727 | P34: =INDEX(WS_Top200_Transm_Dist_2!O:O, MATCH('Site detail lookup'!$C34, WS_Top200_Transm_Dist_2!$B:$B, 0)) -> 69 | Q34: =INDEX(WS_Top200_Transm_Dist_2!I:I, MATCH('Site detail lookup'!$C34, WS_Top200_Transm_Dist_2!$B:$B, 0)) -> UNKNOWN112973 | R34: =INDEX(WS_Top200_Transm_Dist_2!J:J, MATCH('Site detail lookup'!$C34, WS_Top200_Transm_Dist_2!$B:$B, 0)) -> TAP171386
B35: 33 | C35: HETHOHXA | D35: Heath (Newark?) | E35: OH | F35: Licking | G35: 1046 Harris Avenue | H35: 40.0413 | I35: -82.4417 | J35: =INDEX(WS_Sites_Parcel_Sizes_FINAL!$I:$I, MATCH('Site detail lookup'!$C35, WS_Sites_Parcel_Sizes_FINAL!$A:$A, 0)) -> 0.1458 | K35: =INDEX('Top 200 COs'!X:X, MATCH('Site detail lookup'!$C35, 'Top 200 COs'!$C:$C, 0)) -> 27 | L35: =INDEX(WS_Top200_Existing_Power!B:B, MATCH('Site detail lookup'!C35, WS_Top200_Existing_Power!A:A, 0)) -> 100 | M35: =INDEX('Top 200 COs'!W:W, MATCH('Site detail lookup'!$C35, 'Top 200 COs'!$C:$C, 0)) -> 3614 | O35: =INDEX(WS_Top200_Transm_Dist_2!G:G, MATCH('Site detail lookup'!$C35, WS_Top200_Transm_Dist_2!$B:$B, 0))/5280 -> 0.47462121 | P35: =INDEX(WS_Top200_Transm_Dist_2!O:O, MATCH('Site detail lookup'!$C35, WS_Top200_Transm_Dist_2!$B:$B, 0)) -> 69 | Q35: =INDEX(WS_Top200_Transm_Dist_2!I:I, MATCH('Site detail lookup'!$C35, WS_Top200_Transm_Dist_2!$B:$B, 0)) -> UNKNOWN113882 | R35: =INDEX(WS_Top200_Transm_Dist_2!J:J, MATCH('Site detail lookup'!$C35, WS_Top200_Transm_Dist_2!$B:$B, 0)) -> UNKNOWN158903
B36: 34 | C36: NWRKOHXC | D36: Newark | E36: OH | F36: Licking | G36: 214 Neal Avenue (685 W Church St?) | H36: 40.0575 | I36: -82.4272 | J36: =INDEX(WS_Sites_Parcel_Sizes_FINAL!$I:$I, MATCH('Site detail lookup'!$C36, WS_Sites_Parcel_Sizes_FINAL!$A:$A, 0)) -> 0.1312 | K36: =INDEX('Top 200 COs'!X:X, MATCH('Site detail lookup'!$C36, 'Top 200 COs'!$C:$C, 0)) -> 21 | L36: =INDEX(WS_Top200_Existing_Power!B:B, MATCH('Site detail lookup'!C36, WS_Top200_Existing_Power!A:A, 0)) -> 100 | M36: =INDEX('Top 200 COs'!W:W, MATCH('Site detail lookup'!$C36, 'Top 200 COs'!$C:$C, 0)) -> 8571 | N36: seeing parcel size as 0.39 | O36: =INDEX(WS_Top200_Transm_Dist_2!G:G, MATCH('Site detail lookup'!$C36, WS_Top200_Transm_Dist_2!$B:$B, 0))/5280 -> 0.98162879 | P36: =INDEX(WS_Top200_Transm_Dist_2!O:O, MATCH('Site detail lookup'!$C36, WS_Top200_Transm_Dist_2!$B:$B, 0)) -> 69 | Q36: =INDEX(WS_Top200_Transm_Dist_2!I:I, MATCH('Site detail lookup'!$C36, WS_Top200_Transm_Dist_2!$B:$B, 0)) -> UNKNOWN112977 | R36: =INDEX(WS_Top200_Transm_Dist_2!J:J, MATCH('Site detail lookup'!$C36, WS_Top200_Transm_Dist_2!$B:$B, 0)) -> UNKNOWN171395
B37: 35 | C37: NWRKOHXB | D37: Newark | E37: OH | F37: Licking | G37: 320 Deo Drive | H37: 40.0869 | I37: -82.4271 | J37: =INDEX(WS_Sites_Parcel_Sizes_FINAL!$I:$I, MATCH('Site detail lookup'!$C37, WS_Sites_Parcel_Sizes_FINAL!$A:$A, 0)) -> 0.3724 | K37: =INDEX('Top 200 COs'!X:X, MATCH('Site detail lookup'!$C37, 'Top 200 COs'!$C:$C, 0)) -> 25 | L37: =INDEX(WS_Top200_Existing_Power!B:B, MATCH('Site detail lookup'!C37, WS_Top200_Existing_Power!A:A, 0)) -> 125 | M37: =INDEX('Top 200 COs'!W:W, MATCH('Site detail lookup'!$C37, 'Top 200 COs'!$C:$C, 0)) -> 3870 | N37: seeing parcel size as 0.41 | O37: =INDEX(WS_Top200_Transm_Dist_2!G:G, MATCH('Site detail lookup'!$C37, WS_Top200_Transm_Dist_2!$B:$B, 0))/5280 -> 0.40265152 | P37: =INDEX(WS_Top200_Transm_Dist_2!O:O, MATCH('Site detail lookup'!$C37, WS_Top200_Transm_Dist_2!$B:$B, 0)) -> 138 | Q37: =INDEX(WS_Top200_Transm_Dist_2!I:I, MATCH('Site detail lookup'!$C37, WS_Top200_Transm_Dist_2!$B:$B, 0)) -> UNKNOWN113882 | R37: =INDEX(WS_Top200_Transm_Dist_2!J:J, MATCH('Site detail lookup'!$C37, WS_Top200_Transm_Dist_2!$B:$B, 0)) -> NORTH NEWARK SUBSTATION
B38: 36 | C38: ASLDKYXA | D38: Ashland | E38: KY | F38: Boyd | G38: 619 15th Street | H38: 38.4758 | I38: -82.6439 | J38: [Missing] | K38: =INDEX('Top 200 COs'!X:X, MATCH('Site detail lookup'!$C38, 'Top 200 COs'!$C:$C, 0)) -> 232 | L38: =INDEX(WS_Top200_Existing_Power!B:B, MATCH('Site detail lookup'!C38, WS_Top200_Existing_Power!A:A, 0)) -> 600 | M38: =INDEX('Top 200 COs'!W:W, MATCH('Site detail lookup'!$C38, 'Top 200 COs'!$C:$C, 0)) -> 34184 | O38: =INDEX(WS_Top200_Transm_Dist_2!G:G, MATCH('Site detail lookup'!$C38, WS_Top200_Transm_Dist_2!$B:$B, 0))/5280 -> 0.43068182 | P38: =INDEX(WS_Top200_Transm_Dist_2!O:O, MATCH('Site detail lookup'!$C38, WS_Top200_Transm_Dist_2!$B:$B, 0)) -> 69 | Q38: =INDEX(WS_Top200_Transm_Dist_2!I:I, MATCH('Site detail lookup'!$C38, WS_Top200_Transm_Dist_2!$B:$B, 0)) -> UNKNOWN121253 | R38: =INDEX(WS_Top200_Transm_Dist_2!J:J, MATCH('Site detail lookup'!$C38, WS_Top200_Transm_Dist_2!$B:$B, 0)) -> BELLEFONTE
B39: 37 | C39: GNUPKYXA | D39: Greenup | E39: KY | F39: Greenup | G39: 304 Laurel St. (Laurel St 310 1/2, Greenup, KY, 41144?) | H39: 38.5734 | I39: -82.8396 | J39: [Missing] | K39: =INDEX('Top 200 COs'!X:X, MATCH('Site detail lookup'!$C39, 'Top 200 COs'!$C:$C, 0)) -> 52 | L39: =INDEX(WS_Top200_Existing_Power!B:B, MATCH('Site detail lookup'!C39, WS_Top200_Existing_Power!A:A, 0)) -> 100 | M39: =INDEX('Top 200 COs'!W:W, MATCH('Site detail lookup'!$C39, 'Top 200 COs'!$C:$C, 0)) -> 4100 | O39: =INDEX(WS_Top200_Transm_Dist_2!G:G, MATCH('Site detail lookup'!$C39, WS_Top200_Transm_Dist_2!$B:$B, 0))/5280 -> 1.7003788 | P39: =INDEX(WS_Top200_Transm_Dist_2!O:O, MATCH('Site detail lookup'!$C39, WS_Top200_Transm_Dist_2!$B:$B, 0)) -> 69 | Q39: =INDEX(WS_Top200_Transm_Dist_2!I:I, MATCH('Site detail lookup'!$C39, WS_Top200_Transm_Dist_2!$B:$B, 0)) -> UNKNOWN137848 | R39: =INDEX(WS_Top200_Transm_Dist_2!J:J, MATCH('Site detail lookup'!$C39, WS_Top200_Transm_Dist_2!$B:$B, 0)) -> NOT AVAILABLE
B40: 38 | C40: CLVLGAXA | D40: Clarkesville | E40: GA | F40: Habersham | G40: 390 Jefferson Street | H40: 34.6148 | I40: -83.5244 | J40: =INDEX(WS_Sites_Parcel_Sizes_FINAL!$I:$I, MATCH('Site detail lookup'!$C40, WS_Sites_Parcel_Sizes_FINAL!$A:$A, 0)) -> 0.4634 | K40: =INDEX('Top 200 COs'!X:X, MATCH('Site detail lookup'!$C40, 'Top 200 COs'!$C:$C, 0)) -> 25 | L40: =INDEX(WS_Top200_Existing_Power!B:B, MATCH('Site detail lookup'!C40, WS_Top200_Existing_Power!A:A, 0)) -> 150 | M40: =INDEX('Top 200 COs'!W:W, MATCH('Site detail lookup'!$C40, 'Top 200 COs'!$C:$C, 0)) -> 7500 | N40: parcel id: 102-098? Seeing parcel size as 0.57 | O40: =INDEX(WS_Top200_Transm_Dist_2!G:G, MATCH('Site detail lookup'!$C40, WS_Top200_Transm_Dist_2!$B:$B, 0))/5280 -> 0.30587121 | P40: =INDEX(WS_Top200_Transm_Dist_2!O:O, MATCH('Site detail lookup'!$C40, WS_Top200_Transm_Dist_2!$B:$B, 0)) -> -999999 | Q40: =INDEX(WS_Top200_Transm_Dist_2!I:I, MATCH('Site detail lookup'!$C40, WS_Top200_Transm_Dist_2!$B:$B, 0)) -> TAP173810 | R40: =INDEX(WS_Top200_Transm_Dist_2!J:J, MATCH('Site detail lookup'!$C40, WS_Top200_Transm_Dist_2!$B:$B, 0)) -> UNKNOWN173811
B41: 39 | C41: CMRCGAXA | D41: Commerce | E41: GA | F41: Jackson | G41: 45 Georgia Avenue (45 Little Street?) | H41: 34.204 | I41: -83.4595 | J41: =INDEX(WS_Sites_Parcel_Sizes_FINAL!$I:$I, MATCH('Site detail lookup'!$C41, WS_Sites_Parcel_Sizes_FINAL!$A:$A, 0)) -> 0.3236 | K41: =INDEX('Top 200 COs'!X:X, MATCH('Site detail lookup'!$C41, 'Top 200 COs'!$C:$C, 0)) -> 128 | L41: =INDEX(WS_Top200_Existing_Power!B:B, MATCH('Site detail lookup'!C41, WS_Top200_Existing_Power!A:A, 0)) -> 450 | M41: =INDEX('Top 200 COs'!W:W, MATCH('Site detail lookup'!$C41, 'Top 200 COs'!$C:$C, 0)) -> 9417 | N41: seeing parcel size as 0.39 | O41: =INDEX(WS_Top200_Transm_Dist_2!G:G, MATCH('Site detail lookup'!$C41, WS_Top200_Transm_Dist_2!$B:$B, 0))/5280 -> 0.63655303 | P41: =INDEX(WS_Top200_Transm_Dist_2!O:O, MATCH('Site detail lookup'!$C41, WS_Top200_Transm_Dist_2!$B:$B, 0)) -> 115 | Q41: =INDEX(WS_Top200_Transm_Dist_2!I:I, MATCH('Site detail lookup'!$C41, WS_Top200_Transm_Dist_2!$B:$B, 0)) -> UNKNOWN111494 | R41: =INDEX(WS_Top200_Transm_Dist_2!J:J, MATCH('Site detail lookup'!$C41, WS_Top200_Transm_Dist_2!$B:$B, 0)) -> UNKNOWN111501
B42: 40 | C42: HWSSGAXA | D42: Hiawassee | E42: GA | F42: Towns | G42: 228 North Main Street | H42: 34.9517 | I42: -83.7583 | J42: [Missing] | K42: =INDEX('Top 200 COs'!X:X, MATCH('Site detail lookup'!$C42, 'Top 200 COs'!$C:$C, 0)) -> 19 | L42: =INDEX(WS_Top200_Existing_Power!B:B, MATCH('Site detail lookup'!C42, WS_Top200_Existing_Power!A:A, 0)) -> 150 | M42: =INDEX('Top 200 COs'!W:W, MATCH('Site detail lookup'!$C42, 'Top 200 COs'!$C:$C, 0)) -> 3026 | N42: parcel id: H002 076? No parcel size information | O42: =INDEX(WS_Top200_Transm_Dist_2!G:G, MATCH('Site detail lookup'!$C42, WS_Top200_Transm_Dist_2!$B:$B, 0))/5280 -> 0.015909091 | P42: =INDEX(WS_Top200_Transm_Dist_2!O:O, MATCH('Site detail lookup'!$C42, WS_Top200_Transm_Dist_2!$B:$B, 0)) -> 69 | Q42: =INDEX(WS_Top200_Transm_Dist_2!I:I, MATCH('Site detail lookup'!$C42, WS_Top200_Transm_Dist_2!$B:$B, 0)) -> UNKNOWN116503 | R42: =INDEX(WS_Top200_Transm_Dist_2!J:J, MATCH('Site detail lookup'!$C42, WS_Top200_Transm_Dist_2!$B:$B, 0)) -> TAP151237
B43: 41 | C43: JSPRGAXA | D43: Jasper | E43: GA | F43: Pickens | G43: 69 Stegall Drive | H43: 34.4682 | I43: -84.4314 | J43: [Missing] | K43: =INDEX('Top 200 COs'!X:X, MATCH('Site detail lookup'!$C43, 'Top 200 COs'!$C:$C, 0)) -> 22 | L43: =INDEX(WS_Top200_Existing_Power!B:B, MATCH('Site detail lookup'!C43, WS_Top200_Existing_Power!A:A, 0)) -> 125 | M43: =INDEX('Top 200 COs'!W:W, MATCH('Site detail lookup'!$C43, 'Top 200 COs'!$C:$C, 0)) -> 3452 | N43: parcel id: JA07 0U2 102? No parcel size information | O43: =INDEX(WS_Top200_Transm_Dist_2!G:G, MATCH('Site detail lookup'!$C43, WS_Top200_Transm_Dist_2!$B:$B, 0))/5280 -> 0.55378788 | P43: =INDEX(WS_Top200_Transm_Dist_2!O:O, MATCH('Site detail lookup'!$C43, WS_Top200_Transm_Dist_2!$B:$B, 0)) -> -999999 | Q43: =INDEX(WS_Top200_Transm_Dist_2!I:I, MATCH('Site detail lookup'!$C43, WS_Top200_Transm_Dist_2!$B:$B, 0)) -> UNKNOWN169053 | R43: =INDEX(WS_Top200_Transm_Dist_2!J:J, MATCH('Site detail lookup'!$C43, WS_Top200_Transm_Dist_2!$B:$B, 0)) -> TAP169054
B44: 42 | C44: MONRGAXA | D44: Monroe | E44: GA | F44: Walton | G44: 129 East Highland Avenue | H44: 33.7965 | I44: -83.7125 | J44: [Missing] | K44: =INDEX('Top 200 COs'!X:X, MATCH('Site detail lookup'!$C44, 'Top 200 COs'!$C:$C, 0)) -> 36 | L44: =INDEX(WS_Top200_Existing_Power!B:B, MATCH('Site detail lookup'!C44, WS_Top200_Existing_Power!A:A, 0)) -> 125 | M44: =INDEX('Top 200 COs'!W:W, MATCH('Site detail lookup'!$C44, 'Top 200 COs'!$C:$C, 0)) -> 4860 | N44: no parcel id, no parcel size information | O44: =INDEX(WS_Top200_Transm_Dist_2!G:G, MATCH('Site detail lookup'!$C44, WS_Top200_Transm_Dist_2!$B:$B, 0))/5280 -> 0.19261364 | P44: =INDEX(WS_Top200_Transm_Dist_2!O:O, MATCH('Site detail lookup'!$C44, WS_Top200_Transm_Dist_2!$B:$B, 0)) -> 115 | Q44: =INDEX(WS_Top200_Transm_Dist_2!I:I, MATCH('Site detail lookup'!$C44, WS_Top200_Transm_Dist_2!$B:$B, 0)) -> UNKNOWN116149 | R44: =INDEX(WS_Top200_Transm_Dist_2!J:J, MATCH('Site detail lookup'!$C44, WS_Top200_Transm_Dist_2!$B:$B, 0)) -> UNKNOWN116150
B45: 43 | C45: WNDRGAXA | D45: Winder | E45: GA | F45: Barrow | G45: 74 Woodlawn Avenue | H45: 33.9946 | I45: -83.7212 | J45: =INDEX(WS_Sites_Parcel_Sizes_FINAL!$I:$I, MATCH('Site detail lookup'!$C45, WS_Sites_Parcel_Sizes_FINAL!$A:$A, 0)) -> 0.6408 | K45: =INDEX('Top 200 COs'!X:X, MATCH('Site detail lookup'!$C45, 'Top 200 COs'!$C:$C, 0)) -> 119 | L45: =INDEX(WS_Top200_Existing_Power!B:B, MATCH('Site detail lookup'!C45, WS_Top200_Existing_Power!A:A, 0)) -> 350 | M45: =INDEX('Top 200 COs'!W:W, MATCH('Site detail lookup'!$C45, 'Top 200 COs'!$C:$C, 0)) -> 7771 | N45: seeing parcel size as 0.59 | O45: =INDEX(WS_Top200_Transm_Dist_2!G:G, MATCH('Site detail lookup'!$C45, WS_Top200_Transm_Dist_2!$B:$B, 0))/5280 -> 1.3920455 | P45: =INDEX(WS_Top200_Transm_Dist_2!O:O, MATCH('Site detail lookup'!$C45, WS_Top200_Transm_Dist_2!$B:$B, 0)) -> 230 | Q45: =INDEX(WS_Top200_Transm_Dist_2!I:I, MATCH('Site detail lookup'!$C45, WS_Top200_Transm_Dist_2!$B:$B, 0)) -> UNKNOWN111503 | R45: =INDEX(WS_Top200_Transm_Dist_2!J:J, MATCH('Site detail lookup'!$C45, WS_Top200_Transm_Dist_2!$B:$B, 0)) -> WINDER
B46: 44 | C46: PECSTXXB | D46: Pecos | E46: TX | F46: Reeves | G46: 924 West Daggett Street | H46: 31.4044 | I46: -103.503 | J46: [Missing] | K46: =INDEX('Top 200 COs'!X:X, MATCH('Site detail lookup'!$C46, 'Top 200 COs'!$C:$C, 0)) -> 35 | L46: =INDEX(WS_Top200_Existing_Power!B:B, MATCH('Site detail lookup'!C46, WS_Top200_Existing_Power!A:A, 0)) -> 150 | M46: =INDEX('Top 200 COs'!W:W, MATCH('Site detail lookup'!$C46, 'Top 200 COs'!$C:$C, 0)) -> 3520 | N46: parcel id: 0003227? Seeing parcel size as 0.2 | O46: =INDEX(WS_Top200_Transm_Dist_2!G:G, MATCH('Site detail lookup'!$C46, WS_Top200_Transm_Dist_2!$B:$B, 0))/5280 -> 0.23238636 | P46: =INDEX(WS_Top200_Transm_Dist_2!O:O, MATCH('Site detail lookup'!$C46, WS_Top200_Transm_Dist_2!$B:$B, 0)) -> 46 | Q46: =INDEX(WS_Top200_Transm_Dist_2!I:I, MATCH('Site detail lookup'!$C46, WS_Top200_Transm_Dist_2!$B:$B, 0)) -> UNKNOWN300467 | R46: =INDEX(WS_Top200_Transm_Dist_2!J:J, MATCH('Site detail lookup'!$C46, WS_Top200_Transm_Dist_2!$B:$B, 0)) -> NOT AVAILABLE
B47: 45 | C47: KNTNOHXA | D47: Kenton | E47: OH | F47: Hardin | G47: 225 West Columbus Street | H47: 40.6479 | I47: -83.6103 | J47: =INDEX(WS_Sites_Parcel_Sizes_FINAL!$I:$I, MATCH('Site detail lookup'!$C47, WS_Sites_Parcel_Sizes_FINAL!$A:$A, 0)) -> 0.2028 | K47: =INDEX('Top 200 COs'!X:X, MATCH('Site detail lookup'!$C47, 'Top 200 COs'!$C:$C, 0)) -> 30 | L47: =INDEX(WS_Top200_Existing_Power!B:B, MATCH('Site detail lookup'!C47, WS_Top200_Existing_Power!A:A, 0)) -> 125 | M47: =INDEX('Top 200 COs'!W:W, MATCH('Site detail lookup'!$C47, 'Top 200 COs'!$C:$C, 0)) -> 9800 | O47: =INDEX(WS_Top200_Transm_Dist_2!G:G, MATCH('Site detail lookup'!$C47, WS_Top200_Transm_Dist_2!$B:$B, 0))/5280 -> 1.5793561 | P47: =INDEX(WS_Top200_Transm_Dist_2!O:O, MATCH('Site detail lookup'!$C47, WS_Top200_Transm_Dist_2!$B:$B, 0)) -> 138 | Q47: =INDEX(WS_Top200_Transm_Dist_2!I:I, MATCH('Site detail lookup'!$C47, WS_Top200_Transm_Dist_2!$B:$B, 0)) -> UNKNOWN137331 | R47: =INDEX(WS_Top200_Transm_Dist_2!J:J, MATCH('Site detail lookup'!$C47, WS_Top200_Transm_Dist_2!$B:$B, 0)) -> TAP140023

Sheet WS_Sites_Parcel_Sizes_FINAL
A1: clli | B1: address | C1: tier | D1: county | E1: state | F1: lat | G1: lng | H1: status | I1: acres_gis | J1: sqft_gis | K1: m2_gis | L1: acres_stated | M1: acres_stated_field | N1: parcel_id | O1: owner | P1: parcel_address | Q1: source | R1: notes
A2: WNDRGAXA | B2: 74 Woodlawn Avenue | C2: Interesting | D2: Barrow | E2: GA | F2: 33.99464785000001 | G2: -83.721188 | H2: ok | I2: 0.6408 | J2: 27913 | K2: 2593.2 | N2: WN12 293 | P2: 10802 EXECUTIVE CENTER DR | Q2: https://services5.arcgis.com/OVFGXfRTCVcPwl55/arcgis/rest/services/Barrow_Parcels_w_Owner/FeatureServer/0
A3: SUVLGAXA | B3: 66 West Washington Street | C3: Top Site | D3: Chattooga | E3: GA | F3: 34.48152 | G3: -85.34871 | H3: ok | I3: 0.5211 | J3: 22698 | K3: 2108.7 | L3: 0.5198536 | M3: ACRES | N3: S27-009 | P3: COX STREET | Q3: https://services9.arcgis.com/eXIsbyIncFwEzqul/arcgis/rest/services/parcels_zoning/FeatureServer/2
A4: CNTNGAXA | B4: 190 South Church Street | C4: Top Site | D4: Cherokee | E4: GA | F4: 34.23610952999998 | G4: -84.490655 | H4: ok | I4: 0.1743 | J4: 7593 | K4: 705.4 | L4: 1 | M4: Acreage | N4: 14-0166-0003 | O4: CSL GEORGIA SYSTEM LLC | P4: 190 S Church St | Q4: https://services6.arcgis.com/dpaY3zboICQILFY5/arcgis/rest/services/Property_Value_TY2024/FeatureServer/0
A5: CLVLGAXA | B5: 390 Jefferson Street | C5: Interesting | D5: Habersham | E5: GA | F5: 34.61483837000001 | G5: -83.524356 | H5: ok | I5: 0.4634 | J5: 20186 | K5: 1875.4 | L5: 0.46 | M5: CALC_ACRE | N5: 098 | Q5: https://arcgis5.roktech.net/arcgis/rest/services/habersham/habersham_rokmaps/MapServer/8
A6: CRNLGA01 | B6: 2000 Communications Boulevard | C6: Top Site | D6: Habersham | E6: GA | F6: 34.497208 | G6: -83.549978 | H6: ok | I6: 26.4027 | J6: 1150101 | K6: 106848 | L6: 25.27 | M6: CALC_ACRE | N6: 016 | Q6: https://arcgis5.roktech.net/arcgis/rest/services/habersham/habersham_rokmaps/MapServer/8 | R6: Mireye/Regrid reported 26.35 ac.
A7: CRNLGAXA | B7: 350 North Main Street | C7: Top Site | D7: Habersham | E7: GA | F7: 34.514516 | G7: -83.52818 | H7: ok | I7: 1.1876 | J7: 51730 | K7: 4805.9 | L7: 1.18 | M7: CALC_ACRE | N7: 120 | Q7: https://arcgis5.roktech.net/arcgis/rest/services/habersham/habersham_rokmaps/MapServer/8
A8: CMRCGAXA | B8: 45 Georgia Avenue | C8: Interesting | D8: Jackson | E8: GA | F8: 34.20397641999998 | G8: -83.459471 | H8: ok | I8: 0.3236 | J8: 14096 | K8: 1309.6 | L8: 0.39 | M8: TOTALACRES | N8: C14 049 | P8: 10802 EXECUTIVE CENTER DR | Q8: https://services8.arcgis.com/bcbi4lYRFOsss0F5/ArcGIS/rest/services/jackson_baselayers/FeatureServer/9
A9: DHLNGAXA | B9: 200 Boyd Circle | C9: Top Site | D9: Lumpkin | E9: GA | F9: 34.535424 | G9: -83.982514 | H9: ok | I9: 1.4647 | J9: 63803 | K9: 5927.5 | L9: 1.46092 | M9: GIS_ACRES | N9: D10 049 | O9: 24650 | P9: P O BOX 400 | Q9: https://services6.arcgis.com/BAJNi3EgCdtQ1BCG/arcgis/rest/services/Lumpkin_2025Parcels/FeatureServer/0
A10: CHWOGAXA | B10: 220 North 2nd Avenue | C10: Top Site | D10: Murray | E10: GA | F10: 34.76833751000002 | G10: -84.768209 | H10: UNRESOLVED | Q10: https://qpublic.schneidercorp.com/ (search county + address) | R10: qPublic (Schneider) - blocks automated access
A11: JSPRGAXA | B11: 69 Stegall Drive | C11: Interesting | D11: Pickens | E11: GA | F11: 34.468179 | G11: -84.431445 | H11: UNRESOLVED | Q11: https://qpublic.schneidercorp.com/ (search county + address) | R11: qPublic (Schneider) - blocks automated access
A12: HWSSGAXA | B12: 228 North Main Street | C12: Interesting | D12: Towns | E12: GA | F12: 34.951738 | G12: -83.758306 | H12: UNRESOLVED | Q12: https://qpublic.schneidercorp.com/ (search county + address) | R12: qPublic (Schneider) - blocks automated access
A13: BLVIGABW | B13: 40 River Road Connector | C13: Top Site | D13: Union | E13: GA | F13: 34.86402509999999 | G13: -83.984809 | H13: ok | I13: 4.2884 | J13: 186803 | K13: 17354.5 | N13: 071A 050 | Q13: https://services.arcgis.com/ISpzx3B5ZsVA6e1Z/ArcGIS/rest/services/Union_Parcels/FeatureServer/0
A14: LFYTGAXA | B14: 105 Cherokee Street | C14: Top Site | D14: Walker | E14: GA | F14: 34.70665254999999 | G14: -85.28274 | H14: UNRESOLVED | Q14: https://qpublic.schneidercorp.com/ (search county + address) | R14: qPublic (Schneider) - blocks automated access
A15: MONRGAXA | B15: 129 East Highland Avenue | C15: Interesting | D15: Walton | E15: GA | F15: 33.79645657999999 | G15: -83.712539 | H15: UNRESOLVED | Q15: https://qpublic.schneidercorp.com/ (search county + address) | R15: qPublic (Schneider) - blocks automated access
A16: MONRGAXB | B16: 3375 GA-11 | C16: Top Site | D16: Walton | E16: GA | F16: 33.89043801999999 | G16: -83.719923 | H16: UNRESOLVED | Q16: https://qpublic.schneidercorp.com/ (search county + address) | R16: qPublic (Schneider) - blocks automated access
A17: CLEVGAXA | B17: 158 West Kytle Street | C17: Top Site | D17: White | E17: GA | F17: 34.59702661999999 | G17: -83.766127 | H17: UNRESOLVED | Q17: https://qpublic.schneidercorp.com/ (search county + address) | R17: qPublic (Schneider) - blocks automated access
A18: DLTNGAXD | B18: 350 Cross Plains Blvd | C18: Top Site | D18: Whitfield | E18: GA | F18: 34.675055 | G18: -84.966388 | H18: ok | I18: 2.388 | J18: 104022 | K18: 9663.9 | L18: 5.01 | M18: totalacres | P18: CROSSPLAINS | Q18: https://gis.whitfieldcountyga.com/server/rest/services/Parcels_and_Development/MapServer/4
A19: ASLDKYXA | B19: 619 15th Street | C19: Interesting | D19: Boyd | E19: KY | F19: 38.47579999999999 | G19: -82.64385 | H19: UNRESOLVED | Q19: county PVA site / https://qpublic.schneidercorp.com/ | R19: KY PVA - no public service (state server hosts Webster Co only)
A20: MEDSKYXA | B20: 9216 Highway 60 | C20: Top Site | D20: Boyd | E20: KY | F20: 38.40964997000001 | G20: -82.713032 | H20: UNRESOLVED | Q20: county PVA site / https://qpublic.schneidercorp.com/ | R20: KY PVA - no public service (state server hosts Webster Co only)
A21: GNUPKYXA | B21: 304 Laurel St. | C21: Interesting | D21: Greenup | E21: KY | F21: 38.57342447000001 | G21: -82.839627 | H21: UNRESOLVED | Q21: county PVA site / https://qpublic.schneidercorp.com/ | R21: KY PVA - no public service (state server hosts Webster Co only)
A22: ABRDNCXA | B22: 211 North Poplar Street | C22: Top Site | D22: Moore | E22: NC | F22: 35.13471956000002 | G22: -79.426783 | H22: ok | I22: 1.3423 | J22: 58469 | K22: 5432 | L22: 1.338 | M22: CALC_ACRES | N22: 8.57013E+11 | P22: 2101 RIVERFRONT DR #A | Q22: https://services7.arcgis.com/WOKJvFrknOcT2chj/arcgis/rest/services/Accela_taxparcels/FeatureServer/0
A23: CHGVNCXA | B23: 1525 South Main Street | C23: Top Site | D23: Rowan | E23: NC | F23: 35.55692202999999 | G23: -80.595882 | H23: ok | I23: 0.4238 | J23: 18459 | K23: 1714.9 | L23: 0.42 | M23: DEEDACRE | N23: 163 012 | O23: KINETIC ABS NC LLC | P23: 1525 | Q23: https://gis.rowancountync.gov/arcgis/rest/services/Public/RowanTaxParcels/MapServer/0
A24: GRQYNCXA | B24: 8145 Highway 52 | C24: Interesting | D24: Rowan | E24: NC | F24: 35.572011 | G24: -80.417842 | H24: ok | I24: 1.2988 | J24: 56574 | K24: 5255.9 | L24: 1.3 | M24: CALCACRE | N24: 357 085 | O24: KINETIC ABS NC LLC | P24: 8145 | Q24: https://gis.rowancountync.gov/arcgis/rest/services/Public/RowanTaxParcels/MapServer/0
A25: ALBMNCXA | B25: 250 North 1st Street | C25: Top Site | D25: Stanly | E25: NC | F25: 35.35404215000001 | G25: -80.199092 | H25: ok | I25: 0.8423 | J25: 36691 | K25: 3408.7 | L25: 0.8399 | M25: ACRES | N25: 6.54801E+11 | O25: 1923 | P25: 250 N FIRST ST | Q25: https://services6.arcgis.com/w1igg0Q14weqYXUh/arcgis/rest/services/parcel_records_base_2/FeatureServer/3
